Workbook

Sheet Data
A1: Receipt No | B1: Completion Time | C1: Details | D1: Transaction Status | E1: Paid In | F1: Withdrawn | G1: Balance | I1: Total Money IN | J1: Total Money Out | K1: Net | L1: Category | N1: Category | O1: Money Out | P1: Money in | Q1: Investment | R1: Month | S1: Month | T1: Money Out | U1: Money In
A2: UABA93FB4E | B2: 46033.828 | C2: Customer Bundle Purchase to 826915Safaricom Offers by - 2547******109 NAOMI MUREITHI | D2: Completed | F2: 20 | G2: 2620 | I2: =SUM(F:F) -> 161561.22 | J2: =SUM(E:E) -> 165120.13 | K2: =I2-J2 -> -3558.91 | L2: =IF(ISNUMBER(SEARCH("Bundle",C2)),"Bundles",IF(ISNUMBER(SEARCH("Airtime",C2)),"Bundles",IF(ISNUMBER(SEARCH("Merchant",C2)),"Merchant Payment",IF(ISNUMBER(SEARCH("Offnet C2B",C2)),"Merchant Payment",IF(ISNUMBER(SEARCH("Offnet B2C",C2)),"Merchant Payment",IF(ISNUMBER(SEARCH("Customer Payment to Small",C2)),"Merchant Payment",IF(ISNUMBER(SEARCH("Payment to Small Business",C2)),"Merchant Payment",IF(ISNUMBER(SEARCH("Sent to",C2)),"Sent to Person",IF(ISNUMBER(SEARCH("Customer Transfer to",C2)),"Sent to Person",IF(ISNUMBER(SEARCH("Business Payment",C2)),"Money In",IF(ISNUMBER(SEARCH("Funds Received",C2)),"Money In",IF(ISNUMBER(SEARCH("Receive International",C2)),"Money In",IF(ISNUMBER(SEARCH("Send Money Reversal",C2)),"Money In",IF(ISNUMBER(SEARCH("Pay Utility Reversal",C2)),"Money In",IF(ISNUMBER(SEARCH("Customer Transfer",C2)),"Money In",IF(ISNUMBER(SEARCH("Ziidi",C2)),"Investment",IF(ISNUMBER(SEARCH("Nabo",C2)),"Investment",IF(ISNUMBER(SEARCH("Paybill Online",C2)),"Pay Bill",IF(ISNUMBER(SEARCH("Pay Bill",C2)),"Pay Bill",IF(ISNUMBER(SEARCH("Spotify",C2)),"Pay Bill",IF(ISNUMBER(SEARCH("M-Shwari",C2)),"Mshwari",IF(ISNUMBER(SEARCH("Mshwari",C2)),"Mshwari",IF(ISNUMBER(SEARCH("Withdrawal charge",C2)),"Fees",IF(ISNUMBER(SEARCH("Customer Withdrawal",C2)),"Fees",IF(ISNUMBER(SEARCH("charge",C2)),"Fees","Other"))))))))))))))))))))))))) -> Bundles | N2: Bundles | O2: =SUMIF(L:L,"Bundles",F:F) -> 11302 | R2: =TEXT(B2,"MMM YYYY") -> Jan 2026 | S2: 46023 | T2: =SUMIF(R:R,"Jan 2026",F:F) -> 21552 | U2: =SUMIF(R:R,"Jan 2026",E:E) -> 23948 | Z2: =SUM(E2:E10) -> 0
A3: UABA93HFN9 | B3: 46033.828 | C3: Customer Payment to Small Business to - 2541******638 LEAH WAMBUGU | D3: Completed | F3: 40 | G3: 2580 | K3: =I3-J3 -> 0 | L3: =IF(ISNUMBER(SEARCH("Bundle",C3)),"Bundles",IF(ISNUMBER(SEARCH("Airtime",C3)),"Bundles",IF(ISNUMBER(SEARCH("Merchant",C3)),"Merchant Payment",IF(ISNUMBER(SEARCH("Offnet C2B",C3)),"Merchant Payment",IF(ISNUMBER(SEARCH("Offnet B2C",C3)),"Merchant Payment",IF(ISNUMBER(SEARCH("Customer Payment to Small",C3)),"Merchant Payment",IF(ISNUMBER(SEARCH("Payment to Small Business",C3)),"Merchant Payment",IF(ISNUMBER(SEARCH("Sent to",C3)),"Sent to Person",IF(ISNUMBER(SEARCH("Customer Transfer to",C3)),"Sent to Person",IF(ISNUMBER(SEARCH("Business Payment",C3)),"Money In",IF(ISNUMBER(SEARCH("Funds Received",C3)),"Money In",IF(ISNUMBER(SEARCH("Receive International",C3)),"Money In",IF(ISNUMBER(SEARCH("Send Money Reversal",C3)),"Money In",IF(ISNUMBER(SEARCH("Pay Utility Reversal",C3)),"Money In",IF(ISNUMBER(SEARCH("Customer Transfer",C3)),"Money In",IF(ISNUMBER(SEARCH("Ziidi",C3)),"Investment",IF(ISNUMBER(SEARCH("Nabo",C3)),"Investment",IF(ISNUMBER(SEARCH("Paybill Online",C3)),"Pay Bill",IF(ISNUMBER(SEARCH("Pay Bill",C3)),"Pay Bill",IF(ISNUMBER(SEARCH("Spotify",C3)),"Pay Bill",IF(ISNUMBER(SEARCH("M-Shwari",C3)),"Mshwari",IF(ISNUMBER(SEARCH("Mshwari",C3)),"Mshwari",IF(ISNUMBER(SEARCH("Withdrawal charge",C3)),"Fees",IF(ISNUMBER(SEARCH("Customer Withdrawal",C3)),"Fees",IF(ISNUMBER(SEARCH("charge",C3)),"Fees","Other"))))))))))))))))))))))))) -> Merchant Payment | N3: Merchant Payment | O3: =SUMIF(L:L,"Merchant Payment",F:F) -> 36852 | R3: =TEXT(B2,"MMM YYYY") -> Jan 2026 | S3: 46054 | T3: =SUMIF(R:R,"Feb 2026",F:F) -> 47979 | U3: =SUMIF(R:R,"Feb 2026",E:E) -> 49631
A4: UABA93HFOK | B4: 2026-01-11 19:53:39 | C4: Customer Payment to Small Business to - 2547******122 SAMWEL OKUMBOH | D4: Completed | F4: 80 | G4: 2500 | L4: =IF(ISNUMBER(SEARCH("Bundle",C4)),"Bundles",IF(ISNUMBER(SEARCH("Airtime",C4)),"Bundles",IF(ISNUMBER(SEARCH("Merchant",C4)),"Merchant Payment",IF(ISNUMBER(SEARCH("Offnet C2B",C4)),"Merchant Payment",IF(ISNUMBER(SEARCH("Offnet B2C",C4)),"Merchant Payment",IF(ISNUMBER(SEARCH("Customer Payment to Small",C4)),"Merchant Payment",IF(ISNUMBER(SEARCH("Payment to Small Business",C4)),"Merchant Payment",IF(ISNUMBER(SEARCH("Sent to",C4)),"Sent to Person",IF(ISNUMBER(SEARCH("Customer Transfer to",C4)),"Sent to Person",IF(ISNUMBER(SEARCH("Business Payment",C4)),"Money In",IF(ISNUMBER(SEARCH("Funds Received",C4)),"Money In",IF(ISNUMBER(SEARCH("Receive International",C4)),"Money In",IF(ISNUMBER(SEARCH("Send Money Reversal",C4)),"Money In",IF(ISNUMBER(SEARCH("Pay Utility Reversal",C4)),"Money In",IF(ISNUMBER(SEARCH("Customer Transfer",C4)),"Money In",IF(ISNUMBER(SEARCH("Ziidi",C4)),"Investment",IF(ISNUMBER(SEARCH("Nabo",C4)),"Investment",IF(ISNUMBER(SEARCH("Paybill Online",C4)),"Pay Bill",IF(ISNUMBER(SEARCH("Pay Bill",C4)),"Pay Bill",IF(ISNUMBER(SEARCH("Spotify",C4)),"Pay Bill",IF(ISNUMBER(SEARCH("M-Shwari",C4)),"Mshwari",IF(ISNUMBER(SEARCH("Mshwari",C4)),"Mshwari",IF(ISNUMBER(SEARCH("Withdrawal charge",C4)),"Fees",IF(ISNUMBER(SEARCH("Customer Withdrawal",C4)),"Fees",IF(ISNUMBER(SEARCH("charge",C4)),"Fees","Other"))))))))))))))))))))))))) -> Merchant Payment | N4: Paybill | O4: =SUMIF(L:L,"Pay Bill",F:F) -> 16212 | R4: =TEXT(B2,"MMM YYYY") -> Jan 2026 | S4: 46082 | T4: =SUMIF(R:R,"Mar 2026",F:F) -> 35418.22 | U4: =SUMIF(R:R,"Mar 2026",E:E) -> 35435
A5: UACA93I2I5 | B5: 2026-01-12 07:15:58 | C5: Customer Bundle Purchase to 4093441SAFARICOM DATA BUNDLES by - 2547******109 NAOMI MUREITHI | D5: Completed | F5: 20 | G5: 2480 | L5: =IF(ISNUMBER(SEARCH("Bundle",C5)),"Bundles",IF(ISNUMBER(SEARCH("Airtime",C5)),"Bundles",IF(ISNUMBER(SEARCH("Merchant",C5)),"Merchant Payment",IF(ISNUMBER(SEARCH("Offnet C2B",C5)),"Merchant Payment",IF(ISNUMBER(SEARCH("Offnet B2C",C5)),"Merchant Payment",IF(ISNUMBER(SEARCH("Customer Payment to Small",C5)),"Merchant Payment",IF(ISNUMBER(SEARCH("Payment to Small Business",C5)),"Merchant Payment",IF(ISNUMBER(SEARCH("Sent to",C5)),"Sent to Person",IF(ISNUMBER(SEARCH("Customer Transfer to",C5)),"Sent to Person",IF(ISNUMBER(SEARCH("Business Payment",C5)),"Money In",IF(ISNUMBER(SEARCH("Funds Received",C5)),"Money In",IF(ISNUMBER(SEARCH("Receive International",C5)),"Money In",IF(ISNUMBER(SEARCH("Send Money Reversal",C5)),"Money In",IF(ISNUMBER(SEARCH("Pay Utility Reversal",C5)),"Money In",IF(ISNUMBER(SEARCH("Customer Transfer",C5)),"Money In",IF(ISNUMBER(SEARCH("Ziidi",C5)),"Investment",IF(ISNUMBER(SEARCH("Nabo",C5)),"Investment",IF(ISNUMBER(SEARCH("Paybill Online",C5)),"Pay Bill",IF(ISNUMBER(SEARCH("Pay Bill",C5)),"Pay Bill",IF(ISNUMBER(SEARCH("Spotify",C5)),"Pay Bill",IF(ISNUMBER(SEARCH("M-Shwari",C5)),"Mshwari",IF(ISNUMBER(SEARCH("Mshwari",C5)),"Mshwari",IF(ISNUMBER(SEARCH("Withdrawal charge",C5)),"Fees",IF(ISNUMBER(SEARCH("Customer Withdrawal",C5)),"Fees",IF(ISNUMBER(SEARCH("charge",C5)),"Fees","Other"))))))))))))))))))))))))) -> Bundles | N5: Money In | P5: =SUMIF(L:L,"Money In",E:E) -> 117178 | R5: =TEXT(B2,"MMM YYYY") -> Jan 2026 | S5: 46113 | T5: =SUMIF(R:R,"Apr 2026",F:F) -> 31669 | U5: =SUMIF(R:R,"Apr 2026",E:E) -> 31579
A6: UACA93IINZ | B6: 2026-01-12 09:27:39 | C6: Customer Bundle Purchase to 4093441SAFARICOM DATA BUNDLES by - 2547******109 NAOMI MUREITHI | D6: Completed | F6: 10 | G6: 2470 | L6: =IF(ISNUMBER(SEARCH("Bundle",C6)),"Bundles",IF(ISNUMBER(SEARCH("Airtime",C6)),"Bundles",IF(ISNUMBER(SEARCH("Merchant",C6)),"Merchant Payment",IF(ISNUMBER(SEARCH("Offnet C2B",C6)),"Merchant Payment",IF(ISNUMBER(SEARCH("Offnet B2C",C6)),"Merchant Payment",IF(ISNUMBER(SEARCH("Customer Payment to Small",C6)),"Merchant Payment",IF(ISNUMBER(SEARCH("Payment to Small Business",C6)),"Merchant Payment",IF(ISNUMBER(SEARCH("Sent to",C6)),"Sent to Person",IF(ISNUMBER(SEARCH("Customer Transfer to",C6)),"Sent to Person",IF(ISNUMBER(SEARCH("Business Payment",C6)),"Money In",IF(ISNUMBER(SEARCH("Funds Received",C6)),"Money In",IF(ISNUMBER(SEARCH("Receive International",C6)),"Money In",IF(ISNUMBER(SEARCH("Send Money Reversal",C6)),"Money In",IF(ISNUMBER(SEARCH("Pay Utility Reversal",C6)),"Money In",IF(ISNUMBER(SEARCH("Customer Transfer",C6)),"Money In",IF(ISNUMBER(SEARCH("Ziidi",C6)),"Investment",IF(ISNUMBER(SEARCH("Nabo",C6)),"Investment",IF(ISNUMBER(SEARCH("Paybill Online",C6)),"Pay Bill",IF(ISNUMBER(SEARCH("Pay Bill",C6)),"Pay Bill",IF(ISNUMBER(SEARCH("Spotify",C6)),"Pay Bill",IF(ISNUMBER(SEARCH("M-Shwari",C6)),"Mshwari",IF(ISNUMBER(SEARCH("Mshwari",C6)),"Mshwari",IF(ISNUMBER(SEARCH("Withdrawal charge",C6)),"Fees",IF(ISNUMBER(SEARCH("Customer Withdrawal",C6)),"Fees",IF(ISNUMBER(SEARCH("charge",C6)),"Fees","Other"))))))))))))))))))))))))) -> Bundles | N6: Fees | O6: =SUMIF(L:L,"Fees",F:F) -> 1780 | R6: =TEXT(B2,"MMM YYYY") -> Jan 2026 | S6: 46143 | T6: =SUMIF(R:R,"May 2026",F:F) -> 22867 | U6: =SUMIF(R:R,"May 2026",E:E) -> 23720
A7: UACA93IOER | B7: 2026-01-12 10:33:10 | C7: Customer Bundle Purchase to 4093441SAFARICOM DATA BUNDLES by - 2547******109 NAOMI MUREITHI | D7: Completed | F7: 10 | G7: 2460 | L7: =IF(ISNUMBER(SEARCH("Bundle",C7)),"Bundles",IF(ISNUMBER(SEARCH("Airtime",C7)),"Bundles",IF(ISNUMBER(SEARCH("Merchant",C7)),"Merchant Payment",IF(ISNUMBER(SEARCH("Offnet C2B",C7)),"Merchant Payment",IF(ISNUMBER(SEARCH("Offnet B2C",C7)),"Merchant Payment",IF(ISNUMBER(SEARCH("Customer Payment to Small",C7)),"Merchant Payment",IF(ISNUMBER(SEARCH("Payment to Small Business",C7)),"Merchant Payment",IF(ISNUMBER(SEARCH("Sent to",C7)),"Sent to Person",IF(ISNUMBER(SEARCH("Customer Transfer to",C7)),"Sent to Person",IF(ISNUMBER(SEARCH("Business Payment",C7)),"Money In",IF(ISNUMBER(SEARCH("Funds Received",C7)),"Money In",IF(ISNUMBER(SEARCH("Receive International",C7)),"Money In",IF(ISNUMBER(SEARCH("Send Money Reversal",C7)),"Money In",IF(ISNUMBER(SEARCH("Pay Utility Reversal",C7)),"Money In",IF(ISNUMBER(SEARCH("Customer Transfer",C7)),"Money In",IF(ISNUMBER(SEARCH("Ziidi",C7)),"Investment",IF(ISNUMBER(SEARCH("Nabo",C7)),"Investment",IF(ISNUMBER(SEARCH("Paybill Online",C7)),"Pay Bill",IF(ISNUMBER(SEARCH("Pay Bill",C7)),"Pay Bill",IF(ISNUMBER(SEARCH("Spotify",C7)),"Pay Bill",IF(ISNUMBER(SEARCH("M-Shwari",C7)),"Mshwari",IF(ISNUMBER(SEARCH("Mshwari",C7)),"Mshwari",IF(ISNUMBER(SEARCH("Withdrawal charge",C7)),"Fees",IF(ISNUMBER(SEARCH("Customer Withdrawal",C7)),"Fees",IF(ISNUMBER(SEARCH("charge",C7)),"Fees","Other"))))))))))))))))))))))))) -> Bundles | N7: Sent to Person | O7: =SUMIF(L:L,"Sent to Person",F:F) -> 25295 | R7: =TEXT(B2,"MMM YYYY") -> Jan 2026 | S7: Total | T7: =SUM(T2:T6) -> 159485.22 | U7: =SUM(U2:U6) -> 164313
A8: UACA93JEPJ | B8: 2026-01-12 13:56:16 | C8: Customer Bundle Purchase to 826915Safaricom Offers by - 2547******109 NAOMI MUREITHI | D8: Completed | F8: 20 | G8: 2440 | L8: =IF(ISNUMBER(SEARCH("Bundle",C8)),"Bundles",IF(ISNUMBER(SEARCH("Airtime",C8)),"Bundles",IF(ISNUMBER(SEARCH("Merchant",C8)),"Merchant Payment",IF(ISNUMBER(SEARCH("Offnet C2B",C8)),"Merchant Payment",IF(ISNUMBER(SEARCH("Offnet B2C",C8)),"Merchant Payment",IF(ISNUMBER(SEARCH("Customer Payment to Small",C8)),"Merchant Payment",IF(ISNUMBER(SEARCH("Payment to Small Business",C8)),"Merchant Payment",IF(ISNUMBER(SEARCH("Sent to",C8)),"Sent to Person",IF(ISNUMBER(SEARCH("Customer Transfer to",C8)),"Sent to Person",IF(ISNUMBER(SEARCH("Business Payment",C8)),"Money In",IF(ISNUMBER(SEARCH("Funds Received",C8)),"Money In",IF(ISNUMBER(SEARCH("Receive International",C8)),"Money In",IF(ISNUMBER(SEARCH("Send Money Reversal",C8)),"Money In",IF(ISNUMBER(SEARCH("Pay Utility Reversal",C8)),"Money In",IF(ISNUMBER(SEARCH("Customer Transfer",C8)),"Money In",IF(ISNUMBER(SEARCH("Ziidi",C8)),"Investment",IF(ISNUMBER(SEARCH("Nabo",C8)),"Investment",IF(ISNUMBER(SEARCH("Paybill Online",C8)),"Pay Bill",IF(ISNUMBER(SEARCH("Pay Bill",C8)),"Pay Bill",IF(ISNUMBER(SEARCH("Spotify",C8)),"Pay Bill",IF(ISNUMBER(SEARCH("M-Shwari",C8)),"Mshwari",IF(ISNUMBER(SEARCH("Mshwari",C8)),"Mshwari",IF(ISNUMBER(SEARCH("Withdrawal charge",C8)),"Fees",IF(ISNUMBER(SEARCH("Customer Withdrawal",C8)),"Fees",IF(ISNUMBER(SEARCH("charge",C8)),"Fees","Other"))))))))))))))))))))))))) -> Bundles | N8: M-Shwari | O8: =SUMIF(L:L,"Mshwari",F:F) -> 42300 | P8: =SUMIF(L:L,"Mshwari",E:E) -> 47895 | R8: =TEXT(B2,"MMM YYYY") -> Jan 2026
A9: UACA93JGAR | B9: 2026-01-12 13:59:22 | C9: Customer Bundle Purchase to 4093441SAFARICOM DATA BUNDLES by - 2547******109 NAOMI MUREITHI | D9: Completed | F9: 30 | G9: 2410 | L9: =IF(ISNUMBER(SEARCH("Bundle",C9)),"Bundles",IF(ISNUMBER(SEARCH("Airtime",C9)),"Bundles",IF(ISNUMBER(SEARCH("Merchant",C9)),"Merchant Payment",IF(ISNUMBER(SEARCH("Offnet C2B",C9)),"Merchant Payment",IF(ISNUMBER(SEARCH("Offnet B2C",C9)),"Merchant Payment",IF(ISNUMBER(SEARCH("Customer Payment to Small",C9)),"Merchant Payment",IF(ISNUMBER(SEARCH("Payment to Small Business",C9)),"Merchant Payment",IF(ISNUMBER(SEARCH("Sent to",C9)),"Sent to Person",IF(ISNUMBER(SEARCH("Customer Transfer to",C9)),"Sent to Person",IF(ISNUMBER(SEARCH("Business Payment",C9)),"Money In",IF(ISNUMBER(SEARCH("Funds Received",C9)),"Money In",IF(ISNUMBER(SEARCH("Receive International",C9)),"Money In",IF(ISNUMBER(SEARCH("Send Money Reversal",C9)),"Money In",IF(ISNUMBER(SEARCH("Pay Utility Reversal",C9)),"Money In",IF(ISNUMBER(SEARCH("Customer Transfer",C9)),"Money In",IF(ISNUMBER(SEARCH("Ziidi",C9)),"Investment",IF(ISNUMBER(SEARCH("Nabo",C9)),"Investment",IF(ISNUMBER(SEARCH("Paybill Online",C9)),"Pay Bill",IF(ISNUMBER(SEARCH("Pay Bill",C9)),"Pay Bill",IF(ISNUMBER(SEARCH("Spotify",C9)),"Pay Bill",IF(ISNUMBER(SEARCH("M-Shwari",C9)),"Mshwari",IF(ISNUMBER(SEARCH("Mshwari",C9)),"Mshwari",IF(ISNUMBER(SEARCH("Withdrawal charge",C9)),"Fees",IF(ISNUMBER(SEARCH("Customer Withdrawal",C9)),"Fees",IF(ISNUMBER(SEARCH("charge",C9)),"Fees","Other"))))))))))))))))))))))))) -> Bundles | N9: Investment | O9: Asset | Q9: 27313 | R9: =TEXT(B2,"MMM YYYY") -> Jan 2026
A10: UACA93K4N4 | B10: 2026-01-12 18:17:34 | C10: Merchant Payment to 6682492 - OBI BAKERY | D10: Completed | F10: 90 | G10: 2320 | L10: =IF(ISNUMBER(SEARCH("Bundle",C10)),"Bundles",IF(ISNUMBER(SEARCH("Airtime",C10)),"Bundles",IF(ISNUMBER(SEARCH("Merchant",C10)),"Merchant Payment",IF(ISNUMBER(SEARCH("Offnet C2B",C10)),"Merchant Payment",IF(ISNUMBER(SEARCH("Offnet B2C",C10)),"Merchant Payment",IF(ISNUMBER(SEARCH("Customer Payment to Small",C10)),"Merchant Payment",IF(ISNUMBER(SEARCH("Payment to Small Business",C10)),"Merchant Payment",IF(ISNUMBER(SEARCH("Sent to",C10)),"Sent to Person",IF(ISNUMBER(SEARCH("Customer Transfer to",C10)),"Sent to Person",IF(ISNUMBER(SEARCH("Business Payment",C10)),"Money In",IF(ISNUMBER(SEARCH("Funds Received",C10)),"Money In",IF(ISNUMBER(SEARCH("Receive International",C10)),"Money In",IF(ISNUMBER(SEARCH("Send Money Reversal",C10)),"Money In",IF(ISNUMBER(SEARCH("Pay Utility Reversal",C10)),"Money In",IF(ISNUMBER(SEARCH("Customer Transfer",C10)),"Money In",IF(ISNUMBER(SEARCH("Ziidi",C10)),"Investment",IF(ISNUMBER(SEARCH("Nabo",C10)),"Investment",IF(ISNUMBER(SEARCH("Paybill Online",C10)),"Pay Bill",IF(ISNUMBER(SEARCH("Pay Bill",C10)),"Pay Bill",IF(ISNUMBER(SEARCH("Spotify",C10)),"Pay Bill",IF(ISNUMBER(SEARCH("M-Shwari",C10)),"Mshwari",IF(ISNUMBER(SEARCH("Mshwari",C10)),"Mshwari",IF(ISNUMBER(SEARCH("Withdrawal charge",C10)),"Fees",IF(ISNUMBER(SEARCH("Customer Withdrawal",C10)),"Fees",IF(ISNUMBER(SEARCH("charge",C10)),"Fees","Other"))))))))))))))))))))))))) -> Merchant Payment | N10: Other | O10: =SUMIF(L:L,"Other",F:F) -> 0 | R10: =TEXT(B2,"MMM YYYY") -> Jan 2026
A11: UACA93K9LG | B11: 2026-01-12 18:20:35 | C11: Merchant Payment to 7327328 - Vincent Otieno | D11: Completed | F11: 100 | G11: 2220 | L11: =IF(ISNUMBER(SEARCH("Bundle",C11)),"Bundles",IF(ISNUMBER(SEARCH("Airtime",C11)),"Bundles",IF(ISNUMBER(SEARCH("Merchant",C11)),"Merchant Payment",IF(ISNUMBER(SEARCH("Offnet C2B",C11)),"Merchant Payment",IF(ISNUMBER(SEARCH("Offnet B2C",C11)),"Merchant Payment",IF(ISNUMBER(SEARCH("Customer Payment to Small",C11)),"Merchant Payment",IF(ISNUMBER(SEARCH("Payment to Small Business",C11)),"Merchant Payment",IF(ISNUMBER(SEARCH("Sent to",C11)),"Sent to Person",IF(ISNUMBER(SEARCH("Customer Transfer to",C11)),"Sent to Person",IF(ISNUMBER(SEARCH("Business Payment",C11)),"Money In",IF(ISNUMBER(SEARCH("Funds Received",C11)),"Money In",IF(ISNUMBER(SEARCH("Receive International",C11)),"Money In",IF(ISNUMBER(SEARCH("Send Money Reversal",C11)),"Money In",IF(ISNUMBER(SEARCH("Pay Utility Reversal",C11)),"Money In",IF(ISNUMBER(SEARCH("Customer Transfer",C11)),"Money In",IF(ISNUMBER(SEARCH("Ziidi",C11)),"Investment",IF(ISNUMBER(SEARCH("Nabo",C11)),"Investment",IF(ISNUMBER(SEARCH("Paybill Online",C11)),"Pay Bill",IF(ISNUMBER(SEARCH("Pay Bill",C11)),"Pay Bill",IF(ISNUMBER(SEARCH("Spotify",C11)),"Pay Bill",IF(ISNUMBER(SEARCH("M-Shwari",C11)),"Mshwari",IF(ISNUMBER(SEARCH("Mshwari",C11)),"Mshwari",IF(ISNUMBER(SEARCH("Withdrawal charge",C11)),"Fees",IF(ISNUMBER(SEARCH("Customer Withdrawal",C11)),"Fees",IF(ISNUMBER(SEARCH("charge",C11)),"Fees","Other"))))))))))))))))))))))))) -> Merchant Payment | N11: TOTAL | O11: =SUM(O2:O10) -> 133741 | P11: =SUM(P2:P9) -> 165073 | Q11: 27313 | R11: =TEXT(B2,"MMM YYYY") -> Jan 2026
A12: UACA93K8JX | B12: 2026-01-12 18:38:18 | C12: Customer Bundle Purchase to 4093441SAFARICOM DATA BUNDLES by - 2547******109 NAOMI MUREITHI | D12: Completed | F12: 10 | G12: 2210 | L12: =IF(ISNUMBER(SEARCH("Bundle",C12)),"Bundles",IF(ISNUMBER(SEARCH("Airtime",C12)),"Bundles",IF(ISNUMBER(SEARCH("Merchant",C12)),"Merchant Payment",IF(ISNUMBER(SEARCH("Offnet C2B",C12)),"Merchant Payment",IF(ISNUMBER(SEARCH("Offnet B2C",C12)),"Merchant Payment",IF(ISNUMBER(SEARCH("Customer Payment to Small",C12)),"Merchant Payment",IF(ISNUMBER(SEARCH("Payment to Small Business",C12)),"Merchant Payment",IF(ISNUMBER(SEARCH("Sent to",C12)),"Sent to Person",IF(ISNUMBER(SEARCH("Customer Transfer to",C12)),"Sent to Person",IF(ISNUMBER(SEARCH("Business Payment",C12)),"Money In",IF(ISNUMBER(SEARCH("Funds Received",C12)),"Money In",IF(ISNUMBER(SEARCH("Receive International",C12)),"Money In",IF(ISNUMBER(SEARCH("Send Money Reversal",C12)),"Money In",IF(ISNUMBER(SEARCH("Pay Utility Reversal",C12)),"Money In",IF(ISNUMBER(SEARCH("Customer Transfer",C12)),"Money In",IF(ISNUMBER(SEARCH("Ziidi",C12)),"Investment",IF(ISNUMBER(SEARCH("Nabo",C12)),"Investment",IF(ISNUMBER(SEARCH("Paybill Online",C12)),"Pay Bill",IF(ISNUMBER(SEARCH("Pay Bill",C12)),"Pay Bill",IF(ISNUMBER(SEARCH("Spotify",C12)),"Pay Bill",IF(ISNUMBER(SEARCH("M-Shwari",C12)),"Mshwari",IF(ISNUMBER(SEARCH("Mshwari",C12)),"Mshwari",IF(ISNUMBER(SEARCH("Withdrawal charge",C12)),"Fees",IF(ISNUMBER(SEARCH("Customer Withdrawal",C12)),"Fees",IF(ISNUMBER(SEARCH("charge",C12)),"Fees","Other"))))))))))))))))))))))))) -> Bundles | R12: =TEXT(B2,"MMM YYYY") -> Jan 2026
A13: UACA93KYWH | B13: 2026-01-12 20:51:15 | C13: Customer Bundle Purchase to 4093441SAFARICOM DATA BUNDLES by - 2547******109 NAOMI MUREITHI | D13: Completed | F13: 30 | G13: 2180 | L13: =IF(ISNUMBER(SEARCH("Bundle",C13)),"Bundles",IF(ISNUMBER(SEARCH("Airtime",C13)),"Bundles",IF(ISNUMBER(SEARCH("Merchant",C13)),"Merchant Payment",IF(ISNUMBER(SEARCH("Offnet C2B",C13)),"Merchant Payment",IF(ISNUMBER(SEARCH("Offnet B2C",C13)),"Merchant Payment",IF(ISNUMBER(SEARCH("Customer Payment to Small",C13)),"Merchant Payment",IF(ISNUMBER(SEARCH("Payment to Small Business",C13)),"Merchant Payment",IF(ISNUMBER(SEARCH("Sent to",C13)),"Sent to Person",IF(ISNUMBER(SEARCH("Customer Transfer to",C13)),"Sent to Person",IF(ISNUMBER(SEARCH("Business Payment",C13)),"Money In",IF(ISNUMBER(SEARCH("Funds Received",C13)),"Money In",IF(ISNUMBER(SEARCH("Receive International",C13)),"Money In",IF(ISNUMBER(SEARCH("Send Money Reversal",C13)),"Money In",IF(ISNUMBER(SEARCH("Pay Utility Reversal",C13)),"Money In",IF(ISNUMBER(SEARCH("Customer Transfer",C13)),"Money In",IF(ISNUMBER(SEARCH("Ziidi",C13)),"Investment",IF(ISNUMBER(SEARCH("Nabo",C13)),"Investment",IF(ISNUMBER(SEARCH("Paybill Online",C13)),"Pay Bill",IF(ISNUMBER(SEARCH("Pay Bill",C13)),"Pay Bill",IF(ISNUMBER(SEARCH("Spotify",C13)),"Pay Bill",IF(ISNUMBER(SEARCH("M-Shwari",C13)),"Mshwari",IF(ISNUMBER(SEARCH("Mshwari",C13)),"Mshwari",IF(ISNUMBER(SEARCH("Withdrawal charge",C13)),"Fees",IF(ISNUMBER(SEARCH("Customer Withdrawal",C13)),"Fees",IF(ISNUMBER(SEARCH("charge",C13)),"Fees","Other"))))))))))))))))))))))))) -> Bundles | R13: =TEXT(B2,"MMM YYYY") -> Jan 2026
A14: UADA93LBQE | B14: 2026-01-13 03:14:01 | C14: Merchant Payment to 7225027 - NAKURU DRIVE INN HOTEL | D14: Completed | F14: 80 | G14: 2100 | L14: =IF(ISNUMBER(SEARCH("Bundle",C14)),"Bundles",IF(ISNUMBER(SEARCH("Airtime",C14)),"Bundles",IF(ISNUMBER(SEARCH("Merchant",C14)),"Merchant Payment",IF(ISNUMBER(SEARCH("Offnet C2B",C14)),"Merchant Payment",IF(ISNUMBER(SEARCH("Offnet B2C",C14)),"Merchant Payment",IF(ISNUMBER(SEARCH("Customer Payment to Small",C14)),"Merchant Payment",IF(ISNUMBER(SEARCH("Payment to Small Business",C14)),"Merchant Payment",IF(ISNUMBER(SEARCH("Sent to",C14)),"Sent to Person",IF(ISNUMBER(SEARCH("Customer Transfer to",C14)),"Sent to Person",IF(ISNUMBER(SEARCH("Business Payment",C14)),"Money In",IF(ISNUMBER(SEARCH("Funds Received",C14)),"Money In",IF(ISNUMBER(SEARCH("Receive International",C14)),"Money In",IF(ISNUMBER(SEARCH("Send Money Reversal",C14)),"Money In",IF(ISNUMBER(SEARCH("Pay Utility Reversal",C14)),"Money In",IF(ISNUMBER(SEARCH("Customer Transfer",C14)),"Money In",IF(ISNUMBER(SEARCH("Ziidi",C14)),"Investment",IF(ISNUMBER(SEARCH("Nabo",C14)),"Investment",IF(ISNUMBER(SEARCH("Paybill Online",C14)),"Pay Bill",IF(ISNUMBER(SEARCH("Pay Bill",C14)),"Pay Bill",IF(ISNUMBER(SEARCH("Spotify",C14)),"Pay Bill",IF(ISNUMBER(SEARCH("M-Shwari",C14)),"Mshwari",IF(ISNUMBER(SEARCH("Mshwari",C14)),"Mshwari",IF(ISNUMBER(SEARCH("Withdrawal charge",C14)),"Fees",IF(ISNUMBER(SEARCH("Customer Withdrawal",C14)),"Fees",IF(ISNUMBER(SEARCH("charge",C14)),"Fees","Other"))))))))))))))))))))))))) -> Merchant Payment | R14: =TEXT(B2,"MMM YYYY") -> Jan 2026
A15: UADA93LRMF | B15: 2026-01-13 08:45:54 | C15: Customer Bundle Purchase to 4093441SAFARICOM DATA BUNDLES by - 2547******109 NAOMI MUREITHI | D15: Completed | F15: 10 | G15: 2090 | L15: =IF(ISNUMBER(SEARCH("Bundle",C15)),"Bundles",IF(ISNUMBER(SEARCH("Airtime",C15)),"Bundles",IF(ISNUMBER(SEARCH("Merchant",C15)),"Merchant Payment",IF(ISNUMBER(SEARCH("Offnet C2B",C15)),"Merchant Payment",IF(ISNUMBER(SEARCH("Offnet B2C",C15)),"Merchant Payment",IF(ISNUMBER(SEARCH("Customer Payment to Small",C15)),"Merchant Payment",IF(ISNUMBER(SEARCH("Payment to Small Business",C15)),"Merchant Payment",IF(ISNUMBER(SEARCH("Sent to",C15)),"Sent to Person",IF(ISNUMBER(SEARCH("Customer Transfer to",C15)),"Sent to Person",IF(ISNUMBER(SEARCH("Business Payment",C15)),"Money In",IF(ISNUMBER(SEARCH("Funds Received",C15)),"Money In",IF(ISNUMBER(SEARCH("Receive International",C15)),"Money In",IF(ISNUMBER(SEARCH("Send Money Reversal",C15)),"Money In",IF(ISNUMBER(SEARCH("Pay Utility Reversal",C15)),"Money In",IF(ISNUMBER(SEARCH("Customer Transfer",C15)),"Money In",IF(ISNUMBER(SEARCH("Ziidi",C15)),"Investment",IF(ISNUMBER(SEARCH("Nabo",C15)),"Investment",IF(ISNUMBER(SEARCH("Paybill Online",C15)),"Pay Bill",IF(ISNUMBER(SEARCH("Pay Bill",C15)),"Pay Bill",IF(ISNUMBER(SEARCH("Spotify",C15)),"Pay Bill",IF(ISNUMBER(SEARCH("M-Shwari",C15)),"Mshwari",IF(ISNUMBER(SEARCH("Mshwari",C15)),"Mshwari",IF(ISNUMBER(SEARCH("Withdrawal charge",C15)),"Fees",IF(ISNUMBER(SEARCH("Customer Withdrawal",C15)),"Fees",IF(ISNUMBER(SEARCH("charge",C15)),"Fees","Other"))))))))))))))))))))))))) -> Bundles | R15: =TEXT(B2,"MMM YYYY") -> Jan 2026
A16: UADA93LQ7A | B16: 2026-01-13 08:47:08 | C16: Customer Bundle Purchase to 826915Safaricom Offers by - 2547******109 NAOMI MUREITHI | D16: Completed | F16: 10 | G16: 2080 | L16: =IF(ISNUMBER(SEARCH("Bundle",C16)),"Bundles",IF(ISNUMBER(SEARCH("Airtime",C16)),"Bundles",IF(ISNUMBER(SEARCH("Merchant",C16)),"Merchant Payment",IF(ISNUMBER(SEARCH("Offnet C2B",C16)),"Merchant Payment",IF(ISNUMBER(SEARCH("Offnet B2C",C16)),"Merchant Payment",IF(ISNUMBER(SEARCH("Customer Payment to Small",C16)),"Merchant Payment",IF(ISNUMBER(SEARCH("Payment to Small Business",C16)),"Merchant Payment",IF(ISNUMBER(SEARCH("Sent to",C16)),"Sent to Person",IF(ISNUMBER(SEARCH("Customer Transfer to",C16)),"Sent to Person",IF(ISNUMBER(SEARCH("Business Payment",C16)),"Money In",IF(ISNUMBER(SEARCH("Funds Received",C16)),"Money In",IF(ISNUMBER(SEARCH("Receive International",C16)),"Money In",IF(ISNUMBER(SEARCH("Send Money Reversal",C16)),"Money In",IF(ISNUMBER(SEARCH("Pay Utility Reversal",C16)),"Money In",IF(ISNUMBER(SEARCH("Customer Transfer",C16)),"Money In",IF(ISNUMBER(SEARCH("Ziidi",C16)),"Investment",IF(ISNUMBER(SEARCH("Nabo",C16)),"Investment",IF(ISNUMBER(SEARCH("Paybill Online",C16)),"Pay Bill",IF(ISNUMBER(SEARCH("Pay Bill",C16)),"Pay Bill",IF(ISNUMBER(SEARCH("Spotify",C16)),"Pay Bill",IF(ISNUMBER(SEARCH("M-Shwari",C16)),"Mshwari",IF(ISNUMBER(SEARCH("Mshwari",C16)),"Mshwari",IF(ISNUMBER(SEARCH("Withdrawal charge",C16)),"Fees",IF(ISNUMBER(SEARCH("Customer Withdrawal",C16)),"Fees",IF(ISNUMBER(SEARCH("charge",C16)),"Fees","Other"))))))))))))))))))))))))) -> Bundles | R16: =TEXT(B2,"MMM YYYY") -> Jan 2026
A17: UADA93MUBH | B17: 2026-01-13 14:27:42 | C17: Customer Bundle Purchase to 4093441SAFARICOM DATA BUNDLES by - 2547******109 NAOMI MUREITHI | D17: Completed | F17: 10 | G17: 2070 | L17: =IF(ISNUMBER(SEARCH("Bundle",C17)),"Bundles",IF(ISNUMBER(SEARCH("Airtime",C17)),"Bundles",IF(ISNUMBER(SEARCH("Merchant",C17)),"Merchant Payment",IF(ISNUMBER(SEARCH("Offnet C2B",C17)),"Merchant Payment",IF(ISNUMBER(SEARCH("Offnet B2C",C17)),"Merchant Payment",IF(ISNUMBER(SEARCH("Customer Payment to Small",C17)),"Merchant Payment",IF(ISNUMBER(SEARCH("Payment to Small Business",C17)),"Merchant Payment",IF(ISNUMBER(SEARCH("Sent to",C17)),"Sent to Person",IF(ISNUMBER(SEARCH("Customer Transfer to",C17)),"Sent to Person",IF(ISNUMBER(SEARCH("Business Payment",C17)),"Money In",IF(ISNUMBER(SEARCH("Funds Received",C17)),"Money In",IF(ISNUMBER(SEARCH("Receive International",C17)),"Money In",IF(ISNUMBER(SEARCH("Send Money Reversal",C17)),"Money In",IF(ISNUMBER(SEARCH("Pay Utility Reversal",C17)),"Money In",IF(ISNUMBER(SEARCH("Customer Transfer",C17)),"Money In",IF(ISNUMBER(SEARCH("Ziidi",C17)),"Investment",IF(ISNUMBER(SEARCH("Nabo",C17)),"Investment",IF(ISNUMBER(SEARCH("Paybill Online",C17)),"Pay Bill",IF(ISNUMBER(SEARCH("Pay Bill",C17)),"Pay Bill",IF(ISNUMBER(SEARCH("Spotify",C17)),"Pay Bill",IF(ISNUMBER(SEARCH("M-Shwari",C17)),"Mshwari",IF(ISNUMBER(SEARCH("Mshwari",C17)),"Mshwari",IF(ISNUMBER(SEARCH("Withdrawal charge",C17)),"Fees",IF(ISNUMBER(SEARCH("Customer Withdrawal",C17)),"Fees",IF(ISNUMBER(SEARCH("charge",C17)),"Fees","Other"))))))))))))))))))))))))) -> Bundles | R17: =TEXT(B2,"MMM YYYY") -> Jan 2026
A18: UADA93NAPT | B18: 2026-01-13 18:03:09 | C18: Customer Bundle Purchase to 4093441SAFARICOM DATA BUNDLES by - 2547******109 NAOMI MUREITHI | D18: Completed | F18: 10 | G18: 2060 | L18: =IF(ISNUMBER(SEARCH("Bundle",C18)),"Bundles",IF(ISNUMBER(SEARCH("Airtime",C18)),"Bundles",IF(ISNUMBER(SEARCH("Merchant",C18)),"Merchant Payment",IF(ISNUMBER(SEARCH("Offnet C2B",C18)),"Merchant Payment",IF(ISNUMBER(SEARCH("Offnet B2C",C18)),"Merchant Payment",IF(ISNUMBER(SEARCH("Customer Payment to Small",C18)),"Merchant Payment",IF(ISNUMBER(SEARCH("Payment to Small Business",C18)),"Merchant Payment",IF(ISNUMBER(SEARCH("Sent to",C18)),"Sent to Person",IF(ISNUMBER(SEARCH("Customer Transfer to",C18)),"Sent to Person",IF(ISNUMBER(SEARCH("Business Payment",C18)),"Money In",IF(ISNUMBER(SEARCH("Funds Received",C18)),"Money In",IF(ISNUMBER(SEARCH("Receive International",C18)),"Money In",IF(ISNUMBER(SEARCH("Send Money Reversal",C18)),"Money In",IF(ISNUMBER(SEARCH("Pay Utility Reversal",C18)),"Money In",IF(ISNUMBER(SEARCH("Customer Transfer",C18)),"Money In",IF(ISNUMBER(SEARCH("Ziidi",C18)),"Investment",IF(ISNUMBER(SEARCH("Nabo",C18)),"Investment",IF(ISNUMBER(SEARCH("Paybill Online",C18)),"Pay Bill",IF(ISNUMBER(SEARCH("Pay Bill",C18)),"Pay Bill",IF(ISNUMBER(SEARCH("Spotify",C18)),"Pay Bill",IF(ISNUMBER(SEARCH("M-Shwari",C18)),"Mshwari",IF(ISNUMBER(SEARCH("Mshwari",C18)),"Mshwari",IF(ISNUMBER(SEARCH("Withdrawal charge",C18)),"Fees",IF(ISNUMBER(SEARCH("Customer Withdrawal",C18)),"Fees",IF(ISNUMBER(SEARCH("charge",C18)),"Fees","Other"))))))))))))))))))))))))) -> Bundles | R18: =TEXT(B2,"MMM YYYY") -> Jan 2026
A19: UADA93NSWI | B19: 2026-01-13 19:47:14 | C19: Customer Bundle Purchase to 4093441SAFARICOM DATA BUNDLES by - 2547******109 NAOMI MUREITHI | D19: Completed | F19: 10 | G19: 2050 | L19: =IF(ISNUMBER(SEARCH("Bundle",C19)),"Bundles",IF(ISNUMBER(SEARCH("Airtime",C19)),"Bundles",IF(ISNUMBER(SEARCH("Merchant",C19)),"Merchant Payment",IF(ISNUMBER(SEARCH("Offnet C2B",C19)),"Merchant Payment",IF(ISNUMBER(SEARCH("Offnet B2C",C19)),"Merchant Payment",IF(ISNUMBER(SEARCH("Customer Payment to Small",C19)),"Merchant Payment",IF(ISNUMBER(SEARCH("Payment to Small Business",C19)),"Merchant Payment",IF(ISNUMBER(SEARCH("Sent to",C19)),"Sent to Person",IF(ISNUMBER(SEARCH("Customer Transfer to",C19)),"Sent to Person",IF(ISNUMBER(SEARCH("Business Payment",C19)),"Money In",IF(ISNUMBER(SEARCH("Funds Received",C19)),"Money In",IF(ISNUMBER(SEARCH("Receive International",C19)),"Money In",IF(ISNUMBER(SEARCH("Send Money Reversal",C19)),"Money In",IF(ISNUMBER(SEARCH("Pay Utility Reversal",C19)),"Money In",IF(ISNUMBER(SEARCH("Customer Transfer",C19)),"Money In",IF(ISNUMBER(SEARCH("Ziidi",C19)),"Investment",IF(ISNUMBER(SEARCH("Nabo",C19)),"Investment",IF(ISNUMBER(SEARCH("Paybill Online",C19)),"Pay Bill",IF(ISNUMBER(SEARCH("Pay Bill",C19)),"Pay Bill",IF(ISNUMBER(SEARCH("Spotify",C19)),"Pay Bill",IF(ISNUMBER(SEARCH("M-Shwari",C19)),"Mshwari",IF(ISNUMBER(SEARCH("Mshwari",C19)),"Mshwari",IF(ISNUMBER(SEARCH("Withdrawal charge",C19)),"Fees",IF(ISNUMBER(SEARCH("Customer Withdrawal",C19)),"Fees",IF(ISNUMBER(SEARCH("charge",C19)),"Fees","Other"))))))))))))))))))))))))) -> Bundles | R19: =TEXT(B2,"MMM YYYY") -> Jan 2026
A20: UAEA93OZUW | B20: 2026-01-14 09:08:44 | C20: Customer Bundle Purchase to 4093441SAFARICOM DATA BUNDLES by - 2547******109 NAOMI MUREITHI | D20: Completed | F20: 10 | G20: 2040 | L20: =IF(ISNUMBER(SEARCH("Bundle",C20)),"Bundles",IF(ISNUMBER(SEARCH("Airtime",C20)),"Bundles",IF(ISNUMBER(SEARCH("Merchant",C20)),"Merchant Payment",IF(ISNUMBER(SEARCH("Offnet C2B",C20)),"Merchant Payment",IF(ISNUMBER(SEARCH("Offnet B2C",C20)),"Merchant Payment",IF(ISNUMBER(SEARCH("Customer Payment to Small",C20)),"Merchant Payment",IF(ISNUMBER(SEARCH("Payment to Small Business",C20)),"Merchant Payment",IF(ISNUMBER(SEARCH("Sent to",C20)),"Sent to Person",IF(ISNUMBER(SEARCH("Customer Transfer to",C20)),"Sent to Person",IF(ISNUMBER(SEARCH("Business Payment",C20)),"Money In",IF(ISNUMBER(SEARCH("Funds Received",C20)),"Money In",IF(ISNUMBER(SEARCH("Receive International",C20)),"Money In",IF(ISNUMBER(SEARCH("Send Money Reversal",C20)),"Money In",IF(ISNUMBER(SEARCH("Pay Utility Reversal",C20)),"Money In",IF(ISNUMBER(SEARCH("Customer Transfer",C20)),"Money In",IF(ISNUMBER(SEARCH("Ziidi",C20)),"Investment",IF(ISNUMBER(SEARCH("Nabo",C20)),"Investment",IF(ISNUMBER(SEARCH("Paybill Online",C20)),"Pay Bill",IF(ISNUMBER(SEARCH("Pay Bill",C20)),"Pay Bill",IF(ISNUMBER(SEARCH("Spotify",C20)),"Pay Bill",IF(ISNUMBER(SEARCH("M-Shwari",C20)),"Mshwari",IF(ISNUMBER(SEARCH("Mshwari",C20)),"Mshwari",IF(ISNUMBER(SEARCH("Withdrawal charge",C20)),"Fees",IF(ISNUMBER(SEARCH("Customer Withdrawal",C20)),"Fees",IF(ISNUMBER(SEARCH("charge",C20)),"Fees","Other"))))))))))))))))))))))))) -> Bundles | R20: =TEXT(B2,"MMM YYYY") -> Jan 2026
A21: UAEA93PEPB | B21: 2026-01-14 10:27:47 | C21: Customer Bundle Purchase to 4093441SAFARICOM DATA BUNDLES by - 2547******109 NAOMI MUREITHI | D21: Completed | F21: 30 | G21: 2010 | L21: =IF(ISNUMBER(SEARCH("Bundle",C21)),"Bundles",IF(ISNUMBER(SEARCH("Airtime",C21)),"Bundles",IF(ISNUMBER(SEARCH("Merchant",C21)),"Merchant Payment",IF(ISNUMBER(SEARCH("Offnet C2B",C21)),"Merchant Payment",IF(ISNUMBER(SEARCH("Offnet B2C",C21)),"Merchant Payment",IF(ISNUMBER(SEARCH("Customer Payment to Small",C21)),"Merchant Payment",IF(ISNUMBER(SEARCH("Payment to Small Business",C21)),"Merchant Payment",IF(ISNUMBER(SEARCH("Sent to",C21)),"Sent to Person",IF(ISNUMBER(SEARCH("Customer Transfer to",C21)),"Sent to Person",IF(ISNUMBER(SEARCH("Business Payment",C21)),"Money In",IF(ISNUMBER(SEARCH("Funds Received",C21)),"Money In",IF(ISNUMBER(SEARCH("Receive International",C21)),"Money In",IF(ISNUMBER(SEARCH("Send Money Reversal",C21)),"Money In",IF(ISNUMBER(SEARCH("Pay Utility Reversal",C21)),"Money In",IF(ISNUMBER(SEARCH("Customer Transfer",C21)),"Money In",IF(ISNUMBER(SEARCH("Ziidi",C21)),"Investment",IF(ISNUMBER(SEARCH("Nabo",C21)),"Investment",IF(ISNUMBER(SEARCH("Paybill Online",C21)),"Pay Bill",IF(ISNUMBER(SEARCH("Pay Bill",C21)),"Pay Bill",IF(ISNUMBER(SEARCH("Spotify",C21)),"Pay Bill",IF(ISNUMBER(SEARCH("M-Shwari",C21)),"Mshwari",IF(ISNUMBER(SEARCH("Mshwari",C21)),"Mshwari",IF(ISNUMBER(SEARCH("Withdrawal charge",C21)),"Fees",IF(ISNUMBER(SEARCH("Customer Withdrawal",C21)),"Fees",IF(ISNUMBER(SEARCH("charge",C21)),"Fees","Other"))))))))))))))))))))))))) -> Bundles | R21: =TEXT(B2,"MMM YYYY") -> Jan 2026
A22: UAEA93R22B | B22: 2026-01-14 19:14:37 | C22: Customer Bundle Purchase to 4093441SAFARICOM DATA BUNDLES by - 2547******109 NAOMI MUREITHI | D22: Completed | F22: 30 | G22: 1980 | L22: =IF(ISNUMBER(SEARCH("Bundle",C22)),"Bundles",IF(ISNUMBER(SEARCH("Airtime",C22)),"Bundles",IF(ISNUMBER(SEARCH("Merchant",C22)),"Merchant Payment",IF(ISNUMBER(SEARCH("Offnet C2B",C22)),"Merchant Payment",IF(ISNUMBER(SEARCH("Offnet B2C",C22)),"Merchant Payment",IF(ISNUMBER(SEARCH("Customer Payment to Small",C22)),"Merchant Payment",IF(ISNUMBER(SEARCH("Payment to Small Business",C22)),"Merchant Payment",IF(ISNUMBER(SEARCH("Sent to",C22)),"Sent to Person",IF(ISNUMBER(SEARCH("Customer Transfer to",C22)),"Sent to Person",IF(ISNUMBER(SEARCH("Business Payment",C22)),"Money In",IF(ISNUMBER(SEARCH("Funds Received",C22)),"Money In",IF(ISNUMBER(SEARCH("Receive International",C22)),"Money In",IF(ISNUMBER(SEARCH("Send Money Reversal",C22)),"Money In",IF(ISNUMBER(SEARCH("Pay Utility Reversal",C22)),"Money In",IF(ISNUMBER(SEARCH("Customer Transfer",C22)),"Money In",IF(ISNUMBER(SEARCH("Ziidi",C22)),"Investment",IF(ISNUMBER(SEARCH("Nabo",C22)),"Investment",IF(ISNUMBER(SEARCH("Paybill Online",C22)),"Pay Bill",IF(ISNUMBER(SEARCH("Pay Bill",C22)),"Pay Bill",IF(ISNUMBER(SEARCH("Spotify",C22)),"Pay Bill",IF(ISNUMBER(SEARCH("M-Shwari",C22)),"Mshwari",IF(ISNUMBER(SEARCH("Mshwari",C22)),"Mshwari",IF(ISNUMBER(SEARCH("Withdrawal charge",C22)),"Fees",IF(ISNUMBER(SEARCH("Customer Withdrawal",C22)),"Fees",IF(ISNUMBER(SEARCH("charge",C22)),"Fees","Other"))))))))))))))))))))))))) -> Bundles | R22: =TEXT(B2,"MMM YYYY") -> Jan 2026
A23: UAFA93SXMQ | B23: 2026-01-15 12:07:00 | C23: Customer Bundle Purchase to 4093441SAFARICOM DATA BUNDLES by - 2547******109 NAOMI MUREITHI | D23: Completed | F23: 30 | G23: 1950 | L23: =IF(ISNUMBER(SEARCH("Bundle",C23)),"Bundles",IF(ISNUMBER(SEARCH("Airtime",C23)),"Bundles",IF(ISNUMBER(SEARCH("Merchant",C23)),"Merchant Payment",IF(ISNUMBER(SEARCH("Offnet C2B",C23)),"Merchant Payment",IF(ISNUMBER(SEARCH("Offnet B2C",C23)),"Merchant Payment",IF(ISNUMBER(SEARCH("Customer Payment to Small",C23)),"Merchant Payment",IF(ISNUMBER(SEARCH("Payment to Small Business",C23)),"Merchant Payment",IF(ISNUMBER(SEARCH("Sent to",C23)),"Sent to Person",IF(ISNUMBER(SEARCH("Customer Transfer to",C23)),"Sent to Person",IF(ISNUMBER(SEARCH("Business Payment",C23)),"Money In",IF(ISNUMBER(SEARCH("Funds Received",C23)),"Money In",IF(ISNUMBER(SEARCH("Receive International",C23)),"Money In",IF(ISNUMBER(SEARCH("Send Money Reversal",C23)),"Money In",IF(ISNUMBER(SEARCH("Pay Utility Reversal",C23)),"Money In",IF(ISNUMBER(SEARCH("Customer Transfer",C23)),"Money In",IF(ISNUMBER(SEARCH("Ziidi",C23)),"Investment",IF(ISNUMBER(SEARCH("Nabo",C23)),"Investment",IF(ISNUMBER(SEARCH("Paybill Online",C23)),"Pay Bill",IF(ISNUMBER(SEARCH("Pay Bill",C23)),"Pay Bill",IF(ISNUMBER(SEARCH("Spotify",C23)),"Pay Bill",IF(ISNUMBER(SEARCH("M-Shwari",C23)),"Mshwari",IF(ISNUMBER(SEARCH("Mshwari",C23)),"Mshwari",IF(ISNUMBER(SEARCH("Withdrawal charge",C23)),"Fees",IF(ISNUMBER(SEARCH("Customer Withdrawal",C23)),"Fees",IF(ISNUMBER(SEARCH("charge",C23)),"Fees","Other"))))))))))))))))))))))))) -> Bundles | R23: =TEXT(B2,"MMM YYYY") -> Jan 2026
A24: UAFA93TILA | B24: 2026-01-15 16:08:20 | C24: Customer Bundle Purchase to 4093441SAFARICOM DATA BUNDLES by - 2547******109 NAOMI MUREITHI | D24: Completed | F24: 30 | G24: 1920 | L24: =IF(ISNUMBER(SEARCH("Bundle",C24)),"Bundles",IF(ISNUMBER(SEARCH("Airtime",C24)),"Bundles",IF(ISNUMBER(SEARCH("Merchant",C24)),"Merchant Payment",IF(ISNUMBER(SEARCH("Offnet C2B",C24)),"Merchant Payment",IF(ISNUMBER(SEARCH("Offnet B2C",C24)),"Merchant Payment",IF(ISNUMBER(SEARCH("Customer Payment to Small",C24)),"Merchant Payment",IF(ISNUMBER(SEARCH("Payment to Small Business",C24)),"Merchant Payment",IF(ISNUMBER(SEARCH("Sent to",C24)),"Sent to Person",IF(ISNUMBER(SEARCH("Customer Transfer to",C24)),"Sent to Person",IF(ISNUMBER(SEARCH("Business Payment",C24)),"Money In",IF(ISNUMBER(SEARCH("Funds Received",C24)),"Money In",IF(ISNUMBER(SEARCH("Receive International",C24)),"Money In",IF(ISNUMBER(SEARCH("Send Money Reversal",C24)),"Money In",IF(ISNUMBER(SEARCH("Pay Utility Reversal",C24)),"Money In",IF(ISNUMBER(SEARCH("Customer Transfer",C24)),"Money In",IF(ISNUMBER(SEARCH("Ziidi",C24)),"Investment",IF(ISNUMBER(SEARCH("Nabo",C24)),"Investment",IF(ISNUMBER(SEARCH("Paybill Online",C24)),"Pay Bill",IF(ISNUMBER(SEARCH("Pay Bill",C24)),"Pay Bill",IF(ISNUMBER(SEARCH("Spotify",C24)),"Pay Bill",IF(ISNUMBER(SEARCH("M-Shwari",C24)),"Mshwari",IF(ISNUMBER(SEARCH("Mshwari",C24)),"Mshwari",IF(ISNUMBER(SEARCH("Withdrawal charge",C24)),"Fees",IF(ISNUMBER(SEARCH("Customer Withdrawal",C24)),"Fees",IF(ISNUMBER(SEARCH("charge",C24)),"Fees","Other"))))))))))))))))))))))))) -> Bundles | R24: =TEXT(B2,"MMM YYYY") -> Jan 2026
A25: UAFA93ULQZ | B25: 2026-01-15 19:29:44 | C25: Customer Bundle Purchase to 4093441SAFARICOM DATA BUNDLES by - 2547******109 NAOMI MUREITHI | D25: Completed | F25: 10 | G25: 1910 | L25: =IF(ISNUMBER(SEARCH("Bundle",C25)),"Bundles",IF(ISNUMBER(SEARCH("Airtime",C25)),"Bundles",IF(ISNUMBER(SEARCH("Merchant",C25)),"Merchant Payment",IF(ISNUMBER(SEARCH("Offnet C2B",C25)),"Merchant Payment",IF(ISNUMBER(SEARCH("Offnet B2C",C25)),"Merchant Payment",IF(ISNUMBER(SEARCH("Customer Payment to Small",C25)),"Merchant Payment",IF(ISNUMBER(SEARCH("Payment to Small Business",C25)),"Merchant Payment",IF(ISNUMBER(SEARCH("Sent to",C25)),"Sent to Person",IF(ISNUMBER(SEARCH("Customer Transfer to",C25)),"Sent to Person",IF(ISNUMBER(SEARCH("Business Payment",C25)),"Money In",IF(ISNUMBER(SEARCH("Funds Received",C25)),"Money In",IF(ISNUMBER(SEARCH("Receive International",C25)),"Money In",IF(ISNUMBER(SEARCH("Send Money Reversal",C25)),"Money In",IF(ISNUMBER(SEARCH("Pay Utility Reversal",C25)),"Money In",IF(ISNUMBER(SEARCH("Customer Transfer",C25)),"Money In",IF(ISNUMBER(SEARCH("Ziidi",C25)),"Investment",IF(ISNUMBER(SEARCH("Nabo",C25)),"Investment",IF(ISNUMBER(SEARCH("Paybill Online",C25)),"Pay Bill",IF(ISNUMBER(SEARCH("Pay Bill",C25)),"Pay Bill",IF(ISNUMBER(SEARCH("Spotify",C25)),"Pay Bill",IF(ISNUMBER(SEARCH("M-Shwari",C25)),"Mshwari",IF(ISNUMBER(SEARCH("Mshwari",C25)),"Mshwari",IF(ISNUMBER(SEARCH("Withdrawal charge",C25)),"Fees",IF(ISNUMBER(SEARCH("Customer Withdrawal",C25)),"Fees",IF(ISNUMBER(SEARCH("charge",C25)),"Fees","Other"))))))))))))))))))))))))) -> Bundles | R25: =TEXT(B2,"MMM YYYY") -> Jan 2026
A26: UAFA93V31J | B26: 2026-01-15 21:33:55 | C26: Customer Bundle Purchase to 4093441SAFARICOM DATA BUNDLES by - 2547******109 NAOMI MUREITHI | D26: Completed | F26: 10 | G26: 1900 | L26: =IF(ISNUMBER(SEARCH("Bundle",C26)),"Bundles",IF(ISNUMBER(SEARCH("Airtime",C26)),"Bundles",IF(ISNUMBER(SEARCH("Merchant",C26)),"Merchant Payment",IF(ISNUMBER(SEARCH("Offnet C2B",C26)),"Merchant Payment",IF(ISNUMBER(SEARCH("Offnet B2C",C26)),"Merchant Payment",IF(ISNUMBER(SEARCH("Customer Payment to Small",C26)),"Merchant Payment",IF(ISNUMBER(SEARCH("Payment to Small Business",C26)),"Merchant Payment",IF(ISNUMBER(SEARCH("Sent to",C26)),"Sent to Person",IF(ISNUMBER(SEARCH("Customer Transfer to",C26)),"Sent to Person",IF(ISNUMBER(SEARCH("Business Payment",C26)),"Money In",IF(ISNUMBER(SEARCH("Funds Received",C26)),"Money In",IF(ISNUMBER(SEARCH("Receive International",C26)),"Money In",IF(ISNUMBER(SEARCH("Send Money Reversal",C26)),"Money In",IF(ISNUMBER(SEARCH("Pay Utility Reversal",C26)),"Money In",IF(ISNUMBER(SEARCH("Customer Transfer",C26)),"Money In",IF(ISNUMBER(SEARCH("Ziidi",C26)),"Investment",IF(ISNUMBER(SEARCH("Nabo",C26)),"Investment",IF(ISNUMBER(SEARCH("Paybill Online",C26)),"Pay Bill",IF(ISNUMBER(SEARCH("Pay Bill",C26)),"Pay Bill",IF(ISNUMBER(SEARCH("Spotify",C26)),"Pay Bill",IF(ISNUMBER(SEARCH("M-Shwari",C26)),"Mshwari",IF(ISNUMBER(SEARCH("Mshwari",C26)),"Mshwari",IF(ISNUMBER(SEARCH("Withdrawal charge",C26)),"Fees",IF(ISNUMBER(SEARCH("Customer Withdrawal",C26)),"Fees",IF(ISNUMBER(SEARCH("charge",C26)),"Fees","Other"))))))))))))))))))))))))) -> Bundles | R26: =TEXT(B2,"MMM YYYY") -> Jan 2026
A27: UAGA93VFFB | B27: 2026-01-16 03:03:48 | C27: Customer Bundle Purchase to 4093441SAFARICOM DATA BUNDLES by - 2547******109 NAOMI MUREITHI | D27: Completed | F27: 30 | G27: 1870 | L27: =IF(ISNUMBER(SEARCH("Bundle",C27)),"Bundles",IF(ISNUMBER(SEARCH("Airtime",C27)),"Bundles",IF(ISNUMBER(SEARCH("Merchant",C27)),"Merchant Payment",IF(ISNUMBER(SEARCH("Offnet C2B",C27)),"Merchant Payment",IF(ISNUMBER(SEARCH("Offnet B2C",C27)),"Merchant Payment",IF(ISNUMBER(SEARCH("Customer Payment to Small",C27)),"Merchant Payment",IF(ISNUMBER(SEARCH("Payment to Small Business",C27)),"Merchant Payment",IF(ISNUMBER(SEARCH("Sent to",C27)),"Sent to Person",IF(ISNUMBER(SEARCH("Customer Transfer to",C27)),"Sent to Person",IF(ISNUMBER(SEARCH("Business Payment",C27)),"Money In",IF(ISNUMBER(SEARCH("Funds Received",C27)),"Money In",IF(ISNUMBER(SEARCH("Receive International",C27)),"Money In",IF(ISNUMBER(SEARCH("Send Money Reversal",C27)),"Money In",IF(ISNUMBER(SEARCH("Pay Utility Reversal",C27)),"Money In",IF(ISNUMBER(SEARCH("Customer Transfer",C27)),"Money In",IF(ISNUMBER(SEARCH("Ziidi",C27)),"Investment",IF(ISNUMBER(SEARCH("Nabo",C27)),"Investment",IF(ISNUMBER(SEARCH("Paybill Online",C27)),"Pay Bill",IF(ISNUMBER(SEARCH("Pay Bill",C27)),"Pay Bill",IF(ISNUMBER(SEARCH("Spotify",C27)),"Pay Bill",IF(ISNUMBER(SEARCH("M-Shwari",C27)),"Mshwari",IF(ISNUMBER(SEARCH("Mshwari",C27)),"Mshwari",IF(ISNUMBER(SEARCH("Withdrawal charge",C27)),"Fees",IF(ISNUMBER(SEARCH("Customer Withdrawal",C27)),"Fees",IF(ISNUMBER(SEARCH("charge",C27)),"Fees","Other"))))))))))))))))))))))))) -> Bundles | R27: =TEXT(B2,"MMM YYYY") -> Jan 2026
A28: UAGA93X06J | B28: 2026-01-16 15:14:25 | C28: Customer Bundle Purchase to 4093441SAFARICOM DATA BUNDLES by - 2547******109 NAOMI MUREITHI | D28: Completed | F28: 20 | G28: 1850 | L28: =IF(ISNUMBER(SEARCH("Bundle",C28)),"Bundles",IF(ISNUMBER(SEARCH("Airtime",C28)),"Bundles",IF(ISNUMBER(SEARCH("Merchant",C28)),"Merchant Payment",IF(ISNUMBER(SEARCH("Offnet C2B",C28)),"Merchant Payment",IF(ISNUMBER(SEARCH("Offnet B2C",C28)),"Merchant Payment",IF(ISNUMBER(SEARCH("Customer Payment to Small",C28)),"Merchant Payment",IF(ISNUMBER(SEARCH("Payment to Small Business",C28)),"Merchant Payment",IF(ISNUMBER(SEARCH("Sent to",C28)),"Sent to Person",IF(ISNUMBER(SEARCH("Customer Transfer to",C28)),"Sent to Person",IF(ISNUMBER(SEARCH("Business Payment",C28)),"Money In",IF(ISNUMBER(SEARCH("Funds Received",C28)),"Money In",IF(ISNUMBER(SEARCH("Receive International",C28)),"Money In",IF(ISNUMBER(SEARCH("Send Money Reversal",C28)),"Money In",IF(ISNUMBER(SEARCH("Pay Utility Reversal",C28)),"Money In",IF(ISNUMBER(SEARCH("Customer Transfer",C28)),"Money In",IF(ISNUMBER(SEARCH("Ziidi",C28)),"Investment",IF(ISNUMBER(SEARCH("Nabo",C28)),"Investment",IF(ISNUMBER(SEARCH("Paybill Online",C28)),"Pay Bill",IF(ISNUMBER(SEARCH("Pay Bill",C28)),"Pay Bill",IF(ISNUMBER(SEARCH("Spotify",C28)),"Pay Bill",IF(ISNUMBER(SEARCH("M-Shwari",C28)),"Mshwari",IF(ISNUMBER(SEARCH("Mshwari",C28)),"Mshwari",IF(ISNUMBER(SEARCH("Withdrawal charge",C28)),"Fees",IF(ISNUMBER(SEARCH("Customer Withdrawal",C28)),"Fees",IF(ISNUMBER(SEARCH("charge",C28)),"Fees","Other"))))))))))))))))))))))))) -> Bundles
A29: UAGA93XF01 | B29: 2026-01-16 18:19:45 | C29: Customer Bundle Purchase to 4093441SAFARICOM DATA BUNDLES by - 2547******109 NAOMI MUREITHI | D29: Completed | F29: 10 | G29: 1840 | L29: =IF(ISNUMBER(SEARCH("Bundle",C29)),"Bundles",IF(ISNUMBER(SEARCH("Airtime",C29)),"Bundles",IF(ISNUMBER(SEARCH("Merchant",C29)),"Merchant Payment",IF(ISNUMBER(SEARCH("Offnet C2B",C29)),"Merchant Payment",IF(ISNUMBER(SEARCH("Offnet B2C",C29)),"Merchant Payment",IF(ISNUMBER(SEARCH("Customer Payment to Small",C29)),"Merchant Payment",IF(ISNUMBER(SEARCH("Payment to Small Business",C29)),"Merchant Payment",IF(ISNUMBER(SEARCH("Sent to",C29)),"Sent to Person",IF(ISNUMBER(SEARCH("Customer Transfer to",C29)),"Sent to Person",IF(ISNUMBER(SEARCH("Business Payment",C29)),"Money In",IF(ISNUMBER(SEARCH("Funds Received",C29)),"Money In",IF(ISNUMBER(SEARCH("Receive International",C29)),"Money In",IF(ISNUMBER(SEARCH("Send Money Reversal",C29)),"Money In",IF(ISNUMBER(SEARCH("Pay Utility Reversal",C29)),"Money In",IF(ISNUMBER(SEARCH("Customer Transfer",C29)),"Money In",IF(ISNUMBER(SEARCH("Ziidi",C29)),"Investment",IF(ISNUMBER(SEARCH("Nabo",C29)),"Investment",IF(ISNUMBER(SEARCH("Paybill Online",C29)),"Pay Bill",IF(ISNUMBER(SEARCH("Pay Bill",C29)),"Pay Bill",IF(ISNUMBER(SEARCH("Spotify",C29)),"Pay Bill",IF(ISNUMBER(SEARCH("M-Shwari",C29)),"Mshwari",IF(ISNUMBER(SEARCH("Mshwari",C29)),"Mshwari",IF(ISNUMBER(SEARCH("Withdrawal charge",C29)),"Fees",IF(ISNUMBER(SEARCH("Customer Withdrawal",C29)),"Fees",IF(ISNUMBER(SEARCH("charge",C29)),"Fees","Other"))))))))))))))))))))))))) -> Bundles
A30: UAGA93XVXO | B30: 2026-01-16 19:34:53 | C30: Customer Bundle Purchase to | D30: Completed | F30: 10 | G30: 1830 | L30: =IF(ISNUMBER(SEARCH("Bundle",C30)),"Bundles",IF(ISNUMBER(SEARCH("Airtime",C30)),"Bundles",IF(ISNUMBER(SEARCH("Merchant",C30)),"Merchant Payment",IF(ISNUMBER(SEARCH("Offnet C2B",C30)),"Merchant Payment",IF(ISNUMBER(SEARCH("Offnet B2C",C30)),"Merchant Payment",IF(ISNUMBER(SEARCH("Customer Payment to Small",C30)),"Merchant Payment",IF(ISNUMBER(SEARCH("Payment to Small Business",C30)),"Merchant Payment",IF(ISNUMBER(SEARCH("Sent to",C30)),"Sent to Person",IF(ISNUMBER(SEARCH("Customer Transfer to",C30)),"Sent to Person",IF(ISNUMBER(SEARCH("Business Payment",C30)),"Money In",IF(ISNUMBER(SEARCH("Funds Received",C30)),"Money In",IF(ISNUMBER(SEARCH("Receive International",C30)),"Money In",IF(ISNUMBER(SEARCH("Send Money Reversal",C30)),"Money In",IF(ISNUMBER(SEARCH("Pay Utility Reversal",C30)),"Money In",IF(ISNUMBER(SEARCH("Customer Transfer",C30)),"Money In",IF(ISNUMBER(SEARCH("Ziidi",C30)),"Investment",IF(ISNUMBER(SEARCH("Nabo",C30)),"Investment",IF(ISNUMBER(SEARCH("Paybill Online",C30)),"Pay Bill",IF(ISNUMBER(SEARCH("Pay Bill",C30)),"Pay Bill",IF(ISNUMBER(SEARCH("Spotify",C30)),"Pay Bill",IF(ISNUMBER(SEARCH("M-Shwari",C30)),"Mshwari",IF(ISNUMBER(SEARCH("Mshwari",C30)),"Mshwari",IF(ISNUMBER(SEARCH("Withdrawal charge",C30)),"Fees",IF(ISNUMBER(SEARCH("Customer Withdrawal",C30)),"Fees",IF(ISNUMBER(SEARCH("charge",C30)),"Fees","Other"))))))))))))))))))))))))) -> Bundles
A31: UAGA93YOAJ | B31: 2026-01-16 22:10:56 | C31: Customer Bundle Purchase to | D31: Completed | F31: 10 | G31: 1820 | L31: =IF(ISNUMBER(SEARCH("Bundle",C31)),"Bundles",IF(ISNUMBER(SEARCH("Airtime",C31)),"Bundles",IF(ISNUMBER(SEARCH("Merchant",C31)),"Merchant Payment",IF(ISNUMBER(SEARCH("Offnet C2B",C31)),"Merchant Payment",IF(ISNUMBER(SEARCH("Offnet B2C",C31)),"Merchant Payment",IF(ISNUMBER(SEARCH("Customer Payment to Small",C31)),"Merchant Payment",IF(ISNUMBER(SEARCH("Payment to Small Business",C31)),"Merchant Payment",IF(ISNUMBER(SEARCH("Sent to",C31)),"Sent to Person",IF(ISNUMBER(SEARCH("Customer Transfer to",C31)),"Sent to Person",IF(ISNUMBER(SEARCH("Business Payment",C31)),"Money In",IF(ISNUMBER(SEARCH("Funds Received",C31)),"Money In",IF(ISNUMBER(SEARCH("Receive International",C31)),"Money In",IF(ISNUMBER(SEARCH("Send Money Reversal",C31)),"Money In",IF(ISNUMBER(SEARCH("Pay Utility Reversal",C31)),"Money In",IF(ISNUMBER(SEARCH("Customer Transfer",C31)),"Money In",IF(ISNUMBER(SEARCH("Ziidi",C31)),"Investment",IF(ISNUMBER(SEARCH("Nabo",C31)),"Investment",IF(ISNUMBER(SEARCH("Paybill Online",C31)),"Pay Bill",IF(ISNUMBER(SEARCH("Pay Bill",C31)),"Pay Bill",IF(ISNUMBER(SEARCH("Spotify",C31)),"Pay Bill",IF(ISNUMBER(SEARCH("M-Shwari",C31)),"Mshwari",IF(ISNUMBER(SEARCH("Mshwari",C31)),"Mshwari",IF(ISNUMBER(SEARCH("Withdrawal charge",C31)),"Fees",IF(ISNUMBER(SEARCH("Customer Withdrawal",C31)),"Fees",IF(ISNUMBER(SEARCH("charge",C31)),"Fees","Other"))))))))))))))))))))))))) -> Bundles | R31: =TEXT(B2,"MMM YYYY") -> Jan 2026
A32: UAHA93YTJ4 | B32: 2026-01-17 04:28:25 | C32: Customer Bundle Purchase to | D32: Completed | F32: 30 | G32: 1790 | L32: =IF(ISNUMBER(SEARCH("Bundle",C32)),"Bundles",IF(ISNUMBER(SEARCH("Airtime",C32)),"Bundles",IF(ISNUMBER(SEARCH("Merchant",C32)),"Merchant Payment",IF(ISNUMBER(SEARCH("Offnet C2B",C32)),"Merchant Payment",IF(ISNUMBER(SEARCH("Offnet B2C",C32)),"Merchant Payment",IF(ISNUMBER(SEARCH("Customer Payment to Small",C32)),"Merchant Payment",IF(ISNUMBER(SEARCH("Payment to Small Business",C32)),"Merchant Payment",IF(ISNUMBER(SEARCH("Sent to",C32)),"Sent to Person",IF(ISNUMBER(SEARCH("Customer Transfer to",C32)),"Sent to Person",IF(ISNUMBER(SEARCH("Business Payment",C32)),"Money In",IF(ISNUMBER(SEARCH("Funds Received",C32)),"Money In",IF(ISNUMBER(SEARCH("Receive International",C32)),"Money In",IF(ISNUMBER(SEARCH("Send Money Reversal",C32)),"Money In",IF(ISNUMBER(SEARCH("Pay Utility Reversal",C32)),"Money In",IF(ISNUMBER(SEARCH("Customer Transfer",C32)),"Money In",IF(ISNUMBER(SEARCH("Ziidi",C32)),"Investment",IF(ISNUMBER(SEARCH("Nabo",C32)),"Investment",IF(ISNUMBER(SEARCH("Paybill Online",C32)),"Pay Bill",IF(ISNUMBER(SEARCH("Pay Bill",C32)),"Pay Bill",IF(ISNUMBER(SEARCH("Spotify",C32)),"Pay Bill",IF(ISNUMBER(SEARCH("M-Shwari",C32)),"Mshwari",IF(ISNUMBER(SEARCH("Mshwari",C32)),"Mshwari",IF(ISNUMBER(SEARCH("Withdrawal charge",C32)),"Fees",IF(ISNUMBER(SEARCH("Customer Withdrawal",C32)),"Fees",IF(ISNUMBER(SEARCH("charge",C32)),"Fees","Other"))))))))))))))))))))))))) -> Bundles | R32: =TEXT(B2,"MMM YYYY") -> Jan 2026
A33: UAHA940KSY | B33: 2026-01-17 16:37:19 | C33: Customer Bundle Purchase to | D33: Completed | F33: 10 | G33: 1780 | L33: =IF(ISNUMBER(SEARCH("Bundle",C33)),"Bundles",IF(ISNUMBER(SEARCH("Airtime",C33)),"Bundles",IF(ISNUMBER(SEARCH("Merchant",C33)),"Merchant Payment",IF(ISNUMBER(SEARCH("Offnet C2B",C33)),"Merchant Payment",IF(ISNUMBER(SEARCH("Offnet B2C",C33)),"Merchant Payment",IF(ISNUMBER(SEARCH("Customer Payment to Small",C33)),"Merchant Payment",IF(ISNUMBER(SEARCH("Payment to Small Business",C33)),"Merchant Payment",IF(ISNUMBER(SEARCH("Sent to",C33)),"Sent to Person",IF(ISNUMBER(SEARCH("Customer Transfer to",C33)),"Sent to Person",IF(ISNUMBER(SEARCH("Business Payment",C33)),"Money In",IF(ISNUMBER(SEARCH("Funds Received",C33)),"Money In",IF(ISNUMBER(SEARCH("Receive International",C33)),"Money In",IF(ISNUMBER(SEARCH("Send Money Reversal",C33)),"Money In",IF(ISNUMBER(SEARCH("Pay Utility Reversal",C33)),"Money In",IF(ISNUMBER(SEARCH("Customer Transfer",C33)),"Money In",IF(ISNUMBER(SEARCH("Ziidi",C33)),"Investment",IF(ISNUMBER(SEARCH("Nabo",C33)),"Investment",IF(ISNUMBER(SEARCH("Paybill Online",C33)),"Pay Bill",IF(ISNUMBER(SEARCH("Pay Bill",C33)),"Pay Bill",IF(ISNUMBER(SEARCH("Spotify",C33)),"Pay Bill",IF(ISNUMBER(SEARCH("M-Shwari",C33)),"Mshwari",IF(ISNUMBER(SEARCH("Mshwari",C33)),"Mshwari",IF(ISNUMBER(SEARCH("Withdrawal charge",C33)),"Fees",IF(ISNUMBER(SEARCH("Customer Withdrawal",C33)),"Fees",IF(ISNUMBER(SEARCH("charge",C33)),"Fees","Other"))))))))))))))))))))))))) -> Bundles | R33: =TEXT(B33,"MMM YYYY") -> Jan 2026
A34: UAHA94206V | B34: 2026-01-17 21:18:00 | C34: Customer Bundle Purchase to | D34: Completed | F34: 10 | G34: 1770 | L34: =IF(ISNUMBER(SEARCH("Bundle",C34)),"Bundles",IF(ISNUMBER(SEARCH("Airtime",C34)),"Bundles",IF(ISNUMBER(SEARCH("Merchant",C34)),"Merchant Payment",IF(ISNUMBER(SEARCH("Offnet C2B",C34)),"Merchant Payment",IF(ISNUMBER(SEARCH("Offnet B2C",C34)),"Merchant Payment",IF(ISNUMBER(SEARCH("Customer Payment to Small",C34)),"Merchant Payment",IF(ISNUMBER(SEARCH("Payment to Small Business",C34)),"Merchant Payment",IF(ISNUMBER(SEARCH("Sent to",C34)),"Sent to Person",IF(ISNUMBER(SEARCH("Customer Transfer to",C34)),"Sent to Person",IF(ISNUMBER(SEARCH("Business Payment",C34)),"Money In",IF(ISNUMBER(SEARCH("Funds Received",C34)),"Money In",IF(ISNUMBER(SEARCH("Receive International",C34)),"Money In",IF(ISNUMBER(SEARCH("Send Money Reversal",C34)),"Money In",IF(ISNUMBER(SEARCH("Pay Utility Reversal",C34)),"Money In",IF(ISNUMBER(SEARCH("Customer Transfer",C34)),"Money In",IF(ISNUMBER(SEARCH("Ziidi",C34)),"Investment",IF(ISNUMBER(SEARCH("Nabo",C34)),"Investment",IF(ISNUMBER(SEARCH("Paybill Online",C34)),"Pay Bill",IF(ISNUMBER(SEARCH("Pay Bill",C34)),"Pay Bill",IF(ISNUMBER(SEARCH("Spotify",C34)),"Pay Bill",IF(ISNUMBER(SEARCH("M-Shwari",C34)),"Mshwari",IF(ISNUMBER(SEARCH("Mshwari",C34)),"Mshwari",IF(ISNUMBER(SEARCH("Withdrawal charge",C34)),"Fees",IF(ISNUMBER(SEARCH("Customer Withdrawal",C34)),"Fees",IF(ISNUMBER(SEARCH("charge",C34)),"Fees","Other"))))))))))))))))))))))))) -> Bundles | R34: =TEXT(B34,"MMM YYYY") -> Jan 2026
A35: UAIA94510U | B35: 2026-01-18 21:26:13 | C35: Customer Bundle Purchase to | D35: Completed | F35: 10 | G35: 1760 | L35: =IF(ISNUMBER(SEARCH("Bundle",C35)),"Bundles",IF(ISNUMBER(SEARCH("Airtime",C35)),"Bundles",IF(ISNUMBER(SEARCH("Merchant",C35)),"Merchant Payment",IF(ISNUMBER(SEARCH("Offnet C2B",C35)),"Merchant Payment",IF(ISNUMBER(SEARCH("Offnet B2C",C35)),"Merchant Payment",IF(ISNUMBER(SEARCH("Customer Payment to Small",C35)),"Merchant Payment",IF(ISNUMBER(SEARCH("Payment to Small Business",C35)),"Merchant Payment",IF(ISNUMBER(SEARCH("Sent to",C35)),"Sent to Person",IF(ISNUMBER(SEARCH("Customer Transfer to",C35)),"Sent to Person",IF(ISNUMBER(SEARCH("Business Payment",C35)),"Money In",IF(ISNUMBER(SEARCH("Funds Received",C35)),"Money In",IF(ISNUMBER(SEARCH("Receive International",C35)),"Money In",IF(ISNUMBER(SEARCH("Send Money Reversal",C35)),"Money In",IF(ISNUMBER(SEARCH("Pay Utility Reversal",C35)),"Money In",IF(ISNUMBER(SEARCH("Customer Transfer",C35)),"Money In",IF(ISNUMBER(SEARCH("Ziidi",C35)),"Investment",IF(ISNUMBER(SEARCH("Nabo",C35)),"Investment",IF(ISNUMBER(SEARCH("Paybill Online",C35)),"Pay Bill",IF(ISNUMBER(SEARCH("Pay Bill",C35)),"Pay Bill",IF(ISNUMBER(SEARCH("Spotify",C35)),"Pay Bill",IF(ISNUMBER(SEARCH("M-Shwari",C35)),"Mshwari",IF(ISNUMBER(SEARCH("Mshwari",C35)),"Mshwari",IF(ISNUMBER(SEARCH("Withdrawal charge",C35)),"Fees",IF(ISNUMBER(SEARCH("Customer Withdrawal",C35)),"Fees",IF(ISNUMBER(SEARCH("charge",C35)),"Fees","Other"))))))))))))))))))))))))) -> Bundles | R35: =TEXT(B35,"MMM YYYY") -> Jan 2026
A36: UAIA9451BV | B36: 2026-01-18 21:44:57 | C36: Customer Bundle Purchase to | D36: Completed | F36: 10 | G36: 1750 | L36: =IF(ISNUMBER(SEARCH("Bundle",C36)),"Bundles",IF(ISNUMBER(SEARCH("Airtime",C36)),"Bundles",IF(ISNUMBER(SEARCH("Merchant",C36)),"Merchant Payment",IF(ISNUMBER(SEARCH("Offnet C2B",C36)),"Merchant Payment",IF(ISNUMBER(SEARCH("Offnet B2C",C36)),"Merchant Payment",IF(ISNUMBER(SEARCH("Customer Payment to Small",C36)),"Merchant Payment",IF(ISNUMBER(SEARCH("Payment to Small Business",C36)),"Merchant Payment",IF(ISNUMBER(SEARCH("Sent to",C36)),"Sent to Person",IF(ISNUMBER(SEARCH("Customer Transfer to",C36)),"Sent to Person",IF(ISNUMBER(SEARCH("Business Payment",C36)),"Money In",IF(ISNUMBER(SEARCH("Funds Received",C36)),"Money In",IF(ISNUMBER(SEARCH("Receive International",C36)),"Money In",IF(ISNUMBER(SEARCH("Send Money Reversal",C36)),"Money In",IF(ISNUMBER(SEARCH("Pay Utility Reversal",C36)),"Money In",IF(ISNUMBER(SEARCH("Customer Transfer",C36)),"Money In",IF(ISNUMBER(SEARCH("Ziidi",C36)),"Investment",IF(ISNUMBER(SEARCH("Nabo",C36)),"Investment",IF(ISNUMBER(SEARCH("Paybill Online",C36)),"Pay Bill",IF(ISNUMBER(SEARCH("Pay Bill",C36)),"Pay Bill",IF(ISNUMBER(SEARCH("Spotify",C36)),"Pay Bill",IF(ISNUMBER(SEARCH("M-Shwari",C36)),"Mshwari",IF(ISNUMBER(SEARCH("Mshwari",C36)),"Mshwari",IF(ISNUMBER(SEARCH("Withdrawal charge",C36)),"Fees",IF(ISNUMBER(SEARCH("Customer Withdrawal",C36)),"Fees",IF(ISNUMBER(SEARCH("charge",C36)),"Fees","Other"))))))))))))))))))))))))) -> Bundles | R36: =TEXT(B36,"MMM YYYY") -> Jan 2026
A37: UAJA945AIT | B37: 2026-01-19 03:09:39 | C37: Customer Bundle Purchase to | D37: Completed | F37: 30 | G37: 1720 | L37: =IF(ISNUMBER(SEARCH("Bundle",C37)),"Bundles",IF(ISNUMBER(SEARCH("Airtime",C37)),"Bundles",IF(ISNUMBER(SEARCH("Merchant",C37)),"Merchant Payment",IF(ISNUMBER(SEARCH("Offnet C2B",C37)),"Merchant Payment",IF(ISNUMBER(SEARCH("Offnet B2C",C37)),"Merchant Payment",IF(ISNUMBER(SEARCH("Customer Payment to Small",C37)),"Merchant Payment",IF(ISNUMBER(SEARCH("Payment to Small Business",C37)),"Merchant Payment",IF(ISNUMBER(SEARCH("Sent to",C37)),"Sent to Person",IF(ISNUMBER(SEARCH("Customer Transfer to",C37)),"Sent to Person",IF(ISNUMBER(SEARCH("Business Payment",C37)),"Money In",IF(ISNUMBER(SEARCH("Funds Received",C37)),"Money In",IF(ISNUMBER(SEARCH("Receive International",C37)),"Money In",IF(ISNUMBER(SEARCH("Send Money Reversal",C37)),"Money In",IF(ISNUMBER(SEARCH("Pay Utility Reversal",C37)),"Money In",IF(ISNUMBER(SEARCH("Customer Transfer",C37)),"Money In",IF(ISNUMBER(SEARCH("Ziidi",C37)),"Investment",IF(ISNUMBER(SEARCH("Nabo",C37)),"Investment",IF(ISNUMBER(SEARCH("Paybill Online",C37)),"Pay Bill",IF(ISNUMBER(SEARCH("Pay Bill",C37)),"Pay Bill",IF(ISNUMBER(SEARCH("Spotify",C37)),"Pay Bill",IF(ISNUMBER(SEARCH("M-Shwari",C37)),"Mshwari",IF(ISNUMBER(SEARCH("Mshwari",C37)),"Mshwari",IF(ISNUMBER(SEARCH("Withdrawal charge",C37)),"Fees",IF(ISNUMBER(SEARCH("Customer Withdrawal",C37)),"Fees",IF(ISNUMBER(SEARCH("charge",C37)),"Fees","Other"))))))))))))))))))))))))) -> Bundles | R37: =TEXT(B37,"MMM YYYY") -> Jan 2026
A38: UAJA946AB6 | B38: 2026-01-19 12:35:36 | C38: Customer Bundle Purchase to | D38: Completed | F38: 10 | G38: 1710 | L38: =IF(ISNUMBER(SEARCH("Bundle",C38)),"Bundles",IF(ISNUMBER(SEARCH("Airtime",C38)),"Bundles",IF(ISNUMBER(SEARCH("Merchant",C38)),"Merchant Payment",IF(ISNUMBER(SEARCH("Offnet C2B",C38)),"Merchant Payment",IF(ISNUMBER(SEARCH("Offnet B2C",C38)),"Merchant Payment",IF(ISNUMBER(SEARCH("Customer Payment to Small",C38)),"Merchant Payment",IF(ISNUMBER(SEARCH("Payment to Small Business",C38)),"Merchant Payment",IF(ISNUMBER(SEARCH("Sent to",C38)),"Sent to Person",IF(ISNUMBER(SEARCH("Customer Transfer to",C38)),"Sent to Person",IF(ISNUMBER(SEARCH("Business Payment",C38)),"Money In",IF(ISNUMBER(SEARCH("Funds Received",C38)),"Money In",IF(ISNUMBER(SEARCH("Receive International",C38)),"Money In",IF(ISNUMBER(SEARCH("Send Money Reversal",C38)),"Money In",IF(ISNUMBER(SEARCH("Pay Utility Reversal",C38)),"Money In",IF(ISNUMBER(SEARCH("Customer Transfer",C38)),"Money In",IF(ISNUMBER(SEARCH("Ziidi",C38)),"Investment",IF(ISNUMBER(SEARCH("Nabo",C38)),"Investment",IF(ISNUMBER(SEARCH("Paybill Online",C38)),"Pay Bill",IF(ISNUMBER(SEARCH("Pay Bill",C38)),"Pay Bill",IF(ISNUMBER(SEARCH("Spotify",C38)),"Pay Bill",IF(ISNUMBER(SEARCH("M-Shwari",C38)),"Mshwari",IF(ISNUMBER(SEARCH("Mshwari",C38)),"Mshwari",IF(ISNUMBER(SEARCH("Withdrawal charge",C38)),"Fees",IF(ISNUMBER(SEARCH("Customer Withdrawal",C38)),"Fees",IF(ISNUMBER(SEARCH("charge",C38)),"Fees","Other"))))))))))))))))))))))))) -> Bundles | R38: =TEXT(B38,"MMM YYYY") -> Jan 2026
A39: UAJA946TB4 | B39: 2026-01-19 14:42:20 | C39: Customer Bundle Purchase to | D39: Completed | F39: 30 | G39: 1680 | L39: =IF(ISNUMBER(SEARCH("Bundle",C39)),"Bundles",IF(ISNUMBER(SEARCH("Airtime",C39)),"Bundles",IF(ISNUMBER(SEARCH("Merchant",C39)),"Merchant Payment",IF(ISNUMBER(SEARCH("Offnet C2B",C39)),"Merchant Payment",IF(ISNUMBER(SEARCH("Offnet B2C",C39)),"Merchant Payment",IF(ISNUMBER(SEARCH("Customer Payment to Small",C39)),"Merchant Payment",IF(ISNUMBER(SEARCH("Payment to Small Business",C39)),"Merchant Payment",IF(ISNUMBER(SEARCH("Sent to",C39)),"Sent to Person",IF(ISNUMBER(SEARCH("Customer Transfer to",C39)),"Sent to Person",IF(ISNUMBER(SEARCH("Business Payment",C39)),"Money In",IF(ISNUMBER(SEARCH("Funds Received",C39)),"Money In",IF(ISNUMBER(SEARCH("Receive International",C39)),"Money In",IF(ISNUMBER(SEARCH("Send Money Reversal",C39)),"Money In",IF(ISNUMBER(SEARCH("Pay Utility Reversal",C39)),"Money In",IF(ISNUMBER(SEARCH("Customer Transfer",C39)),"Money In",IF(ISNUMBER(SEARCH("Ziidi",C39)),"Investment",IF(ISNUMBER(SEARCH("Nabo",C39)),"Investment",IF(ISNUMBER(SEARCH("Paybill Online",C39)),"Pay Bill",IF(ISNUMBER(SEARCH("Pay Bill",C39)),"Pay Bill",IF(ISNUMBER(SEARCH("Spotify",C39)),"Pay Bill",IF(ISNUMBER(SEARCH("M-Shwari",C39)),"Mshwari",IF(ISNUMBER(SEARCH("Mshwari",C39)),"Mshwari",IF(ISNUMBER(SEARCH("Withdrawal charge",C39)),"Fees",IF(ISNUMBER(SEARCH("Customer Withdrawal",C39)),"Fees",IF(ISNUMBER(SEARCH("charge",C39)),"Fees","Other"))))))))))))))))))))))))) -> Bundles | R39: =TEXT(B39,"MMM YYYY") -> Jan 2026
A40: UAJA947K9V | B40: 2026-01-19 18:55:20 | C40: Customer Bundle Purchase to | D40: Completed | F40: 10 | G40: 1670 | L40: =IF(ISNUMBER(SEARCH("Bundle",C40)),"Bundles",IF(ISNUMBER(SEARCH("Airtime",C40)),"Bundles",IF(ISNUMBER(SEARCH("Merchant",C40)),"Merchant Payment",IF(ISNUMBER(SEARCH("Offnet C2B",C40)),"Merchant Payment",IF(ISNUMBER(SEARCH("Offnet B2C",C40)),"Merchant Payment",IF(ISNUMBER(SEARCH("Customer Payment to Small",C40)),"Merchant Payment",IF(ISNUMBER(SEARCH("Payment to Small Business",C40)),"Merchant Payment",IF(ISNUMBER(SEARCH("Sent to",C40)),"Sent to Person",IF(ISNUMBER(SEARCH("Customer Transfer to",C40)),"Sent to Person",IF(ISNUMBER(SEARCH("Business Payment",C40)),"Money In",IF(ISNUMBER(SEARCH("Funds Received",C40)),"Money In",IF(ISNUMBER(SEARCH("Receive International",C40)),"Money In",IF(ISNUMBER(SEARCH("Send Money Reversal",C40)),"Money In",IF(ISNUMBER(SEARCH("Pay Utility Reversal",C40)),"Money In",IF(ISNUMBER(SEARCH("Customer Transfer",C40)),"Money In",IF(ISNUMBER(SEARCH("Ziidi",C40)),"Investment",IF(ISNUMBER(SEARCH("Nabo",C40)),"Investment",IF(ISNUMBER(SEARCH("Paybill Online",C40)),"Pay Bill",IF(ISNUMBER(SEARCH("Pay Bill",C40)),"Pay Bill",IF(ISNUMBER(SEARCH("Spotify",C40)),"Pay Bill",IF(ISNUMBER(SEARCH("M-Shwari",C40)),"Mshwari",IF(ISNUMBER(SEARCH("Mshwari",C40)),"Mshwari",IF(ISNUMBER(SEARCH("Withdrawal charge",C40)),"Fees",IF(ISNUMBER(SEARCH("Customer Withdrawal",C40)),"Fees",IF(ISNUMBER(SEARCH("charge",C40)),"Fees","Other"))))))))))))))))))))))))) -> Bundles | R40: =TEXT(B40,"MMM YYYY") -> Jan 2026
A41: UAJA947X46 | B41: 2026-01-19 20:38:20 | C41: Customer Bundle Purchase to | D41: Completed | F41: 10 | G41: 1660 | L41: =IF(ISNUMBER(SEARCH("Bundle",C41)),"Bundles",IF(ISNUMBER(SEARCH("Airtime",C41)),"Bundles",IF(ISNUMBER(SEARCH("Merchant",C41)),"Merchant Payment",IF(ISNUMBER(SEARCH("Offnet C2B",C41)),"Merchant Payment",IF(ISNUMBER(SEARCH("Offnet B2C",C41)),"Merchant Payment",IF(ISNUMBER(SEARCH("Customer Payment to Small",C41)),"Merchant Payment",IF(ISNUMBER(SEARCH("Payment to Small Business",C41)),"Merchant Payment",IF(ISNUMBER(SEARCH("Sent to",C41)),"Sent to Person",IF(ISNUMBER(SEARCH("Customer Transfer to",C41)),"Sent to Person",IF(ISNUMBER(SEARCH("Business Payment",C41)),"Money In",IF(ISNUMBER(SEARCH("Funds Received",C41)),"Money In",IF(ISNUMBER(SEARCH("Receive International",C41)),"Money In",IF(ISNUMBER(SEARCH("Send Money Reversal",C41)),"Money In",IF(ISNUMBER(SEARCH("Pay Utility Reversal",C41)),"Money In",IF(ISNUMBER(SEARCH("Customer Transfer",C41)),"Money In",IF(ISNUMBER(SEARCH("Ziidi",C41)),"Investment",IF(ISNUMBER(SEARCH("Nabo",C41)),"Investment",IF(ISNUMBER(SEARCH("Paybill Online",C41)),"Pay Bill",IF(ISNUMBER(SEARCH("Pay Bill",C41)),"Pay Bill",IF(ISNUMBER(SEARCH("Spotify",C41)),"Pay Bill",IF(ISNUMBER(SEARCH("M-Shwari",C41)),"Mshwari",IF(ISNUMBER(SEARCH("Mshwari",C41)),"Mshwari",IF(ISNUMBER(SEARCH("Withdrawal charge",C41)),"Fees",IF(ISNUMBER(SEARCH("Customer Withdrawal",C41)),"Fees",IF(ISNUMBER(SEARCH("charge",C41)),"Fees","Other"))))))))))))))))))))))))) -> Bundles | R41: =TEXT(B41,"MMM YYYY") -> Jan 2026
A42: UAKA948JLQ | B42: 2026-01-20 03:11:59 | C42: Customer Bundle Purchase to | D42: Completed | F42: 30 | G42: 1630 | L42: =IF(ISNUMBER(SEARCH("Bundle",C42)),"Bundles",IF(ISNUMBER(SEARCH("Airtime",C42)),"Bundles",IF(ISNUMBER(SEARCH("Merchant",C42)),"Merchant Payment",IF(ISNUMBER(SEARCH("Offnet C2B",C42)),"Merchant Payment",IF(ISNUMBER(SEARCH("Offnet B2C",C42)),"Merchant Payment",IF(ISNUMBER(SEARCH("Customer Payment to Small",C42)),"Merchant Payment",IF(ISNUMBER(SEARCH("Payment to Small Business",C42)),"Merchant Payment",IF(ISNUMBER(SEARCH("Sent to",C42)),"Sent to Person",IF(ISNUMBER(SEARCH("Customer Transfer to",C42)),"Sent to Person",IF(ISNUMBER(SEARCH("Business Payment",C42)),"Money In",IF(ISNUMBER(SEARCH("Funds Received",C42)),"Money In",IF(ISNUMBER(SEARCH("Receive International",C42)),"Money In",IF(ISNUMBER(SEARCH("Send Money Reversal",C42)),"Money In",IF(ISNUMBER(SEARCH("Pay Utility Reversal",C42)),"Money In",IF(ISNUMBER(SEARCH("Customer Transfer",C42)),"Money In",IF(ISNUMBER(SEARCH("Ziidi",C42)),"Investment",IF(ISNUMBER(SEARCH("Nabo",C42)),"Investment",IF(ISNUMBER(SEARCH("Paybill Online",C42)),"Pay Bill",IF(ISNUMBER(SEARCH("Pay Bill",C42)),"Pay Bill",IF(ISNUMBER(SEARCH("Spotify",C42)),"Pay Bill",IF(ISNUMBER(SEARCH("M-Shwari",C42)),"Mshwari",IF(ISNUMBER(SEARCH("Mshwari",C42)),"Mshwari",IF(ISNUMBER(SEARCH("Withdrawal charge",C42)),"Fees",IF(ISNUMBER(SEARCH("Customer Withdrawal",C42)),"Fees",IF(ISNUMBER(SEARCH("charge",C42)),"Fees","Other"))))))))))))))))))))))))) -> Bundles | R42: =TEXT(B42,"MMM YYYY") -> Jan 2026
A43: UAKA949351 | B43: 2026-01-20 09:28:33 | C43: Customer Bundle Purchase to | D43: Completed | F43: 10 | G43: 1620 | L43: =IF(ISNUMBER(SEARCH("Bundle",C43)),"Bundles",IF(ISNUMBER(SEARCH("Airtime",C43)),"Bundles",IF(ISNUMBER(SEARCH("Merchant",C43)),"Merchant Payment",IF(ISNUMBER(SEARCH("Offnet C2B",C43)),"Merchant Payment",IF(ISNUMBER(SEARCH("Offnet B2C",C43)),"Merchant Payment",IF(ISNUMBER(SEARCH("Customer Payment to Small",C43)),"Merchant Payment",IF(ISNUMBER(SEARCH("Payment to Small Business",C43)),"Merchant Payment",IF(ISNUMBER(SEARCH("Sent to",C43)),"Sent to Person",IF(ISNUMBER(SEARCH("Customer Transfer to",C43)),"Sent to Person",IF(ISNUMBER(SEARCH("Business Payment",C43)),"Money In",IF(ISNUMBER(SEARCH("Funds Received",C43)),"Money In",IF(ISNUMBER(SEARCH("Receive International",C43)),"Money In",IF(ISNUMBER(SEARCH("Send Money Reversal",C43)),"Money In",IF(ISNUMBER(SEARCH("Pay Utility Reversal",C43)),"Money In",IF(ISNUMBER(SEARCH("Customer Transfer",C43)),"Money In",IF(ISNUMBER(SEARCH("Ziidi",C43)),"Investment",IF(ISNUMBER(SEARCH("Nabo",C43)),"Investment",IF(ISNUMBER(SEARCH("Paybill Online",C43)),"Pay Bill",IF(ISNUMBER(SEARCH("Pay Bill",C43)),"Pay Bill",IF(ISNUMBER(SEARCH("Spotify",C43)),"Pay Bill",IF(ISNUMBER(SEARCH("M-Shwari",C43)),"Mshwari",IF(ISNUMBER(SEARCH("Mshwari",C43)),"Mshwari",IF(ISNUMBER(SEARCH("Withdrawal charge",C43)),"Fees",IF(ISNUMBER(SEARCH("Customer Withdrawal",C43)),"Fees",IF(ISNUMBER(SEARCH("charge",C43)),"Fees","Other"))))))))))))))))))))))))) -> Bundles | R43: =TEXT(B43,"MMM YYYY") -> Jan 2026
A44: UAKA949JW7 | B44: 2026-01-20 11:15:28 | C44: Customer Bundle Purchase to | D44: Completed | F44: 30 | G44: 1590 | L44: =IF(ISNUMBER(SEARCH("Bundle",C44)),"Bundles",IF(ISNUMBER(SEARCH("Airtime",C44)),"Bundles",IF(ISNUMBER(SEARCH("Merchant",C44)),"Merchant Payment",IF(ISNUMBER(SEARCH("Offnet C2B",C44)),"Merchant Payment",IF(ISNUMBER(SEARCH("Offnet B2C",C44)),"Merchant Payment",IF(ISNUMBER(SEARCH("Customer Payment to Small",C44)),"Merchant Payment",IF(ISNUMBER(SEARCH("Payment to Small Business",C44)),"Merchant Payment",IF(ISNUMBER(SEARCH("Sent to",C44)),"Sent to Person",IF(ISNUMBER(SEARCH("Customer Transfer to",C44)),"Sent to Person",IF(ISNUMBER(SEARCH("Business Payment",C44)),"Money In",IF(ISNUMBER(SEARCH("Funds Received",C44)),"Money In",IF(ISNUMBER(SEARCH("Receive International",C44)),"Money In",IF(ISNUMBER(SEARCH("Send Money Reversal",C44)),"Money In",IF(ISNUMBER(SEARCH("Pay Utility Reversal",C44)),"Money In",IF(ISNUMBER(SEARCH("Customer Transfer",C44)),"Money In",IF(ISNUMBER(SEARCH("Ziidi",C44)),"Investment",IF(ISNUMBER(SEARCH("Nabo",C44)),"Investment",IF(ISNUMBER(SEARCH("Paybill Online",C44)),"Pay Bill",IF(ISNUMBER(SEARCH("Pay Bill",C44)),"Pay Bill",IF(ISNUMBER(SEARCH("Spotify",C44)),"Pay Bill",IF(ISNUMBER(SEARCH("M-Shwari",C44)),"Mshwari",IF(ISNUMBER(SEARCH("Mshwari",C44)),"Mshwari",IF(ISNUMBER(SEARCH("Withdrawal charge",C44)),"Fees",IF(ISNUMBER(SEARCH("Customer Withdrawal",C44)),"Fees",IF(ISNUMBER(SEARCH("charge",C44)),"Fees","Other"))))))))))))))))))))))))) -> Bundles | R44: =TEXT(B44,"MMM YYYY") -> Jan 2026
... A71: UARA94W59J | B71: 2026-01-27 08:34:18 | C71: Customer Bundle Purchase to 4093441SAFARICOM DATA BUNDLES by - 2547******109 NAOMI MUREITHI | D71: Completed | F71: 10 | G71: 345 | L71: =IF(ISNUMBER(SEARCH("Bundle",C71)),"Bundles",IF(ISNUMBER(SEARCH("Airtime",C71)),"Bundles",IF(ISNUMBER(SEARCH("Merchant",C71)),"Merchant Payment",IF(ISNUMBER(SEARCH("Offnet C2B",C71)),"Merchant Payment",IF(ISNUMBER(SEARCH("Offnet B2C",C71)),"Merchant Payment",IF(ISNUMBER(SEARCH("Customer Payment to Small",C71)),"Merchant Payment",IF(ISNUMBER(SEARCH("Payment to Small Business",C71)),"Merchant Payment",IF(ISNUMBER(SEARCH("Sent to",C71)),"Sent to Person",IF(ISNUMBER(SEARCH("Customer Transfer to",C71)),"Sent to Person",IF(ISNUMBER(SEARCH("Business Payment",C71)),"Money In",IF(ISNUMBER(SEARCH("Funds Received",C71)),"Money In",IF(ISNUMBER(SEARCH("Receive International",C71)),"Money In",IF(ISNUMBER(SEARCH("Send Money Reversal",C71)),"Money In",IF(ISNUMBER(SEARCH("Pay Utility Reversal",C71)),"Money In",IF(ISNUMBER(SEARCH("Customer Transfer",C71)),"Money In",IF(ISNUMBER(SEARCH("Ziidi",C71)),"Investment",IF(ISNUMBER(SEARCH("Nabo",C71)),"Investment",IF(ISNUMBER(SEARCH("Paybill Online",C71)),"Pay Bill",IF(ISNUMBER(SEARCH("Pay Bill",C71)),"Pay Bill",IF(ISNUMBER(SEARCH("Spotify",C71)),"Pay Bill",IF(ISNUMBER(SEARCH("M-Shwari",C71)),"Mshwari",IF(ISNUMBER(SEARCH("Mshwari",C71)),"Mshwari",IF(ISNUMBER(SEARCH("Withdrawal charge",C71)),"Fees",IF(ISNUMBER(SEARCH("Customer Withdrawal",C71)),"Fees",IF(ISNUMBER(SEARCH("charge",C71)),"Fees","Other"))))))))))))))))))))))))) -> Bundles | R71: =TEXT(B71,"MMM YYYY") -> Jan 2026
A72: UAR4Q4X4LB | B72: 2026-01-27 15:39:45 | C72: Funds received from - 2547******442 PETER MAGANJO | D72: Completed | E72: 2000 | G72: 2345 | L72: =IF(ISNUMBER(SEARCH("Bundle",C72)),"Bundles",IF(ISNUMBER(SEARCH("Airtime",C72)),"Bundles",IF(ISNUMBER(SEARCH("Merchant",C72)),"Merchant Payment",IF(ISNUMBER(SEARCH("Offnet C2B",C72)),"Merchant Payment",IF(ISNUMBER(SEARCH("Offnet B2C",C72)),"Merchant Payment",IF(ISNUMBER(SEARCH("Customer Payment to Small",C72)),"Merchant Payment",IF(ISNUMBER(SEARCH("Payment to Small Business",C72)),"Merchant Payment",IF(ISNUMBER(SEARCH("Sent to",C72)),"Sent to Person",IF(ISNUMBER(SEARCH("Customer Transfer to",C72)),"Sent to Person",IF(ISNUMBER(SEARCH("Business Payment",C72)),"Money In",IF(ISNUMBER(SEARCH("Funds Received",C72)),"Money In",IF(ISNUMBER(SEARCH("Receive International",C72)),"Money In",IF(ISNUMBER(SEARCH("Send Money Reversal",C72)),"Money In",IF(ISNUMBER(SEARCH("Pay Utility Reversal",C72)),"Money In",IF(ISNUMBER(SEARCH("Customer Transfer",C72)),"Money In",IF(ISNUMBER(SEARCH("Ziidi",C72)),"Investment",IF(ISNUMBER(SEARCH("Nabo",C72)),"Investment",IF(ISNUMBER(SEARCH("Paybill Online",C72)),"Pay Bill",IF(ISNUMBER(SEARCH("Pay Bill",C72)),"Pay Bill",IF(ISNUMBER(SEARCH("Spotify",C72)),"Pay Bill",IF(ISNUMBER(SEARCH("M-Shwari",C72)),"Mshwari",IF(ISNUMBER(SEARCH("Mshwari",C72)),"Mshwari",IF(ISNUMBER(SEARCH("Withdrawal charge",C72)),"Fees",IF(ISNUMBER(SEARCH("Customer Withdrawal",C72)),"Fees",IF(ISNUMBER(SEARCH("charge",C72)),"Fees","Other"))))))))))))))))))))))))) -> Money In | R72: =TEXT(B72,"MMM YYYY") -> Jan 2026
A73: UARA94XL25 | B73: 2026-01-27 16:46:31 | C73: Customer Bundle Purchase to 4093441SAFARICOM DATA BUNDLES by - 2547******109 NAOMI MUREITHI | D73: Completed | F73: 10 | G73: 2335 | L73: =IF(ISNUMBER(SEARCH("Bundle",C73)),"Bundles",IF(ISNUMBER(SEARCH("Airtime",C73)),"Bundles",IF(ISNUMBER(SEARCH("Merchant",C73)),"Merchant Payment",IF(ISNUMBER(SEARCH("Offnet C2B",C73)),"Merchant Payment",IF(ISNUMBER(SEARCH("Offnet B2C",C73)),"Merchant Payment",IF(ISNUMBER(SEARCH("Customer Payment to Small",C73)),"Merchant Payment",IF(ISNUMBER(SEARCH("Payment to Small Business",C73)),"Merchant Payment",IF(ISNUMBER(SEARCH("Sent to",C73)),"Sent to Person",IF(ISNUMBER(SEARCH("Customer Transfer to",C73)),"Sent to Person",IF(ISNUMBER(SEARCH("Business Payment",C73)),"Money In",IF(ISNUMBER(SEARCH("Funds Received",C73)),"Money In",IF(ISNUMBER(SEARCH("Receive International",C73)),"Money In",IF(ISNUMBER(SEARCH("Send Money Reversal",C73)),"Money In",IF(ISNUMBER(SEARCH("Pay Utility Reversal",C73)),"Money In",IF(ISNUMBER(SEARCH("Customer Transfer",C73)),"Money In",IF(ISNUMBER(SEARCH("Ziidi",C73)),"Investment",IF(ISNUMBER(SEARCH("Nabo",C73)),"Investment",IF(ISNUMBER(SEARCH("Paybill Online",C73)),"Pay Bill",IF(ISNUMBER(SEARCH("Pay Bill",C73)),"Pay Bill",IF(ISNUMBER(SEARCH("Spotify",C73)),"Pay Bill",IF(ISNUMBER(SEARCH("M-Shwari",C73)),"Mshwari",IF(ISNUMBER(SEARCH("Mshwari",C73)),"Mshwari",IF(ISNUMBER(SEARCH("Withdrawal charge",C73)),"Fees",IF(ISNUMBER(SEARCH("Customer Withdrawal",C73)),"Fees",IF(ISNUMBER(SEARCH("charge",C73)),"Fees","Other"))))))))))))))))))))))))) -> Bundles | R73: =TEXT(B73,"MMM YYYY") -> Jan 2026
A74: UARA94XDOF | B74: 2026-01-27 16:51:33 | C74: Pay Bill Charge | D74: Completed | F74: 20 | G74: 2315 | L74: =IF(ISNUMBER(SEARCH("Bundle",C74)),"Bundles",IF(ISNUMBER(SEARCH("Airtime",C74)),"Bundles",IF(ISNUMBER(SEARCH("Merchant",C74)),"Merchant Payment",IF(ISNUMBER(SEARCH("Offnet C2B",C74)),"Merchant Payment",IF(ISNUMBER(SEARCH("Offnet B2C",C74)),"Merchant Payment",IF(ISNUMBER(SEARCH("Customer Payment to Small",C74)),"Merchant Payment",IF(ISNUMBER(SEARCH("Payment to Small Business",C74)),"Merchant Payment",IF(ISNUMBER(SEARCH("Sent to",C74)),"Sent to Person",IF(ISNUMBER(SEARCH("Customer Transfer to",C74)),"Sent to Person",IF(ISNUMBER(SEARCH("Business Payment",C74)),"Money In",IF(ISNUMBER(SEARCH("Funds Received",C74)),"Money In",IF(ISNUMBER(SEARCH("Receive International",C74)),"Money In",IF(ISNUMBER(SEARCH("Send Money Reversal",C74)),"Money In",IF(ISNUMBER(SEARCH("Pay Utility Reversal",C74)),"Money In",IF(ISNUMBER(SEARCH("Customer Transfer",C74)),"Money In",IF(ISNUMBER(SEARCH("Ziidi",C74)),"Investment",IF(ISNUMBER(SEARCH("Nabo",C74)),"Investment",IF(ISNUMBER(SEARCH("Paybill Online",C74)),"Pay Bill",IF(ISNUMBER(SEARCH("Pay Bill",C74)),"Pay Bill",IF(ISNUMBER(SEARCH("Spotify",C74)),"Pay Bill",IF(ISNUMBER(SEARCH("M-Shwari",C74)),"Mshwari",IF(ISNUMBER(SEARCH("Mshwari",C74)),"Mshwari",IF(ISNUMBER(SEARCH("Withdrawal charge",C74)),"Fees",IF(ISNUMBER(SEARCH("Customer Withdrawal",C74)),"Fees",IF(ISNUMBER(SEARCH("charge",C74)),"Fees","Other"))))))))))))))))))))))))) -> Pay Bill | R74: =TEXT(B74,"MMM YYYY") -> Jan 2026
A75: UARA94XDOF | B75: 2026-01-27 16:51:33 | C75: Pay Bill Online to 308900 - Guardian Coach Limited Acc. TMPX6Y | D75: Completed | F75: 1650 | G75: 665 | L75: =IF(ISNUMBER(SEARCH("Bundle",C75)),"Bundles",IF(ISNUMBER(SEARCH("Airtime",C75)),"Bundles",IF(ISNUMBER(SEARCH("Merchant",C75)),"Merchant Payment",IF(ISNUMBER(SEARCH("Offnet C2B",C75)),"Merchant Payment",IF(ISNUMBER(SEARCH("Offnet B2C",C75)),"Merchant Payment",IF(ISNUMBER(SEARCH("Customer Payment to Small",C75)),"Merchant Payment",IF(ISNUMBER(SEARCH("Payment to Small Business",C75)),"Merchant Payment",IF(ISNUMBER(SEARCH("Sent to",C75)),"Sent to Person",IF(ISNUMBER(SEARCH("Customer Transfer to",C75)),"Sent to Person",IF(ISNUMBER(SEARCH("Business Payment",C75)),"Money In",IF(ISNUMBER(SEARCH("Funds Received",C75)),"Money In",IF(ISNUMBER(SEARCH("Receive International",C75)),"Money In",IF(ISNUMBER(SEARCH("Send Money Reversal",C75)),"Money In",IF(ISNUMBER(SEARCH("Pay Utility Reversal",C75)),"Money In",IF(ISNUMBER(SEARCH("Customer Transfer",C75)),"Money In",IF(ISNUMBER(SEARCH("Ziidi",C75)),"Investment",IF(ISNUMBER(SEARCH("Nabo",C75)),"Investment",IF(ISNUMBER(SEARCH("Paybill Online",C75)),"Pay Bill",IF(ISNUMBER(SEARCH("Pay Bill",C75)),"Pay Bill",IF(ISNUMBER(SEARCH("Spotify",C75)),"Pay Bill",IF(ISNUMBER(SEARCH("M-Shwari",C75)),"Mshwari",IF(ISNUMBER(SEARCH("Mshwari",C75)),"Mshwari",IF(ISNUMBER(SEARCH("Withdrawal charge",C75)),"Fees",IF(ISNUMBER(SEARCH("Customer Withdrawal",C75)),"Fees",IF(ISNUMBER(SEARCH("charge",C75)),"Fees","Other"))))))))))))))))))))))))) -> Pay Bill | R75: =TEXT(B75,"MMM YYYY") -> Jan 2026
A76: UARA94Y7B3 | B76: 2026-01-27 18:36:25 | C76: Customer Bundle Purchase to 4093441SAFARICOM DATA BUNDLES by - 2547******109 NAOMI MUREITHI | D76: Completed | F76: 10 | G76: 655 | L76: =IF(ISNUMBER(SEARCH("Bundle",C76)),"Bundles",IF(ISNUMBER(SEARCH("Airtime",C76)),"Bundles",IF(ISNUMBER(SEARCH("Merchant",C76)),"Merchant Payment",IF(ISNUMBER(SEARCH("Offnet C2B",C76)),"Merchant Payment",IF(ISNUMBER(SEARCH("Offnet B2C",C76)),"Merchant Payment",IF(ISNUMBER(SEARCH("Customer Payment to Small",C76)),"Merchant Payment",IF(ISNUMBER(SEARCH("Payment to Small Business",C76)),"Merchant Payment",IF(ISNUMBER(SEARCH("Sent to",C76)),"Sent to Person",IF(ISNUMBER(SEARCH("Customer Transfer to",C76)),"Sent to Person",IF(ISNUMBER(SEARCH("Business Payment",C76)),"Money In",IF(ISNUMBER(SEARCH("Funds Received",C76)),"Money In",IF(ISNUMBER(SEARCH("Receive International",C76)),"Money In",IF(ISNUMBER(SEARCH("Send Money Reversal",C76)),"Money In",IF(ISNUMBER(SEARCH("Pay Utility Reversal",C76)),"Money In",IF(ISNUMBER(SEARCH("Customer Transfer",C76)),"Money In",IF(ISNUMBER(SEARCH("Ziidi",C76)),"Investment",IF(ISNUMBER(SEARCH("Nabo",C76)),"Investment",IF(ISNUMBER(SEARCH("Paybill Online",C76)),"Pay Bill",IF(ISNUMBER(SEARCH("Pay Bill",C76)),"Pay Bill",IF(ISNUMBER(SEARCH("Spotify",C76)),"Pay Bill",IF(ISNUMBER(SEARCH("M-Shwari",C76)),"Mshwari",IF(ISNUMBER(SEARCH("Mshwari",C76)),"Mshwari",IF(ISNUMBER(SEARCH("Withdrawal charge",C76)),"Fees",IF(ISNUMBER(SEARCH("Customer Withdrawal",C76)),"Fees",IF(ISNUMBER(SEARCH("charge",C76)),"Fees","Other"))))))))))))))))))))))))) -> Bundles | R76: =TEXT(B76,"MMM YYYY") -> Jan 2026
A77: UARA94YPK4 | B77: 2026-01-27 21:35:45 | C77: Customer Bundle Purchase to 4093441SAFARICOM DATA BUNDLES by - 2547******109 NAOMI MUREITHI | D77: Completed | F77: 10 | G77: 645 | L77: =IF(ISNUMBER(SEARCH("Bundle",C77)),"Bundles",IF(ISNUMBER(SEARCH("Airtime",C77)),"Bundles",IF(ISNUMBER(SEARCH("Merchant",C77)),"Merchant Payment",IF(ISNUMBER(SEARCH("Offnet C2B",C77)),"Merchant Payment",IF(ISNUMBER(SEARCH("Offnet B2C",C77)),"Merchant Payment",IF(ISNUMBER(SEARCH("Customer Payment to Small",C77)),"Merchant Payment",IF(ISNUMBER(SEARCH("Payment to Small Business",C77)),"Merchant Payment",IF(ISNUMBER(SEARCH("Sent to",C77)),"Sent to Person",IF(ISNUMBER(SEARCH("Customer Transfer to",C77)),"Sent to Person",IF(ISNUMBER(SEARCH("Business Payment",C77)),"Money In",IF(ISNUMBER(SEARCH("Funds Received",C77)),"Money In",IF(ISNUMBER(SEARCH("Receive International",C77)),"Money In",IF(ISNUMBER(SEARCH("Send Money Reversal",C77)),"Money In",IF(ISNUMBER(SEARCH("Pay Utility Reversal",C77)),"Money In",IF(ISNUMBER(SEARCH("Customer Transfer",C77)),"Money In",IF(ISNUMBER(SEARCH("Ziidi",C77)),"Investment",IF(ISNUMBER(SEARCH("Nabo",C77)),"Investment",IF(ISNUMBER(SEARCH("Paybill Online",C77)),"Pay Bill",IF(ISNUMBER(SEARCH("Pay Bill",C77)),"Pay Bill",IF(ISNUMBER(SEARCH("Spotify",C77)),"Pay Bill",IF(ISNUMBER(SEARCH("M-Shwari",C77)),"Mshwari",IF(ISNUMBER(SEARCH("Mshwari",C77)),"Mshwari",IF(ISNUMBER(SEARCH("Withdrawal charge",C77)),"Fees",IF(ISNUMBER(SEARCH("Customer Withdrawal",C77)),"Fees",IF(ISNUMBER(SEARCH("charge",C77)),"Fees","Other"))))))))))))))))))))))))) -> Bundles | R77: =TEXT(B77,"MMM YYYY") -> Jan 2026
A78: UASA94ZG6M | B78: 2026-01-28 08:46:34 | C78: Customer Bundle Purchase to 4093441SAFARICOM DATA BUNDLES by - 2547******109 NAOMI MUREITHI | D78: Completed | F78: 10 | G78: 635 | L78: =IF(ISNUMBER(SEARCH("Bundle",C78)),"Bundles",IF(ISNUMBER(SEARCH("Airtime",C78)),"Bundles",IF(ISNUMBER(SEARCH("Merchant",C78)),"Merchant Payment",IF(ISNUMBER(SEARCH("Offnet C2B",C78)),"Merchant Payment",IF(ISNUMBER(SEARCH("Offnet B2C",C78)),"Merchant Payment",IF(ISNUMBER(SEARCH("Customer Payment to Small",C78)),"Merchant Payment",IF(ISNUMBER(SEARCH("Payment to Small Business",C78)),"Merchant Payment",IF(ISNUMBER(SEARCH("Sent to",C78)),"Sent to Person",IF(ISNUMBER(SEARCH("Customer Transfer to",C78)),"Sent to Person",IF(ISNUMBER(SEARCH("Business Payment",C78)),"Money In",IF(ISNUMBER(SEARCH("Funds Received",C78)),"Money In",IF(ISNUMBER(SEARCH("Receive International",C78)),"Money In",IF(ISNUMBER(SEARCH("Send Money Reversal",C78)),"Money In",IF(ISNUMBER(SEARCH("Pay Utility Reversal",C78)),"Money In",IF(ISNUMBER(SEARCH("Customer Transfer",C78)),"Money In",IF(ISNUMBER(SEARCH("Ziidi",C78)),"Investment",IF(ISNUMBER(SEARCH("Nabo",C78)),"Investment",IF(ISNUMBER(SEARCH("Paybill Online",C78)),"Pay Bill",IF(ISNUMBER(SEARCH("Pay Bill",C78)),"Pay Bill",IF(ISNUMBER(SEARCH("Spotify",C78)),"Pay Bill",IF(ISNUMBER(SEARCH("M-Shwari",C78)),"Mshwari",IF(ISNUMBER(SEARCH("Mshwari",C78)),"Mshwari",IF(ISNUMBER(SEARCH("Withdrawal charge",C78)),"Fees",IF(ISNUMBER(SEARCH("Customer Withdrawal",C78)),"Fees",IF(ISNUMBER(SEARCH("charge",C78)),"Fees","Other"))))))))))))))))))))))))) -> Bundles | R78: =TEXT(B78,"MMM YYYY") -> Jan 2026
A79: UA4A92RUGU | B79: 2026-01-04 09:07:23 | C79: M-Shwari Withdraw | D79: Completed | E79: 500 | G79: 600 | L79: =IF(ISNUMBER(SEARCH("Bundle",C79)),"Bundles",IF(ISNUMBER(SEARCH("Airtime",C79)),"Bundles",IF(ISNUMBER(SEARCH("Merchant",C79)),"Merchant Payment",IF(ISNUMBER(SEARCH("Offnet C2B",C79)),"Merchant Payment",IF(ISNUMBER(SEARCH("Offnet B2C",C79)),"Merchant Payment",IF(ISNUMBER(SEARCH("Customer Payment to Small",C79)),"Merchant Payment",IF(ISNUMBER(SEARCH("Payment to Small Business",C79)),"Merchant Payment",IF(ISNUMBER(SEARCH("Sent to",C79)),"Sent to Person",IF(ISNUMBER(SEARCH("Customer Transfer to",C79)),"Sent to Person",IF(ISNUMBER(SEARCH("Business Payment",C79)),"Money In",IF(ISNUMBER(SEARCH("Funds Received",C79)),"Money In",IF(ISNUMBER(SEARCH("Receive International",C79)),"Money In",IF(ISNUMBER(SEARCH("Send Money Reversal",C79)),"Money In",IF(ISNUMBER(SEARCH("Pay Utility Reversal",C79)),"Money In",IF(ISNUMBER(SEARCH("Customer Transfer",C79)),"Money In",IF(ISNUMBER(SEARCH("Ziidi",C79)),"Investment",IF(ISNUMBER(SEARCH("Nabo",C79)),"Investment",IF(ISNUMBER(SEARCH("Paybill Online",C79)),"Pay Bill",IF(ISNUMBER(SEARCH("Pay Bill",C79)),"Pay Bill",IF(ISNUMBER(SEARCH("Spotify",C79)),"Pay Bill",IF(ISNUMBER(SEARCH("M-Shwari",C79)),"Mshwari",IF(ISNUMBER(SEARCH("Mshwari",C79)),"Mshwari",IF(ISNUMBER(SEARCH("Withdrawal charge",C79)),"Fees",IF(ISNUMBER(SEARCH("Customer Withdrawal",C79)),"Fees",IF(ISNUMBER(SEARCH("charge",C79)),"Fees","Other"))))))))))))))))))))))))) -> Mshwari | R79: =TEXT(B79,"MMM YYYY") -> Jan 2026
A80: UA4A92RNWW | B80: 2026-01-04 09:09:29 | C80: Customer Bundle Purchase to 4093441SAFARICOM DATA BUNDLES by - 2547******109 NAOMI MUREITHI | D80: Completed | F80: 10 | G80: 490 | L80: =IF(ISNUMBER(SEARCH("Bundle",C80)),"Bundles",IF(ISNUMBER(SEARCH("Airtime",C80)),"Bundles",IF(ISNUMBER(SEARCH("Merchant",C80)),"Merchant Payment",IF(ISNUMBER(SEARCH("Offnet C2B",C80)),"Merchant Payment",IF(ISNUMBER(SEARCH("Offnet B2C",C80)),"Merchant Payment",IF(ISNUMBER(SEARCH("Customer Payment to Small",C80)),"Merchant Payment",IF(ISNUMBER(SEARCH("Payment to Small Business",C80)),"Merchant Payment",IF(ISNUMBER(SEARCH("Sent to",C80)),"Sent to Person",IF(ISNUMBER(SEARCH("Customer Transfer to",C80)),"Sent to Person",IF(ISNUMBER(SEARCH("Business Payment",C80)),"Money In",IF(ISNUMBER(SEARCH("Funds Received",C80)),"Money In",IF(ISNUMBER(SEARCH("Receive International",C80)),"Money In",IF(ISNUMBER(SEARCH("Send Money Reversal",C80)),"Money In",IF(ISNUMBER(SEARCH("Pay Utility Reversal",C80)),"Money In",IF(ISNUMBER(SEARCH("Customer Transfer",C80)),"Money In",IF(ISNUMBER(SEARCH("Ziidi",C80)),"Investment",IF(ISNUMBER(SEARCH("Nabo",C80)),"Investment",IF(ISNUMBER(SEARCH("Paybill Online",C80)),"Pay Bill",IF(ISNUMBER(SEARCH("Pay Bill",C80)),"Pay Bill",IF(ISNUMBER(SEARCH("Spotify",C80)),"Pay Bill",IF(ISNUMBER(SEARCH("M-Shwari",C80)),"Mshwari",IF(ISNUMBER(SEARCH("Mshwari",C80)),"Mshwari",IF(ISNUMBER(SEARCH("Withdrawal charge",C80)),"Fees",IF(ISNUMBER(SEARCH("Customer Withdrawal",C80)),"Fees",IF(ISNUMBER(SEARCH("charge",C80)),"Fees","Other"))))))))))))))))))))))))) -> Bundles | R80: =TEXT(B80,"MMM YYYY") -> Jan 2026
A81: UA4A92RSFZ | B81: 2026-01-04 10:20:32 | C81: Customer Bundle Purchase to 4093441SAFARICOM DATA BUNDLES by - 2547******109 NAOMI MUREITHI | D81: Completed | F81: 10 | G81: 480 | L81: =IF(ISNUMBER(SEARCH("Bundle",C81)),"Bundles",IF(ISNUMBER(SEARCH("Airtime",C81)),"Bundles",IF(ISNUMBER(SEARCH("Merchant",C81)),"Merchant Payment",IF(ISNUMBER(SEARCH("Offnet C2B",C81)),"Merchant Payment",IF(ISNUMBER(SEARCH("Offnet B2C",C81)),"Merchant Payment",IF(ISNUMBER(SEARCH("Customer Payment to Small",C81)),"Merchant Payment",IF(ISNUMBER(SEARCH("Payment to Small Business",C81)),"Merchant Payment",IF(ISNUMBER(SEARCH("Sent to",C81)),"Sent to Person",IF(ISNUMBER(SEARCH("Customer Transfer to",C81)),"Sent to Person",IF(ISNUMBER(SEARCH("Business Payment",C81)),"Money In",IF(ISNUMBER(SEARCH("Funds Received",C81)),"Money In",IF(ISNUMBER(SEARCH("Receive International",C81)),"Money In",IF(ISNUMBER(SEARCH("Send Money Reversal",C81)),"Money In",IF(ISNUMBER(SEARCH("Pay Utility Reversal",C81)),"Money In",IF(ISNUMBER(SEARCH("Customer Transfer",C81)),"Money In",IF(ISNUMBER(SEARCH("Ziidi",C81)),"Investment",IF(ISNUMBER(SEARCH("Nabo",C81)),"Investment",IF(ISNUMBER(SEARCH("Paybill Online",C81)),"Pay Bill",IF(ISNUMBER(SEARCH("Pay Bill",C81)),"Pay Bill",IF(ISNUMBER(SEARCH("Spotify",C81)),"Pay Bill",IF(ISNUMBER(SEARCH("M-Shwari",C81)),"Mshwari",IF(ISNUMBER(SEARCH("Mshwari",C81)),"Mshwari",IF(ISNUMBER(SEARCH("Withdrawal charge",C81)),"Fees",IF(ISNUMBER(SEARCH("Customer Withdrawal",C81)),"Fees",IF(ISNUMBER(SEARCH("charge",C81)),"Fees","Other"))))))))))))))))))))))))) -> Bundles | R81: =TEXT(B81,"MMM YYYY") -> Jan 2026
A82: UA4A92SQU9 | B82: 2026-01-04 14:40:58 | C82: Customer Bundle Purchase to 826915Safaricom Offers by - 2547******109 NAOMI MUREITHI | D82: Completed | F82: 20 | G82: 460 | L82: =IF(ISNUMBER(SEARCH("Bundle",C82)),"Bundles",IF(ISNUMBER(SEARCH("Airtime",C82)),"Bundles",IF(ISNUMBER(SEARCH("Merchant",C82)),"Merchant Payment",IF(ISNUMBER(SEARCH("Offnet C2B",C82)),"Merchant Payment",IF(ISNUMBER(SEARCH("Offnet B2C",C82)),"Merchant Payment",IF(ISNUMBER(SEARCH("Customer Payment to Small",C82)),"Merchant Payment",IF(ISNUMBER(SEARCH("Payment to Small Business",C82)),"Merchant Payment",IF(ISNUMBER(SEARCH("Sent to",C82)),"Sent to Person",IF(ISNUMBER(SEARCH("Customer Transfer to",C82)),"Sent to Person",IF(ISNUMBER(SEARCH("Business Payment",C82)),"Money In",IF(ISNUMBER(SEARCH("Funds Received",C82)),"Money In",IF(ISNUMBER(SEARCH("Receive International",C82)),"Money In",IF(ISNUMBER(SEARCH("Send Money Reversal",C82)),"Money In",IF(ISNUMBER(SEARCH("Pay Utility Reversal",C82)),"Money In",IF(ISNUMBER(SEARCH("Customer Transfer",C82)),"Money In",IF(ISNUMBER(SEARCH("Ziidi",C82)),"Investment",IF(ISNUMBER(SEARCH("Nabo",C82)),"Investment",IF(ISNUMBER(SEARCH("Paybill Online",C82)),"Pay Bill",IF(ISNUMBER(SEARCH("Pay Bill",C82)),"Pay Bill",IF(ISNUMBER(SEARCH("Spotify",C82)),"Pay Bill",IF(ISNUMBER(SEARCH("M-Shwari",C82)),"Mshwari",IF(ISNUMBER(SEARCH("Mshwari",C82)),"Mshwari",IF(ISNUMBER(SEARCH("Withdrawal charge",C82)),"Fees",IF(ISNUMBER(SEARCH("Customer Withdrawal",C82)),"Fees",IF(ISNUMBER(SEARCH("charge",C82)),"Fees","Other"))))))))))))))))))))))))) -> Bundles | R82: =TEXT(B82,"MMM YYYY") -> Jan 2026
A83: UA4A92SPBK | B83: 2026-01-04 14:41:25 | C83: Customer Bundle Purchase to 4093441SAFARICOM DATA BUNDLES by - 2547******109 NAOMI MUREITHI | D83: Completed | F83: 10 | G83: 450 | L83: =IF(ISNUMBER(SEARCH("Bundle",C83)),"Bundles",IF(ISNUMBER(SEARCH("Airtime",C83)),"Bundles",IF(ISNUMBER(SEARCH("Merchant",C83)),"Merchant Payment",IF(ISNUMBER(SEARCH("Offnet C2B",C83)),"Merchant Payment",IF(ISNUMBER(SEARCH("Offnet B2C",C83)),"Merchant Payment",IF(ISNUMBER(SEARCH("Customer Payment to Small",C83)),"Merchant Payment",IF(ISNUMBER(SEARCH("Payment to Small Business",C83)),"Merchant Payment",IF(ISNUMBER(SEARCH("Sent to",C83)),"Sent to Person",IF(ISNUMBER(SEARCH("Customer Transfer to",C83)),"Sent to Person",IF(ISNUMBER(SEARCH("Business Payment",C83)),"Money In",IF(ISNUMBER(SEARCH("Funds Received",C83)),"Money In",IF(ISNUMBER(SEARCH("Receive International",C83)),"Money In",IF(ISNUMBER(SEARCH("Send Money Reversal",C83)),"Money In",IF(ISNUMBER(SEARCH("Pay Utility Reversal",C83)),"Money In",IF(ISNUMBER(SEARCH("Customer Transfer",C83)),"Money In",IF(ISNUMBER(SEARCH("Ziidi",C83)),"Investment",IF(ISNUMBER(SEARCH("Nabo",C83)),"Investment",IF(ISNUMBER(SEARCH("Paybill Online",C83)),"Pay Bill",IF(ISNUMBER(SEARCH("Pay Bill",C83)),"Pay Bill",IF(ISNUMBER(SEARCH("Spotify",C83)),"Pay Bill",IF(ISNUMBER(SEARCH("M-Shwari",C83)),"Mshwari",IF(ISNUMBER(SEARCH("Mshwari",C83)),"Mshwari",IF(ISNUMBER(SEARCH("Withdrawal charge",C83)),"Fees",IF(ISNUMBER(SEARCH("Customer Withdrawal",C83)),"Fees",IF(ISNUMBER(SEARCH("charge",C83)),"Fees","Other"))))))))))))))))))))))))) -> Bundles | R83: =TEXT(B83,"MMM YYYY") -> Jan 2026
A84: UA4A92SX7N | B84: 2026-01-04 16:18:32 | C84: Customer Bundle Purchase to 826915Safaricom Offers by - 2547******109 NAOMI MUREITHI | D84: Completed | F84: 250 | G84: 200 | L84: =IF(ISNUMBER(SEARCH("Bundle",C84)),"Bundles",IF(ISNUMBER(SEARCH("Airtime",C84)),"Bundles",IF(ISNUMBER(SEARCH("Merchant",C84)),"Merchant Payment",IF(ISNUMBER(SEARCH("Offnet C2B",C84)),"Merchant Payment",IF(ISNUMBER(SEARCH("Offnet B2C",C84)),"Merchant Payment",IF(ISNUMBER(SEARCH("Customer Payment to Small",C84)),"Merchant Payment",IF(ISNUMBER(SEARCH("Payment to Small Business",C84)),"Merchant Payment",IF(ISNUMBER(SEARCH("Sent to",C84)),"Sent to Person",IF(ISNUMBER(SEARCH("Customer Transfer to",C84)),"Sent to Person",IF(ISNUMBER(SEARCH("Business Payment",C84)),"Money In",IF(ISNUMBER(SEARCH("Funds Received",C84)),"Money In",IF(ISNUMBER(SEARCH("Receive International",C84)),"Money In",IF(ISNUMBER(SEARCH("Send Money Reversal",C84)),"Money In",IF(ISNUMBER(SEARCH("Pay Utility Reversal",C84)),"Money In",IF(ISNUMBER(SEARCH("Customer Transfer",C84)),"Money In",IF(ISNUMBER(SEARCH("Ziidi",C84)),"Investment",IF(ISNUMBER(SEARCH("Nabo",C84)),"Investment",IF(ISNUMBER(SEARCH("Paybill Online",C84)),"Pay Bill",IF(ISNUMBER(SEARCH("Pay Bill",C84)),"Pay Bill",IF(ISNUMBER(SEARCH("Spotify",C84)),"Pay Bill",IF(ISNUMBER(SEARCH("M-Shwari",C84)),"Mshwari",IF(ISNUMBER(SEARCH("Mshwari",C84)),"Mshwari",IF(ISNUMBER(SEARCH("Withdrawal charge",C84)),"Fees",IF(ISNUMBER(SEARCH("Customer Withdrawal",C84)),"Fees",IF(ISNUMBER(SEARCH("charge",C84)),"Fees","Other"))))))))))))))))))))))))) -> Bundles | R84: =TEXT(B84,"MMM YYYY") -> Jan 2026
A85: UA5A92UL2N | B85: 2026-01-05 00:41:21 | C85: Customer Bundle Purchase to 4093441SAFARICOM DATA BUNDLES by - 2547******109 NAOMI MUREITHI | D85: Completed | F85: 10 | G85: 190 | L85: =IF(ISNUMBER(SEARCH("Bundle",C85)),"Bundles",IF(ISNUMBER(SEARCH("Airtime",C85)),"Bundles",IF(ISNUMBER(SEARCH("Merchant",C85)),"Merchant Payment",IF(ISNUMBER(SEARCH("Offnet C2B",C85)),"Merchant Payment",IF(ISNUMBER(SEARCH("Offnet B2C",C85)),"Merchant Payment",IF(ISNUMBER(SEARCH("Customer Payment to Small",C85)),"Merchant Payment",IF(ISNUMBER(SEARCH("Payment to Small Business",C85)),"Merchant Payment",IF(ISNUMBER(SEARCH("Sent to",C85)),"Sent to Person",IF(ISNUMBER(SEARCH("Customer Transfer to",C85)),"Sent to Person",IF(ISNUMBER(SEARCH("Business Payment",C85)),"Money In",IF(ISNUMBER(SEARCH("Funds Received",C85)),"Money In",IF(ISNUMBER(SEARCH("Receive International",C85)),"Money In",IF(ISNUMBER(SEARCH("Send Money Reversal",C85)),"Money In",IF(ISNUMBER(SEARCH("Pay Utility Reversal",C85)),"Money In",IF(ISNUMBER(SEARCH("Customer Transfer",C85)),"Money In",IF(ISNUMBER(SEARCH("Ziidi",C85)),"Investment",IF(ISNUMBER(SEARCH("Nabo",C85)),"Investment",IF(ISNUMBER(SEARCH("Paybill Online",C85)),"Pay Bill",IF(ISNUMBER(SEARCH("Pay Bill",C85)),"Pay Bill",IF(ISNUMBER(SEARCH("Spotify",C85)),"Pay Bill",IF(ISNUMBER(SEARCH("M-Shwari",C85)),"Mshwari",IF(ISNUMBER(SEARCH("Mshwari",C85)),"Mshwari",IF(ISNUMBER(SEARCH("Withdrawal charge",C85)),"Fees",IF(ISNUMBER(SEARCH("Customer Withdrawal",C85)),"Fees",IF(ISNUMBER(SEARCH("charge",C85)),"Fees","Other"))))))))))))))))))))))))) -> Bundles | R85: =TEXT(B85,"MMM YYYY") -> Jan 2026
A86: UA5A92UFFO | B86: 2026-01-05 03:59:44 | C86: Customer Bundle Purchase to 4093441SAFARICOM DATA BUNDLES by - 2547******109 NAOMI MUREITHI | D86: Completed | F86: 10 | G86: 180 | L86: =IF(ISNUMBER(SEARCH("Bundle",C86)),"Bundles",IF(ISNUMBER(SEARCH("Airtime",C86)),"Bundles",IF(ISNUMBER(SEARCH("Merchant",C86)),"Merchant Payment",IF(ISNUMBER(SEARCH("Offnet C2B",C86)),"Merchant Payment",IF(ISNUMBER(SEARCH("Offnet B2C",C86)),"Merchant Payment",IF(ISNUMBER(SEARCH("Customer Payment to Small",C86)),"Merchant Payment",IF(ISNUMBER(SEARCH("Payment to Small Business",C86)),"Merchant Payment",IF(ISNUMBER(SEARCH("Sent to",C86)),"Sent to Person",IF(ISNUMBER(SEARCH("Customer Transfer to",C86)),"Sent to Person",IF(ISNUMBER(SEARCH("Business Payment",C86)),"Money In",IF(ISNUMBER(SEARCH("Funds Received",C86)),"Money In",IF(ISNUMBER(SEARCH("Receive International",C86)),"Money In",IF(ISNUMBER(SEARCH("Send Money Reversal",C86)),"Money In",IF(ISNUMBER(SEARCH("Pay Utility Reversal",C86)),"Money In",IF(ISNUMBER(SEARCH("Customer Transfer",C86)),"Money In",IF(ISNUMBER(SEARCH("Ziidi",C86)),"Investment",IF(ISNUMBER(SEARCH("Nabo",C86)),"Investment",IF(ISNUMBER(SEARCH("Paybill Online",C86)),"Pay Bill",IF(ISNUMBER(SEARCH("Pay Bill",C86)),"Pay Bill",IF(ISNUMBER(SEARCH("Spotify",C86)),"Pay Bill",IF(ISNUMBER(SEARCH("M-Shwari",C86)),"Mshwari",IF(ISNUMBER(SEARCH("Mshwari",C86)),"Mshwari",IF(ISNUMBER(SEARCH("Withdrawal charge",C86)),"Fees",IF(ISNUMBER(SEARCH("Customer Withdrawal",C86)),"Fees",IF(ISNUMBER(SEARCH("charge",C86)),"Fees","Other"))))))))))))))))))))))))) -> Bundles | R86: =TEXT(B86,"MMM YYYY") -> Jan 2026
A87: UA5A92UIF4 | B87: 2026-01-05 05:00:43 | C87: Customer Bundle Purchase to 4093441SAFARICOM DATA BUNDLES by - 2547******109 NAOMI MUREITHI | D87: Completed | F87: 10 | G87: 170 | L87: =IF(ISNUMBER(SEARCH("Bundle",C87)),"Bundles",IF(ISNUMBER(SEARCH("Airtime",C87)),"Bundles",IF(ISNUMBER(SEARCH("Merchant",C87)),"Merchant Payment",IF(ISNUMBER(SEARCH("Offnet C2B",C87)),"Merchant Payment",IF(ISNUMBER(SEARCH("Offnet B2C",C87)),"Merchant Payment",IF(ISNUMBER(SEARCH("Customer Payment to Small",C87)),"Merchant Payment",IF(ISNUMBER(SEARCH("Payment to Small Business",C87)),"Merchant Payment",IF(ISNUMBER(SEARCH("Sent to",C87)),"Sent to Person",IF(ISNUMBER(SEARCH("Customer Transfer to",C87)),"Sent to Person",IF(ISNUMBER(SEARCH("Business Payment",C87)),"Money In",IF(ISNUMBER(SEARCH("Funds Received",C87)),"Money In",IF(ISNUMBER(SEARCH("Receive International",C87)),"Money In",IF(ISNUMBER(SEARCH("Send Money Reversal",C87)),"Money In",IF(ISNUMBER(SEARCH("Pay Utility Reversal",C87)),"Money In",IF(ISNUMBER(SEARCH("Customer Transfer",C87)),"Money In",IF(ISNUMBER(SEARCH("Ziidi",C87)),"Investment",IF(ISNUMBER(SEARCH("Nabo",C87)),"Investment",IF(ISNUMBER(SEARCH("Paybill Online",C87)),"Pay Bill",IF(ISNUMBER(SEARCH("Pay Bill",C87)),"Pay Bill",IF(ISNUMBER(SEARCH("Spotify",C87)),"Pay Bill",IF(ISNUMBER(SEARCH("M-Shwari",C87)),"Mshwari",IF(ISNUMBER(SEARCH("Mshwari",C87)),"Mshwari",IF(ISNUMBER(SEARCH("Withdrawal charge",C87)),"Fees",IF(ISNUMBER(SEARCH("Customer Withdrawal",C87)),"Fees",IF(ISNUMBER(SEARCH("charge",C87)),"Fees","Other"))))))))))))))))))))))))) -> Bundles | R87: =TEXT(B87,"MMM YYYY") -> Jan 2026
A88: UA5A92V0PW | B88: 2026-01-05 10:06:54 | C88: Customer Bundle Purchase to 4093441SAFARICOM DATA BUNDLES by - 2547******109 NAOMI MUREITHI | D88: Completed | F88: 10 | G88: 160 | L88: =IF(ISNUMBER(SEARCH("Bundle",C88)),"Bundles",IF(ISNUMBER(SEARCH("Airtime",C88)),"Bundles",IF(ISNUMBER(SEARCH("Merchant",C88)),"Merchant Payment",IF(ISNUMBER(SEARCH("Offnet C2B",C88)),"Merchant Payment",IF(ISNUMBER(SEARCH("Offnet B2C",C88)),"Merchant Payment",IF(ISNUMBER(SEARCH("Customer Payment to Small",C88)),"Merchant Payment",IF(ISNUMBER(SEARCH("Payment to Small Business",C88)),"Merchant Payment",IF(ISNUMBER(SEARCH("Sent to",C88)),"Sent to Person",IF(ISNUMBER(SEARCH("Customer Transfer to",C88)),"Sent to Person",IF(ISNUMBER(SEARCH("Business Payment",C88)),"Money In",IF(ISNUMBER(SEARCH("Funds Received",C88)),"Money In",IF(ISNUMBER(SEARCH("Receive International",C88)),"Money In",IF(ISNUMBER(SEARCH("Send Money Reversal",C88)),"Money In",IF(ISNUMBER(SEARCH("Pay Utility Reversal",C88)),"Money In",IF(ISNUMBER(SEARCH("Customer Transfer",C88)),"Money In",IF(ISNUMBER(SEARCH("Ziidi",C88)),"Investment",IF(ISNUMBER(SEARCH("Nabo",C88)),"Investment",IF(ISNUMBER(SEARCH("Paybill Online",C88)),"Pay Bill",IF(ISNUMBER(SEARCH("Pay Bill",C88)),"Pay Bill",IF(ISNUMBER(SEARCH("Spotify",C88)),"Pay Bill",IF(ISNUMBER(SEARCH("M-Shwari",C88)),"Mshwari",IF(ISNUMBER(SEARCH("Mshwari",C88)),"Mshwari",IF(ISNUMBER(SEARCH("Withdrawal charge",C88)),"Fees",IF(ISNUMBER(SEARCH("Customer Withdrawal",C88)),"Fees",IF(ISNUMBER(SEARCH("charge",C88)),"Fees","Other"))))))))))))))))))))))))) -> Bundles | R88: =TEXT(B88,"MMM YYYY") -> Jan 2026
A89: UA5A92V7U2 | B89: 2026-01-05 11:22:34 | C89: Customer Bundle Purchase to 4093441SAFARICOM DATA BUNDLES by - 2547******109 NAOMI MUREITHI | D89: Completed | F89: 10 | G89: 150 | L89: =IF(ISNUMBER(SEARCH("Bundle",C89)),"Bundles",IF(ISNUMBER(SEARCH("Airtime",C89)),"Bundles",IF(ISNUMBER(SEARCH("Merchant",C89)),"Merchant Payment",IF(ISNUMBER(SEARCH("Offnet C2B",C89)),"Merchant Payment",IF(ISNUMBER(SEARCH("Offnet B2C",C89)),"Merchant Payment",IF(ISNUMBER(SEARCH("Customer Payment to Small",C89)),"Merchant Payment",IF(ISNUMBER(SEARCH("Payment to Small Business",C89)),"Merchant Payment",IF(ISNUMBER(SEARCH("Sent to",C89)),"Sent to Person",IF(ISNUMBER(SEARCH("Customer Transfer to",C89)),"Sent to Person",IF(ISNUMBER(SEARCH("Business Payment",C89)),"Money In",IF(ISNUMBER(SEARCH("Funds Received",C89)),"Money In",IF(ISNUMBER(SEARCH("Receive International",C89)),"Money In",IF(ISNUMBER(SEARCH("Send Money Reversal",C89)),"Money In",IF(ISNUMBER(SEARCH("Pay Utility Reversal",C89)),"Money In",IF(ISNUMBER(SEARCH("Customer Transfer",C89)),"Money In",IF(ISNUMBER(SEARCH("Ziidi",C89)),"Investment",IF(ISNUMBER(SEARCH("Nabo",C89)),"Investment",IF(ISNUMBER(SEARCH("Paybill Online",C89)),"Pay Bill",IF(ISNUMBER(SEARCH("Pay Bill",C89)),"Pay Bill",IF(ISNUMBER(SEARCH("Spotify",C89)),"Pay Bill",IF(ISNUMBER(SEARCH("M-Shwari",C89)),"Mshwari",IF(ISNUMBER(SEARCH("Mshwari",C89)),"Mshwari",IF(ISNUMBER(SEARCH("Withdrawal charge",C89)),"Fees",IF(ISNUMBER(SEARCH("Customer Withdrawal",C89)),"Fees",IF(ISNUMBER(SEARCH("charge",C89)),"Fees","Other"))))))))))))))))))))))))) -> Bundles | R89: =TEXT(B89,"MMM YYYY") -> Jan 2026
A90: UA5A92W01W | B90: 2026-01-05 14:44:17 | C90: Customer Bundle Purchase to 4093441SAFARICOM DATA BUNDLES by - 2547******109 NAOMI MUREITHI | D90: Completed | F90: 10 | G90: 140 | L90: =IF(ISNUMBER(SEARCH("Bundle",C90)),"Bundles",IF(ISNUMBER(SEARCH("Airtime",C90)),"Bundles",IF(ISNUMBER(SEARCH("Merchant",C90)),"Merchant Payment",IF(ISNUMBER(SEARCH("Offnet C2B",C90)),"Merchant Payment",IF(ISNUMBER(SEARCH("Offnet B2C",C90)),"Merchant Payment",IF(ISNUMBER(SEARCH("Customer Payment to Small",C90)),"Merchant Payment",IF(ISNUMBER(SEARCH("Payment to Small Business",C90)),"Merchant Payment",IF(ISNUMBER(SEARCH("Sent to",C90)),"Sent to Person",IF(ISNUMBER(SEARCH("Customer Transfer to",C90)),"Sent to Person",IF(ISNUMBER(SEARCH("Business Payment",C90)),"Money In",IF(ISNUMBER(SEARCH("Funds Received",C90)),"Money In",IF(ISNUMBER(SEARCH("Receive International",C90)),"Money In",IF(ISNUMBER(SEARCH("Send Money Reversal",C90)),"Money In",IF(ISNUMBER(SEARCH("Pay Utility Reversal",C90)),"Money In",IF(ISNUMBER(SEARCH("Customer Transfer",C90)),"Money In",IF(ISNUMBER(SEARCH("Ziidi",C90)),"Investment",IF(ISNUMBER(SEARCH("Nabo",C90)),"Investment",IF(ISNUMBER(SEARCH("Paybill Online",C90)),"Pay Bill",IF(ISNUMBER(SEARCH("Pay Bill",C90)),"Pay Bill",IF(ISNUMBER(SEARCH("Spotify",C90)),"Pay Bill",IF(ISNUMBER(SEARCH("M-Shwari",C90)),"Mshwari",IF(ISNUMBER(SEARCH("Mshwari",C90)),"Mshwari",IF(ISNUMBER(SEARCH("Withdrawal charge",C90)),"Fees",IF(ISNUMBER(SEARCH("Customer Withdrawal",C90)),"Fees",IF(ISNUMBER(SEARCH("charge",C90)),"Fees","Other"))))))))))))))))))))))))) -> Bundles | R90: =TEXT(B90,"MMM YYYY") -> Jan 2026
A91: UA5A92W3PA | B91: 2026-01-05 15:21:35 | C91: Pay Bill Online to 4072222 - NABO CAPITAL LTD C2B Acc. PFCMKU | D91: Completed | F91: 100 | G91: 40 | L91: =IF(ISNUMBER(SEARCH("Bundle",C91)),"Bundles",IF(ISNUMBER(SEARCH("Airtime",C91)),"Bundles",IF(ISNUMBER(SEARCH("Merchant",C91)),"Merchant Payment",IF(ISNUMBER(SEARCH("Offnet C2B",C91)),"Merchant Payment",IF(ISNUMBER(SEARCH("Offnet B2C",C91)),"Merchant Payment",IF(ISNUMBER(SEARCH("Customer Payment to Small",C91)),"Merchant Payment",IF(ISNUMBER(SEARCH("Payment to Small Business",C91)),"Merchant Payment",IF(ISNUMBER(SEARCH("Sent to",C91)),"Sent to Person",IF(ISNUMBER(SEARCH("Customer Transfer to",C91)),"Sent to Person",IF(ISNUMBER(SEARCH("Business Payment",C91)),"Money In",IF(ISNUMBER(SEARCH("Funds Received",C91)),"Money In",IF(ISNUMBER(SEARCH("Receive International",C91)),"Money In",IF(ISNUMBER(SEARCH("Send Money Reversal",C91)),"Money In",IF(ISNUMBER(SEARCH("Pay Utility Reversal",C91)),"Money In",IF(ISNUMBER(SEARCH("Customer Transfer",C91)),"Money In",IF(ISNUMBER(SEARCH("Ziidi",C91)),"Investment",IF(ISNUMBER(SEARCH("Nabo",C91)),"Investment",IF(ISNUMBER(SEARCH("Paybill Online",C91)),"Pay Bill",IF(ISNUMBER(SEARCH("Pay Bill",C91)),"Pay Bill",IF(ISNUMBER(SEARCH("Spotify",C91)),"Pay Bill",IF(ISNUMBER(SEARCH("M-Shwari",C91)),"Mshwari",IF(ISNUMBER(SEARCH("Mshwari",C91)),"Mshwari",IF(ISNUMBER(SEARCH("Withdrawal charge",C91)),"Fees",IF(ISNUMBER(SEARCH("Customer Withdrawal",C91)),"Fees",IF(ISNUMBER(SEARCH("charge",C91)),"Fees","Other"))))))))))))))))))))))))) -> Investment | R91: =TEXT(B91,"MMM YYYY") -> Jan 2026
A92: UA5A92VZI0 | B92: 2026-01-05 15:42:58 | C92: M-Shwari Withdraw | D92: Completed | E92: 500 | G92: 540 | L92: =IF(ISNUMBER(SEARCH("Bundle",C92)),"Bundles",IF(ISNUMBER(SEARCH("Airtime",C92)),"Bundles",IF(ISNUMBER(SEARCH("Merchant",C92)),"Merchant Payment",IF(ISNUMBER(SEARCH("Offnet C2B",C92)),"Merchant Payment",IF(ISNUMBER(SEARCH("Offnet B2C",C92)),"Merchant Payment",IF(ISNUMBER(SEARCH("Customer Payment to Small",C92)),"Merchant Payment",IF(ISNUMBER(SEARCH("Payment to Small Business",C92)),"Merchant Payment",IF(ISNUMBER(SEARCH("Sent to",C92)),"Sent to Person",IF(ISNUMBER(SEARCH("Customer Transfer to",C92)),"Sent to Person",IF(ISNUMBER(SEARCH("Business Payment",C92)),"Money In",IF(ISNUMBER(SEARCH("Funds Received",C92)),"Money In",IF(ISNUMBER(SEARCH("Receive International",C92)),"Money In",IF(ISNUMBER(SEARCH("Send Money Reversal",C92)),"Money In",IF(ISNUMBER(SEARCH("Pay Utility Reversal",C92)),"Money In",IF(ISNUMBER(SEARCH("Customer Transfer",C92)),"Money In",IF(ISNUMBER(SEARCH("Ziidi",C92)),"Investment",IF(ISNUMBER(SEARCH("Nabo",C92)),"Investment",IF(ISNUMBER(SEARCH("Paybill Online",C92)),"Pay Bill",IF(ISNUMBER(SEARCH("Pay Bill",C92)),"Pay Bill",IF(ISNUMBER(SEARCH("Spotify",C92)),"Pay Bill",IF(ISNUMBER(SEARCH("M-Shwari",C92)),"Mshwari",IF(ISNUMBER(SEARCH("Mshwari",C92)),"Mshwari",IF(ISNUMBER(SEARCH("Withdrawal charge",C92)),"Fees",IF(ISNUMBER(SEARCH("Customer Withdrawal",C92)),"Fees",IF(ISNUMBER(SEARCH("charge",C92)),"Fees","Other"))))))))))))))))))))))))) -> Mshwari | R92: =TEXT(B92,"MMM YYYY") -> Jan 2026
A93: UA5A92VY5L | B93: 2026-01-05 15:45:02 | C93: Offnet C2B Transfer to 585555 - AIRTEL MONEY. for Mobile No. 254782822044 | D93: Completed | F93: 100 | G93: 440 | L93: =IF(ISNUMBER(SEARCH("Bundle",C93)),"Bundles",IF(ISNUMBER(SEARCH("Airtime",C93)),"Bundles",IF(ISNUMBER(SEARCH("Merchant",C93)),"Merchant Payment",IF(ISNUMBER(SEARCH("Offnet C2B",C93)),"Merchant Payment",IF(ISNUMBER(SEARCH("Offnet B2C",C93)),"Merchant Payment",IF(ISNUMBER(SEARCH("Customer Payment to Small",C93)),"Merchant Payment",IF(ISNUMBER(SEARCH("Payment to Small Business",C93)),"Merchant Payment",IF(ISNUMBER(SEARCH("Sent to",C93)),"Sent to Person",IF(ISNUMBER(SEARCH("Customer Transfer to",C93)),"Sent to Person",IF(ISNUMBER(SEARCH("Business Payment",C93)),"Money In",IF(ISNUMBER(SEARCH("Funds Received",C93)),"Money In",IF(ISNUMBER(SEARCH("Receive International",C93)),"Money In",IF(ISNUMBER(SEARCH("Send Money Reversal",C93)),"Money In",IF(ISNUMBER(SEARCH("Pay Utility Reversal",C93)),"Money In",IF(ISNUMBER(SEARCH("Customer Transfer",C93)),"Money In",IF(ISNUMBER(SEARCH("Ziidi",C93)),"Investment",IF(ISNUMBER(SEARCH("Nabo",C93)),"Investment",IF(ISNUMBER(SEARCH("Paybill Online",C93)),"Pay Bill",IF(ISNUMBER(SEARCH("Pay Bill",C93)),"Pay Bill",IF(ISNUMBER(SEARCH("Spotify",C93)),"Pay Bill",IF(ISNUMBER(SEARCH("M-Shwari",C93)),"Mshwari",IF(ISNUMBER(SEARCH("Mshwari",C93)),"Mshwari",IF(ISNUMBER(SEARCH("Withdrawal charge",C93)),"Fees",IF(ISNUMBER(SEARCH("Customer Withdrawal",C93)),"Fees",IF(ISNUMBER(SEARCH("charge",C93)),"Fees","Other"))))))))))))))))))))))))) -> Merchant Payment | R93: =TEXT(B93,"MMM YYYY") -> Jan 2026
A94: UA5A92WQ98 | B94: 2026-01-05 17:49:26 | C94: Merchant Payment to 7327328 - Vincent Otieno | D94: Completed | F94: 100 | G94: 340 | L94: =IF(ISNUMBER(SEARCH("Bundle",C94)),"Bundles",IF(ISNUMBER(SEARCH("Airtime",C94)),"Bundles",IF(ISNUMBER(SEARCH("Merchant",C94)),"Merchant Payment",IF(ISNUMBER(SEARCH("Offnet C2B",C94)),"Merchant Payment",IF(ISNUMBER(SEARCH("Offnet B2C",C94)),"Merchant Payment",IF(ISNUMBER(SEARCH("Customer Payment to Small",C94)),"Merchant Payment",IF(ISNUMBER(SEARCH("Payment to Small Business",C94)),"Merchant Payment",IF(ISNUMBER(SEARCH("Sent to",C94)),"Sent to Person",IF(ISNUMBER(SEARCH("Customer Transfer to",C94)),"Sent to Person",IF(ISNUMBER(SEARCH("Business Payment",C94)),"Money In",IF(ISNUMBER(SEARCH("Funds Received",C94)),"Money In",IF(ISNUMBER(SEARCH("Receive International",C94)),"Money In",IF(ISNUMBER(SEARCH("Send Money Reversal",C94)),"Money In",IF(ISNUMBER(SEARCH("Pay Utility Reversal",C94)),"Money In",IF(ISNUMBER(SEARCH("Customer Transfer",C94)),"Money In",IF(ISNUMBER(SEARCH("Ziidi",C94)),"Investment",IF(ISNUMBER(SEARCH("Nabo",C94)),"Investment",IF(ISNUMBER(SEARCH("Paybill Online",C94)),"Pay Bill",IF(ISNUMBER(SEARCH("Pay Bill",C94)),"Pay Bill",IF(ISNUMBER(SEARCH("Spotify",C94)),"Pay Bill",IF(ISNUMBER(SEARCH("M-Shwari",C94)),"Mshwari",IF(ISNUMBER(SEARCH("Mshwari",C94)),"Mshwari",IF(ISNUMBER(SEARCH("Withdrawal charge",C94)),"Fees",IF(ISNUMBER(SEARCH("Customer Withdrawal",C94)),"Fees",IF(ISNUMBER(SEARCH("charge",C94)),"Fees","Other"))))))))))))))))))))))))) -> Merchant Payment | R94: =TEXT(B94,"MMM YYYY") -> Jan 2026
A95: UA5A92WQD4 | B95: 2026-01-05 17:55:05 | C95: Merchant Payment to 6682492 - OBI BAKERY | D95: Completed | F95: 100 | G95: 240 | L95: =IF(ISNUMBER(SEARCH("Bundle",C95)),"Bundles",IF(ISNUMBER(SEARCH("Airtime",C95)),"Bundles",IF(ISNUMBER(SEARCH("Merchant",C95)),"Merchant Payment",IF(ISNUMBER(SEARCH("Offnet C2B",C95)),"Merchant Payment",IF(ISNUMBER(SEARCH("Offnet B2C",C95)),"Merchant Payment",IF(ISNUMBER(SEARCH("Customer Payment to Small",C95)),"Merchant Payment",IF(ISNUMBER(SEARCH("Payment to Small Business",C95)),"Merchant Payment",IF(ISNUMBER(SEARCH("Sent to",C95)),"Sent to Person",IF(ISNUMBER(SEARCH("Customer Transfer to",C95)),"Sent to Person",IF(ISNUMBER(SEARCH("Business Payment",C95)),"Money In",IF(ISNUMBER(SEARCH("Funds Received",C95)),"Money In",IF(ISNUMBER(SEARCH("Receive International",C95)),"Money In",IF(ISNUMBER(SEARCH("Send Money Reversal",C95)),"Money In",IF(ISNUMBER(SEARCH("Pay Utility Reversal",C95)),"Money In",IF(ISNUMBER(SEARCH("Customer Transfer",C95)),"Money In",IF(ISNUMBER(SEARCH("Ziidi",C95)),"Investment",IF(ISNUMBER(SEARCH("Nabo",C95)),"Investment",IF(ISNUMBER(SEARCH("Paybill Online",C95)),"Pay Bill",IF(ISNUMBER(SEARCH("Pay Bill",C95)),"Pay Bill",IF(ISNUMBER(SEARCH("Spotify",C95)),"Pay Bill",IF(ISNUMBER(SEARCH("M-Shwari",C95)),"Mshwari",IF(ISNUMBER(SEARCH("Mshwari",C95)),"Mshwari",IF(ISNUMBER(SEARCH("Withdrawal charge",C95)),"Fees",IF(ISNUMBER(SEARCH("Customer Withdrawal",C95)),"Fees",IF(ISNUMBER(SEARCH("charge",C95)),"Fees","Other"))))))))))))))))))))))))) -> Merchant Payment | R95: =TEXT(B95,"MMM YYYY") -> Jan 2026
A96: UA6A92YAZT | B96: 2026-01-06 10:12:01 | C96: Pay Bill Online to 4072222 - NABO CAPITAL LTD C2B Acc. PFCMKU | D96: Completed | F96: 100 | G96: 140 | L96: =IF(ISNUMBER(SEARCH("Bundle",C96)),"Bundles",IF(ISNUMBER(SEARCH("Airtime",C96)),"Bundles",IF(ISNUMBER(SEARCH("Merchant",C96)),"Merchant Payment",IF(ISNUMBER(SEARCH("Offnet C2B",C96)),"Merchant Payment",IF(ISNUMBER(SEARCH("Offnet B2C",C96)),"Merchant Payment",IF(ISNUMBER(SEARCH("Customer Payment to Small",C96)),"Merchant Payment",IF(ISNUMBER(SEARCH("Payment to Small Business",C96)),"Merchant Payment",IF(ISNUMBER(SEARCH("Sent to",C96)),"Sent to Person",IF(ISNUMBER(SEARCH("Customer Transfer to",C96)),"Sent to Person",IF(ISNUMBER(SEARCH("Business Payment",C96)),"Money In",IF(ISNUMBER(SEARCH("Funds Received",C96)),"Money In",IF(ISNUMBER(SEARCH("Receive International",C96)),"Money In",IF(ISNUMBER(SEARCH("Send Money Reversal",C96)),"Money In",IF(ISNUMBER(SEARCH("Pay Utility Reversal",C96)),"Money In",IF(ISNUMBER(SEARCH("Customer Transfer",C96)),"Money In",IF(ISNUMBER(SEARCH("Ziidi",C96)),"Investment",IF(ISNUMBER(SEARCH("Nabo",C96)),"Investment",IF(ISNUMBER(SEARCH("Paybill Online",C96)),"Pay Bill",IF(ISNUMBER(SEARCH("Pay Bill",C96)),"Pay Bill",IF(ISNUMBER(SEARCH("Spotify",C96)),"Pay Bill",IF(ISNUMBER(SEARCH("M-Shwari",C96)),"Mshwari",IF(ISNUMBER(SEARCH("Mshwari",C96)),"Mshwari",IF(ISNUMBER(SEARCH("Withdrawal charge",C96)),"Fees",IF(ISNUMBER(SEARCH("Customer Withdrawal",C96)),"Fees",IF(ISNUMBER(SEARCH("charge",C96)),"Fees","Other"))))))))))))))))))))))))) -> Investment | R96: =TEXT(B96,"MMM YYYY") -> Jan 2026
A97: UA6A92YM5S | B97: 2026-01-06 10:33:28 | C97: Pay Bill Online to 4072222 - NABO CAPITAL LTD C2B Acc. PFCMKU | D97: Completed | F97: 100 | G97: 40 | L97: =IF(ISNUMBER(SEARCH("Bundle",C97)),"Bundles",IF(ISNUMBER(SEARCH("Airtime",C97)),"Bundles",IF(ISNUMBER(SEARCH("Merchant",C97)),"Merchant Payment",IF(ISNUMBER(SEARCH("Offnet C2B",C97)),"Merchant Payment",IF(ISNUMBER(SEARCH("Offnet B2C",C97)),"Merchant Payment",IF(ISNUMBER(SEARCH("Customer Payment to Small",C97)),"Merchant Payment",IF(ISNUMBER(SEARCH("Payment to Small Business",C97)),"Merchant Payment",IF(ISNUMBER(SEARCH("Sent to",C97)),"Sent to Person",IF(ISNUMBER(SEARCH("Customer Transfer to",C97)),"Sent to Person",IF(ISNUMBER(SEARCH("Business Payment",C97)),"Money In",IF(ISNUMBER(SEARCH("Funds Received",C97)),"Money In",IF(ISNUMBER(SEARCH("Receive International",C97)),"Money In",IF(ISNUMBER(SEARCH("Send Money Reversal",C97)),"Money In",IF(ISNUMBER(SEARCH("Pay Utility Reversal",C97)),"Money In",IF(ISNUMBER(SEARCH("Customer Transfer",C97)),"Money In",IF(ISNUMBER(SEARCH("Ziidi",C97)),"Investment",IF(ISNUMBER(SEARCH("Nabo",C97)),"Investment",IF(ISNUMBER(SEARCH("Paybill Online",C97)),"Pay Bill",IF(ISNUMBER(SEARCH("Pay Bill",C97)),"Pay Bill",IF(ISNUMBER(SEARCH("Spotify",C97)),"Pay Bill",IF(ISNUMBER(SEARCH("M-Shwari",C97)),"Mshwari",IF(ISNUMBER(SEARCH("Mshwari",C97)),"Mshwari",IF(ISNUMBER(SEARCH("Withdrawal charge",C97)),"Fees",IF(ISNUMBER(SEARCH("Customer Withdrawal",C97)),"Fees",IF(ISNUMBER(SEARCH("charge",C97)),"Fees","Other"))))))))))))))))))))))))) -> Investment | R97: =TEXT(B97,"MMM YYYY") -> Jan 2026
A98: UA7A931HL7 | B98: 2026-01-07 05:10:21 | C98: Customer Bundle Purchase to 4093441SAFARICOM DATA BUNDLES by - 2547******109 NAOMI MUREITHI | D98: Completed | F98: 10 | G98: 30 | L98: =IF(ISNUMBER(SEARCH("Bundle",C98)),"Bundles",IF(ISNUMBER(SEARCH("Airtime",C98)),"Bundles",IF(ISNUMBER(SEARCH("Merchant",C98)),"Merchant Payment",IF(ISNUMBER(SEARCH("Offnet C2B",C98)),"Merchant Payment",IF(ISNUMBER(SEARCH("Offnet B2C",C98)),"Merchant Payment",IF(ISNUMBER(SEARCH("Customer Payment to Small",C98)),"Merchant Payment",IF(ISNUMBER(SEARCH("Payment to Small Business",C98)),"Merchant Payment",IF(ISNUMBER(SEARCH("Sent to",C98)),"Sent to Person",IF(ISNUMBER(SEARCH("Customer Transfer to",C98)),"Sent to Person",IF(ISNUMBER(SEARCH("Business Payment",C98)),"Money In",IF(ISNUMBER(SEARCH("Funds Received",C98)),"Money In",IF(ISNUMBER(SEARCH("Receive International",C98)),"Money In",IF(ISNUMBER(SEARCH("Send Money Reversal",C98)),"Money In",IF(ISNUMBER(SEARCH("Pay Utility Reversal",C98)),"Money In",IF(ISNUMBER(SEARCH("Customer Transfer",C98)),"Money In",IF(ISNUMBER(SEARCH("Ziidi",C98)),"Investment",IF(ISNUMBER(SEARCH("Nabo",C98)),"Investment",IF(ISNUMBER(SEARCH("Paybill Online",C98)),"Pay Bill",IF(ISNUMBER(SEARCH("Pay Bill",C98)),"Pay Bill",IF(ISNUMBER(SEARCH("Spotify",C98)),"Pay Bill",IF(ISNUMBER(SEARCH("M-Shwari",C98)),"Mshwari",IF(ISNUMBER(SEARCH("Mshwari",C98)),"Mshwari",IF(ISNUMBER(SEARCH("Withdrawal charge",C98)),"Fees",IF(ISNUMBER(SEARCH("Customer Withdrawal",C98)),"Fees",IF(ISNUMBER(SEARCH("charge",C98)),"Fees","Other"))))))))))))))))))))))))) -> Bundles | R98: =TEXT(B98,"MMM YYYY") -> Jan 2026
A99: UA7A932EUR | B99: 2026-01-07 12:50:20 | C99: Customer Bundle Purchase to 4093441SAFARICOM DATA BUNDLES by - 2547******109 NAOMI MUREITHI | D99: Completed | F99: 10 | G99: 20 | L99: =IF(ISNUMBER(SEARCH("Bundle",C99)),"Bundles",IF(ISNUMBER(SEARCH("Airtime",C99)),"Bundles",IF(ISNUMBER(SEARCH("Merchant",C99)),"Merchant Payment",IF(ISNUMBER(SEARCH("Offnet C2B",C99)),"Merchant Payment",IF(ISNUMBER(SEARCH("Offnet B2C",C99)),"Merchant Payment",IF(ISNUMBER(SEARCH("Customer Payment to Small",C99)),"Merchant Payment",IF(ISNUMBER(SEARCH("Payment to Small Business",C99)),"Merchant Payment",IF(ISNUMBER(SEARCH("Sent to",C99)),"Sent to Person",IF(ISNUMBER(SEARCH("Customer Transfer to",C99)),"Sent to Person",IF(ISNUMBER(SEARCH("Business Payment",C99)),"Money In",IF(ISNUMBER(SEARCH("Funds Received",C99)),"Money In",IF(ISNUMBER(SEARCH("Receive International",C99)),"Money In",IF(ISNUMBER(SEARCH("Send Money Reversal",C99)),"Money In",IF(ISNUMBER(SEARCH("Pay Utility Reversal",C99)),"Money In",IF(ISNUMBER(SEARCH("Customer Transfer",C99)),"Money In",IF(ISNUMBER(SEARCH("Ziidi",C99)),"Investment",IF(ISNUMBER(SEARCH("Nabo",C99)),"Investment",IF(ISNUMBER(SEARCH("Paybill Online",C99)),"Pay Bill",IF(ISNUMBER(SEARCH("Pay Bill",C99)),"Pay Bill",IF(ISNUMBER(SEARCH("Spotify",C99)),"Pay Bill",IF(ISNUMBER(SEARCH("M-Shwari",C99)),"Mshwari",IF(ISNUMBER(SEARCH("Mshwari",C99)),"Mshwari",IF(ISNUMBER(SEARCH("Withdrawal charge",C99)),"Fees",IF(ISNUMBER(SEARCH("Customer Withdrawal",C99)),"Fees",IF(ISNUMBER(SEARCH("charge",C99)),"Fees","Other"))))))))))))))))))))))))) -> Bundles | R99: =TEXT(B99,"MMM YYYY") -> Jan 2026
A100: UA7A932LWZ | B100: 2026-01-07 13:41:01 | C100: M-Shwari Withdraw | D100: Completed | E100: 500 | G100: 520 | L100: =IF(ISNUMBER(SEARCH("Bundle",C100)),"Bundles",IF(ISNUMBER(SEARCH("Airtime",C100)),"Bundles",IF(ISNUMBER(SEARCH("Merchant",C100)),"Merchant Payment",IF(ISNUMBER(SEARCH("Offnet C2B",C100)),"Merchant Payment",IF(ISNUMBER(SEARCH("Offnet B2C",C100)),"Merchant Payment",IF(ISNUMBER(SEARCH("Customer Payment to Small",C100)),"Merchant Payment",IF(ISNUMBER(SEARCH("Payment to Small Business",C100)),"Merchant Payment",IF(ISNUMBER(SEARCH("Sent to",C100)),"Sent to Person",IF(ISNUMBER(SEARCH("Customer Transfer to",C100)),"Sent to Person",IF(ISNUMBER(SEARCH("Business Payment",C100)),"Money In",IF(ISNUMBER(SEARCH("Funds Received",C100)),"Money In",IF(ISNUMBER(SEARCH("Receive International",C100)),"Money In",IF(ISNUMBER(SEARCH("Send Money Reversal",C100)),"Money In",IF(ISNUMBER(SEARCH("Pay Utility Reversal",C100)),"Money In",IF(ISNUMBER(SEARCH("Customer Transfer",C100)),"Money In",IF(ISNUMBER(SEARCH("Ziidi",C100)),"Investment",IF(ISNUMBER(SEARCH("Nabo",C100)),"Investment",IF(ISNUMBER(SEARCH("Paybill Online",C100)),"Pay Bill",IF(ISNUMBER(SEARCH("Pay Bill",C100)),"Pay Bill",IF(ISNUMBER(SEARCH("Spotify",C100)),"Pay Bill",IF(ISNUMBER(SEARCH("M-Shwari",C100)),"Mshwari",IF(ISNUMBER(SEARCH("Mshwari",C100)),"Mshwari",IF(ISNUMBER(SEARCH("Withdrawal charge",C100)),"Fees",IF(ISNUMBER(SEARCH("Customer Withdrawal",C100)),"Fees",IF(ISNUMBER(SEARCH("charge",C100)),"Fees","Other"))))))))))))))))))))))))) -> Mshwari | R100: =TEXT(B100,"MMM YYYY") -> Jan 2026
A101: UA7A932KGE | B101: 2026-01-07 13:41:42 | C101: Customer Transfer of Funds Charge | D101: Completed | F101: 7 | G101: 313 | L101: =IF(ISNUMBER(SEARCH("Bundle",C101)),"Bundles",IF(ISNUMBER(SEARCH("Airtime",C101)),"Bundles",IF(ISNUMBER(SEARCH("Merchant",C101)),"Merchant Payment",IF(ISNUMBER(SEARCH("Offnet C2B",C101)),"Merchant Payment",IF(ISNUMBER(SEARCH("Offnet B2C",C101)),"Merchant Payment",IF(ISNUMBER(SEARCH("Customer Payment to Small",C101)),"Merchant Payment",IF(ISNUMBER(SEARCH("Payment to Small Business",C101)),"Merchant Payment",IF(ISNUMBER(SEARCH("Sent to",C101)),"Sent to Person",IF(ISNUMBER(SEARCH("Customer Transfer to",C101)),"Sent to Person",IF(ISNUMBER(SEARCH("Business Payment",C101)),"Money In",IF(ISNUMBER(SEARCH("Funds Received",C101)),"Money In",IF(ISNUMBER(SEARCH("Receive International",C101)),"Money In",IF(ISNUMBER(SEARCH("Send Money Reversal",C101)),"Money In",IF(ISNUMBER(SEARCH("Pay Utility Reversal",C101)),"Money In",IF(ISNUMBER(SEARCH("Customer Transfer",C101)),"Money In",IF(ISNUMBER(SEARCH("Ziidi",C101)),"Investment",IF(ISNUMBER(SEARCH("Nabo",C101)),"Investment",IF(ISNUMBER(SEARCH("Paybill Online",C101)),"Pay Bill",IF(ISNUMBER(SEARCH("Pay Bill",C101)),"Pay Bill",IF(ISNUMBER(SEARCH("Spotify",C101)),"Pay Bill",IF(ISNUMBER(SEARCH("M-Shwari",C101)),"Mshwari",IF(ISNUMBER(SEARCH("Mshwari",C101)),"Mshwari",IF(ISNUMBER(SEARCH("Withdrawal charge",C101)),"Fees",IF(ISNUMBER(SEARCH("Customer Withdrawal",C101)),"Fees",IF(ISNUMBER(SEARCH("charge",C101)),"Fees","Other"))))))))))))))))))))))))) -> Money In | R101: =TEXT(B101,"MMM YYYY") -> Jan 2026
A102: UA7A932KGE | B102: 2026-01-07 13:41:42 | C102: Customer Payment to Small Business to - 01******856 sadaty musa | D102: Completed | F102: 200 | G102: 320 | L102: =IF(ISNUMBER(SEARCH("Bundle",C102)),"Bundles",IF(ISNUMBER(SEARCH("Airtime",C102)),"Bundles",IF(ISNUMBER(SEARCH("Merchant",C102)),"Merchant Payment",IF(ISNUMBER(SEARCH("Offnet C2B",C102)),"Merchant Payment",IF(ISNUMBER(SEARCH("Offnet B2C",C102)),"Merchant Payment",IF(ISNUMBER(SEARCH("Customer Payment to Small",C102)),"Merchant Payment",IF(ISNUMBER(SEARCH("Payment to Small Business",C102)),"Merchant Payment",IF(ISNUMBER(SEARCH("Sent to",C102)),"Sent to Person",IF(ISNUMBER(SEARCH("Customer Transfer to",C102)),"Sent to Person",IF(ISNUMBER(SEARCH("Business Payment",C102)),"Money In",IF(ISNUMBER(SEARCH("Funds Received",C102)),"Money In",IF(ISNUMBER(SEARCH("Receive International",C102)),"Money In",IF(ISNUMBER(SEARCH("Send Money Reversal",C102)),"Money In",IF(ISNUMBER(SEARCH("Pay Utility Reversal",C102)),"Money In",IF(ISNUMBER(SEARCH("Customer Transfer",C102)),"Money In",IF(ISNUMBER(SEARCH("Ziidi",C102)),"Investment",IF(ISNUMBER(SEARCH("Nabo",C102)),"Investment",IF(ISNUMBER(SEARCH("Paybill Online",C102)),"Pay Bill",IF(ISNUMBER(SEARCH("Pay Bill",C102)),"Pay Bill",IF(ISNUMBER(SEARCH("Spotify",C102)),"Pay Bill",IF(ISNUMBER(SEARCH("M-Shwari",C102)),"Mshwari",IF(ISNUMBER(SEARCH("Mshwari",C102)),"Mshwari",IF(ISNUMBER(SEARCH("Withdrawal charge",C102)),"Fees",IF(ISNUMBER(SEARCH("Customer Withdrawal",C102)),"Fees",IF(ISNUMBER(SEARCH("charge",C102)),"Fees","Other"))))))))))))))))))))))))) -> Merchant Payment | R102: =TEXT(B102,"MMM YYYY") -> Jan 2026
A103: UA7A932HO5 | B103: 2026-01-07 13:43:16 | C103: Customer Payment to Small Business to - 07******180 CONSOLATER ODUOR | D103: Completed | F103: 70 | G103: 243 | L103: =IF(ISNUMBER(SEARCH("Bundle",C103)),"Bundles",IF(ISNUMBER(SEARCH("Airtime",C103)),"Bundles",IF(ISNUMBER(SEARCH("Merchant",C103)),"Merchant Payment",IF(ISNUMBER(SEARCH("Offnet C2B",C103)),"Merchant Payment",IF(ISNUMBER(SEARCH("Offnet B2C",C103)),"Merchant Payment",IF(ISNUMBER(SEARCH("Customer Payment to Small",C103)),"Merchant Payment",IF(ISNUMBER(SEARCH("Payment to Small Business",C103)),"Merchant Payment",IF(ISNUMBER(SEARCH("Sent to",C103)),"Sent to Person",IF(ISNUMBER(SEARCH("Customer Transfer to",C103)),"Sent to Person",IF(ISNUMBER(SEARCH("Business Payment",C103)),"Money In",IF(ISNUMBER(SEARCH("Funds Received",C103)),"Money In",IF(ISNUMBER(SEARCH("Receive International",C103)),"Money In",IF(ISNUMBER(SEARCH("Send Money Reversal",C103)),"Money In",IF(ISNUMBER(SEARCH("Pay Utility Reversal",C103)),"Money In",IF(ISNUMBER(SEARCH("Customer Transfer",C103)),"Money In",IF(ISNUMBER(SEARCH("Ziidi",C103)),"Investment",IF(ISNUMBER(SEARCH("Nabo",C103)),"Investment",IF(ISNUMBER(SEARCH("Paybill Online",C103)),"Pay Bill",IF(ISNUMBER(SEARCH("Pay Bill",C103)),"Pay Bill",IF(ISNUMBER(SEARCH("Spotify",C103)),"Pay Bill",IF(ISNUMBER(SEARCH("M-Shwari",C103)),"Mshwari",IF(ISNUMBER(SEARCH("Mshwari",C103)),"Mshwari",IF(ISNUMBER(SEARCH("Withdrawal charge",C103)),"Fees",IF(ISNUMBER(SEARCH("Customer Withdrawal",C103)),"Fees",IF(ISNUMBER(SEARCH("charge",C103)),"Fees","Other"))))))))))))))))))))))))) -> Merchant Payment | R103: =TEXT(B103,"MMM YYYY") -> Jan 2026
A104: UA7A932KM5 | B104: 2026-01-07 13:51:37 | C104: Customer Transfer of Funds Charge | D104: Completed | F104: 7 | G104: 96 | L104: =IF(ISNUMBER(SEARCH("Bundle",C104)),"Bundles",IF(ISNUMBER(SEARCH("Airtime",C104)),"Bundles",IF(ISNUMBER(SEARCH("Merchant",C104)),"Merchant Payment",IF(ISNUMBER(SEARCH("Offnet C2B",C104)),"Merchant Payment",IF(ISNUMBER(SEARCH("Offnet B2C",C104)),"Merchant Payment",IF(ISNUMBER(SEARCH("Customer Payment to Small",C104)),"Merchant Payment",IF(ISNUMBER(SEARCH("Payment to Small Business",C104)),"Merchant Payment",IF(ISNUMBER(SEARCH("Sent to",C104)),"Sent to Person",IF(ISNUMBER(SEARCH("Customer Transfer to",C104)),"Sent to Person",IF(ISNUMBER(SEARCH("Business Payment",C104)),"Money In",IF(ISNUMBER(SEARCH("Funds Received",C104)),"Money In",IF(ISNUMBER(SEARCH("Receive International",C104)),"Money In",IF(ISNUMBER(SEARCH("Send Money Reversal",C104)),"Money In",IF(ISNUMBER(SEARCH("Pay Utility Reversal",C104)),"Money In",IF(ISNUMBER(SEARCH("Customer Transfer",C104)),"Money In",IF(ISNUMBER(SEARCH("Ziidi",C104)),"Investment",IF(ISNUMBER(SEARCH("Nabo",C104)),"Investment",IF(ISNUMBER(SEARCH("Paybill Online",C104)),"Pay Bill",IF(ISNUMBER(SEARCH("Pay Bill",C104)),"Pay Bill",IF(ISNUMBER(SEARCH("Spotify",C104)),"Pay Bill",IF(ISNUMBER(SEARCH("M-Shwari",C104)),"Mshwari",IF(ISNUMBER(SEARCH("Mshwari",C104)),"Mshwari",IF(ISNUMBER(SEARCH("Withdrawal charge",C104)),"Fees",IF(ISNUMBER(SEARCH("Customer Withdrawal",C104)),"Fees",IF(ISNUMBER(SEARCH("charge",C104)),"Fees","Other"))))))))))))))))))))))))) -> Money In | R104: =TEXT(B104,"MMM YYYY") -> Jan 2026
A105: UA7A932KM5 | B105: 2026-01-07 13:51:37 | C105: Customer Payment to Small Business to - 2541******999 YATINKUMAR PATEL | D105: Completed | F105: 140 | G105: 103 | L105: =IF(ISNUMBER(SEARCH("Bundle",C105)),"Bundles",IF(ISNUMBER(SEARCH("Airtime",C105)),"Bundles",IF(ISNUMBER(SEARCH("Merchant",C105)),"Merchant Payment",IF(ISNUMBER(SEARCH("Offnet C2B",C105)),"Merchant Payment",IF(ISNUMBER(SEARCH("Offnet B2C",C105)),"Merchant Payment",IF(ISNUMBER(SEARCH("Customer Payment to Small",C105)),"Merchant Payment",IF(ISNUMBER(SEARCH("Payment to Small Business",C105)),"Merchant Payment",IF(ISNUMBER(SEARCH("Sent to",C105)),"Sent to Person",IF(ISNUMBER(SEARCH("Customer Transfer to",C105)),"Sent to Person",IF(ISNUMBER(SEARCH("Business Payment",C105)),"Money In",IF(ISNUMBER(SEARCH("Funds Received",C105)),"Money In",IF(ISNUMBER(SEARCH("Receive International",C105)),"Money In",IF(ISNUMBER(SEARCH("Send Money Reversal",C105)),"Money In",IF(ISNUMBER(SEARCH("Pay Utility Reversal",C105)),"Money In",IF(ISNUMBER(SEARCH("Customer Transfer",C105)),"Money In",IF(ISNUMBER(SEARCH("Ziidi",C105)),"Investment",IF(ISNUMBER(SEARCH("Nabo",C105)),"Investment",IF(ISNUMBER(SEARCH("Paybill Online",C105)),"Pay Bill",IF(ISNUMBER(SEARCH("Pay Bill",C105)),"Pay Bill",IF(ISNUMBER(SEARCH("Spotify",C105)),"Pay Bill",IF(ISNUMBER(SEARCH("M-Shwari",C105)),"Mshwari",IF(ISNUMBER(SEARCH("Mshwari",C105)),"Mshwari",IF(ISNUMBER(SEARCH("Withdrawal charge",C105)),"Fees",IF(ISNUMBER(SEARCH("Customer Withdrawal",C105)),"Fees",IF(ISNUMBER(SEARCH("charge",C105)),"Fees","Other"))))))))))))))))))))))))) -> Merchant Payment | R105: =TEXT(B105,"MMM YYYY") -> Jan 2026
A106: UA7A932NSV | B106: 2026-01-07 14:07:35 | C106: Offnet C2B Transfer to 585555 - AIRTEL MONEY. for Mobile No. 254782822044 | D106: Completed | F106: 50 | G106: 46 | L106: =IF(ISNUMBER(SEARCH("Bundle",C106)),"Bundles",IF(ISNUMBER(SEARCH("Airtime",C106)),"Bundles",IF(ISNUMBER(SEARCH("Merchant",C106)),"Merchant Payment",IF(ISNUMBER(SEARCH("Offnet C2B",C106)),"Merchant Payment",IF(ISNUMBER(SEARCH("Offnet B2C",C106)),"Merchant Payment",IF(ISNUMBER(SEARCH("Customer Payment to Small",C106)),"Merchant Payment",IF(ISNUMBER(SEARCH("Payment to Small Business",C106)),"Merchant Payment",IF(ISNUMBER(SEARCH("Sent to",C106)),"Sent to Person",IF(ISNUMBER(SEARCH("Customer Transfer to",C106)),"Sent to Person",IF(ISNUMBER(SEARCH("Business Payment",C106)),"Money In",IF(ISNUMBER(SEARCH("Funds Received",C106)),"Money In",IF(ISNUMBER(SEARCH("Receive International",C106)),"Money In",IF(ISNUMBER(SEARCH("Send Money Reversal",C106)),"Money In",IF(ISNUMBER(SEARCH("Pay Utility Reversal",C106)),"Money In",IF(ISNUMBER(SEARCH("Customer Transfer",C106)),"Money In",IF(ISNUMBER(SEARCH("Ziidi",C106)),"Investment",IF(ISNUMBER(SEARCH("Nabo",C106)),"Investment",IF(ISNUMBER(SEARCH("Paybill Online",C106)),"Pay Bill",IF(ISNUMBER(SEARCH("Pay Bill",C106)),"Pay Bill",IF(ISNUMBER(SEARCH("Spotify",C106)),"Pay Bill",IF(ISNUMBER(SEARCH("M-Shwari",C106)),"Mshwari",IF(ISNUMBER(SEARCH("Mshwari",C106)),"Mshwari",IF(ISNUMBER(SEARCH("Withdrawal charge",C106)),"Fees",IF(ISNUMBER(SEARCH("Customer Withdrawal",C106)),"Fees",IF(ISNUMBER(SEARCH("charge",C106)),"Fees","Other"))))))))))))))))))))))))) -> Merchant Payment | R106: =TEXT(B106,"MMM YYYY") -> Jan 2026
A107: UA7A932PWV | B107: 2026-01-07 14:42:45 | C107: Customer Bundle Purchase to 4093441SAFARICOM DATA BUNDLES by - 2547******109 NAOMI MUREITHI | D107: Completed | F107: 30 | G107: 16 | L107: =IF(ISNUMBER(SEARCH("Bundle",C107)),"Bundles",IF(ISNUMBER(SEARCH("Airtime",C107)),"Bundles",IF(ISNUMBER(SEARCH("Merchant",C107)),"Merchant Payment",IF(ISNUMBER(SEARCH("Offnet C2B",C107)),"Merchant Payment",IF(ISNUMBER(SEARCH("Offnet B2C",C107)),"Merchant Payment",IF(ISNUMBER(SEARCH("Customer Payment to Small",C107)),"Merchant Payment",IF(ISNUMBER(SEARCH("Payment to Small Business",C107)),"Merchant Payment",IF(ISNUMBER(SEARCH("Sent to",C107)),"Sent to Person",IF(ISNUMBER(SEARCH("Customer Transfer to",C107)),"Sent to Person",IF(ISNUMBER(SEARCH("Business Payment",C107)),"Money In",IF(ISNUMBER(SEARCH("Funds Received",C107)),"Money In",IF(ISNUMBER(SEARCH("Receive International",C107)),"Money In",IF(ISNUMBER(SEARCH("Send Money Reversal",C107)),"Money In",IF(ISNUMBER(SEARCH("Pay Utility Reversal",C107)),"Money In",IF(ISNUMBER(SEARCH("Customer Transfer",C107)),"Money In",IF(ISNUMBER(SEARCH("Ziidi",C107)),"Investment",IF(ISNUMBER(SEARCH("Nabo",C107)),"Investment",IF(ISNUMBER(SEARCH("Paybill Online",C107)),"Pay Bill",IF(ISNUMBER(SEARCH("Pay Bill",C107)),"Pay Bill",IF(ISNUMBER(SEARCH("Spotify",C107)),"Pay Bill",IF(ISNUMBER(SEARCH("M-Shwari",C107)),"Mshwari",IF(ISNUMBER(SEARCH("Mshwari",C107)),"Mshwari",IF(ISNUMBER(SEARCH("Withdrawal charge",C107)),"Fees",IF(ISNUMBER(SEARCH("Customer Withdrawal",C107)),"Fees",IF(ISNUMBER(SEARCH("charge",C107)),"Fees","Other"))))))))))))))))))))))))) -> Bundles | R107: =TEXT(B107,"MMM YYYY") -> Jan 2026
A108: UA7A9347YB | B108: 2026-01-07 20:57:30 | C108: M-Shwari Withdraw | D108: Completed | E108: 500 | G108: 516 | L108: =IF(ISNUMBER(SEARCH("Bundle",C108)),"Bundles",IF(ISNUMBER(SEARCH("Airtime",C108)),"Bundles",IF(ISNUMBER(SEARCH("Merchant",C108)),"Merchant Payment",IF(ISNUMBER(SEARCH("Offnet C2B",C108)),"Merchant Payment",IF(ISNUMBER(SEARCH("Offnet B2C",C108)),"Merchant Payment",IF(ISNUMBER(SEARCH("Customer Payment to Small",C108)),"Merchant Payment",IF(ISNUMBER(SEARCH("Payment to Small Business",C108)),"Merchant Payment",IF(ISNUMBER(SEARCH("Sent to",C108)),"Sent to Person",IF(ISNUMBER(SEARCH("Customer Transfer to",C108)),"Sent to Person",IF(ISNUMBER(SEARCH("Business Payment",C108)),"Money In",IF(ISNUMBER(SEARCH("Funds Received",C108)),"Money In",IF(ISNUMBER(SEARCH("Receive International",C108)),"Money In",IF(ISNUMBER(SEARCH("Send Money Reversal",C108)),"Money In",IF(ISNUMBER(SEARCH("Pay Utility Reversal",C108)),"Money In",IF(ISNUMBER(SEARCH("Customer Transfer",C108)),"Money In",IF(ISNUMBER(SEARCH("Ziidi",C108)),"Investment",IF(ISNUMBER(SEARCH("Nabo",C108)),"Investment",IF(ISNUMBER(SEARCH("Paybill Online",C108)),"Pay Bill",IF(ISNUMBER(SEARCH("Pay Bill",C108)),"Pay Bill",IF(ISNUMBER(SEARCH("Spotify",C108)),"Pay Bill",IF(ISNUMBER(SEARCH("M-Shwari",C108)),"Mshwari",IF(ISNUMBER(SEARCH("Mshwari",C108)),"Mshwari",IF(ISNUMBER(SEARCH("Withdrawal charge",C108)),"Fees",IF(ISNUMBER(SEARCH("Customer Withdrawal",C108)),"Fees",IF(ISNUMBER(SEARCH("charge",C108)),"Fees","Other"))))))))))))))))))))))))) -> Mshwari | R108: =TEXT(B108,"MMM YYYY") -> Jan 2026
A109: UA7A9349XP | B109: 2026-01-07 20:58:34 | C109: Customer Bundle Purchase to 4093441SAFARICOM DATA BUNDLES by - 2547******109 NAOMI MUREITHI | D109: Completed | F109: 30 | G109: 486 | L109: =IF(ISNUMBER(SEARCH("Bundle",C109)),"Bundles",IF(ISNUMBER(SEARCH("Airtime",C109)),"Bundles",IF(ISNUMBER(SEARCH("Merchant",C109)),"Merchant Payment",IF(ISNUMBER(SEARCH("Offnet C2B",C109)),"Merchant Payment",IF(ISNUMBER(SEARCH("Offnet B2C",C109)),"Merchant Payment",IF(ISNUMBER(SEARCH("Customer Payment to Small",C109)),"Merchant Payment",IF(ISNUMBER(SEARCH("Payment to Small Business",C109)),"Merchant Payment",IF(ISNUMBER(SEARCH("Sent to",C109)),"Sent to Person",IF(ISNUMBER(SEARCH("Customer Transfer to",C109)),"Sent to Person",IF(ISNUMBER(SEARCH("Business Payment",C109)),"Money In",IF(ISNUMBER(SEARCH("Funds Received",C109)),"Money In",IF(ISNUMBER(SEARCH("Receive International",C109)),"Money In",IF(ISNUMBER(SEARCH("Send Money Reversal",C109)),"Money In",IF(ISNUMBER(SEARCH("Pay Utility Reversal",C109)),"Money In",IF(ISNUMBER(SEARCH("Customer Transfer",C109)),"Money In",IF(ISNUMBER(SEARCH("Ziidi",C109)),"Investment",IF(ISNUMBER(SEARCH("Nabo",C109)),"Investment",IF(ISNUMBER(SEARCH("Paybill Online",C109)),"Pay Bill",IF(ISNUMBER(SEARCH("Pay Bill",C109)),"Pay Bill",IF(ISNUMBER(SEARCH("Spotify",C109)),"Pay Bill",IF(ISNUMBER(SEARCH("M-Shwari",C109)),"Mshwari",IF(ISNUMBER(SEARCH("Mshwari",C109)),"Mshwari",IF(ISNUMBER(SEARCH("Withdrawal charge",C109)),"Fees",IF(ISNUMBER(SEARCH("Customer Withdrawal",C109)),"Fees",IF(ISNUMBER(SEARCH("charge",C109)),"Fees","Other"))))))))))))))))))))))))) -> Bundles | R109: =TEXT(B109,"MMM YYYY") -> Jan 2026
A110: UA8A934UD0 | B110: 2026-01-08 05:44:11 | C110: Customer Bundle Purchase to 4093441SAFARICOM DATA BUNDLES by - 2547******109 NAOMI MUREITHI | D110: Completed | F110: 10 | G110: 476 | L110: =IF(ISNUMBER(SEARCH("Bundle",C110)),"Bundles",IF(ISNUMBER(SEARCH("Airtime",C110)),"Bundles",IF(ISNUMBER(SEARCH("Merchant",C110)),"Merchant Payment",IF(ISNUMBER(SEARCH("Offnet C2B",C110)),"Merchant Payment",IF(ISNUMBER(SEARCH("Offnet B2C",C110)),"Merchant Payment",IF(ISNUMBER(SEARCH("Customer Payment to Small",C110)),"Merchant Payment",IF(ISNUMBER(SEARCH("Payment to Small Business",C110)),"Merchant Payment",IF(ISNUMBER(SEARCH("Sent to",C110)),"Sent to Person",IF(ISNUMBER(SEARCH("Customer Transfer to",C110)),"Sent to Person",IF(ISNUMBER(SEARCH("Business Payment",C110)),"Money In",IF(ISNUMBER(SEARCH("Funds Received",C110)),"Money In",IF(ISNUMBER(SEARCH("Receive International",C110)),"Money In",IF(ISNUMBER(SEARCH("Send Money Reversal",C110)),"Money In",IF(ISNUMBER(SEARCH("Pay Utility Reversal",C110)),"Money In",IF(ISNUMBER(SEARCH("Customer Transfer",C110)),"Money In",IF(ISNUMBER(SEARCH("Ziidi",C110)),"Investment",IF(ISNUMBER(SEARCH("Nabo",C110)),"Investment",IF(ISNUMBER(SEARCH("Paybill Online",C110)),"Pay Bill",IF(ISNUMBER(SEARCH("Pay Bill",C110)),"Pay Bill",IF(ISNUMBER(SEARCH("Spotify",C110)),"Pay Bill",IF(ISNUMBER(SEARCH("M-Shwari",C110)),"Mshwari",IF(ISNUMBER(SEARCH("Mshwari",C110)),"Mshwari",IF(ISNUMBER(SEARCH("Withdrawal charge",C110)),"Fees",IF(ISNUMBER(SEARCH("Customer Withdrawal",C110)),"Fees",IF(ISNUMBER(SEARCH("charge",C110)),"Fees","Other"))))))))))))))))))))))))) -> Bundles | R110: =TEXT(B110,"MMM YYYY") -> Jan 2026
A111: UA8A935H1U | B111: 2026-01-08 10:59:04 | C111: Customer Bundle Purchase to 4093441SAFARICOM DATA BUNDLES by - 2547******109 NAOMI MUREITHI | D111: Completed | F111: 5 | G111: 471 | L111: =IF(ISNUMBER(SEARCH("Bundle",C111)),"Bundles",IF(ISNUMBER(SEARCH("Airtime",C111)),"Bundles",IF(ISNUMBER(SEARCH("Merchant",C111)),"Merchant Payment",IF(ISNUMBER(SEARCH("Offnet C2B",C111)),"Merchant Payment",IF(ISNUMBER(SEARCH("Offnet B2C",C111)),"Merchant Payment",IF(ISNUMBER(SEARCH("Customer Payment to Small",C111)),"Merchant Payment",IF(ISNUMBER(SEARCH("Payment to Small Business",C111)),"Merchant Payment",IF(ISNUMBER(SEARCH("Sent to",C111)),"Sent to Person",IF(ISNUMBER(SEARCH("Customer Transfer to",C111)),"Sent to Person",IF(ISNUMBER(SEARCH("Business Payment",C111)),"Money In",IF(ISNUMBER(SEARCH("Funds Received",C111)),"Money In",IF(ISNUMBER(SEARCH("Receive International",C111)),"Money In",IF(ISNUMBER(SEARCH("Send Money Reversal",C111)),"Money In",IF(ISNUMBER(SEARCH("Pay Utility Reversal",C111)),"Money In",IF(ISNUMBER(SEARCH("Customer Transfer",C111)),"Money In",IF(ISNUMBER(SEARCH("Ziidi",C111)),"Investment",IF(ISNUMBER(SEARCH("Nabo",C111)),"Investment",IF(ISNUMBER(SEARCH("Paybill Online",C111)),"Pay Bill",IF(ISNUMBER(SEARCH("Pay Bill",C111)),"Pay Bill",IF(ISNUMBER(SEARCH("Spotify",C111)),"Pay Bill",IF(ISNUMBER(SEARCH("M-Shwari",C111)),"Mshwari",IF(ISNUMBER(SEARCH("Mshwari",C111)),"Mshwari",IF(ISNUMBER(SEARCH("Withdrawal charge",C111)),"Fees",IF(ISNUMBER(SEARCH("Customer Withdrawal",C111)),"Fees",IF(ISNUMBER(SEARCH("charge",C111)),"Fees","Other"))))))))))))))))))))))))) -> Bundles | R111: =TEXT(B111,"MMM YYYY") -> Jan 2026
A112: UA8A935Z6W | B112: 2026-01-08 14:18:13 | C112: M-Shwari Withdraw | D112: Completed | E112: 500 | G112: 971 | L112: =IF(ISNUMBER(SEARCH("Bundle",C112)),"Bundles",IF(ISNUMBER(SEARCH("Airtime",C112)),"Bundles",IF(ISNUMBER(SEARCH("Merchant",C112)),"Merchant Payment",IF(ISNUMBER(SEARCH("Offnet C2B",C112)),"Merchant Payment",IF(ISNUMBER(SEARCH("Offnet B2C",C112)),"Merchant Payment",IF(ISNUMBER(SEARCH("Customer Payment to Small",C112)),"Merchant Payment",IF(ISNUMBER(SEARCH("Payment to Small Business",C112)),"Merchant Payment",IF(ISNUMBER(SEARCH("Sent to",C112)),"Sent to Person",IF(ISNUMBER(SEARCH("Customer Transfer to",C112)),"Sent to Person",IF(ISNUMBER(SEARCH("Business Payment",C112)),"Money In",IF(ISNUMBER(SEARCH("Funds Received",C112)),"Money In",IF(ISNUMBER(SEARCH("Receive International",C112)),"Money In",IF(ISNUMBER(SEARCH("Send Money Reversal",C112)),"Money In",IF(ISNUMBER(SEARCH("Pay Utility Reversal",C112)),"Money In",IF(ISNUMBER(SEARCH("Customer Transfer",C112)),"Money In",IF(ISNUMBER(SEARCH("Ziidi",C112)),"Investment",IF(ISNUMBER(SEARCH("Nabo",C112)),"Investment",IF(ISNUMBER(SEARCH("Paybill Online",C112)),"Pay Bill",IF(ISNUMBER(SEARCH("Pay Bill",C112)),"Pay Bill",IF(ISNUMBER(SEARCH("Spotify",C112)),"Pay Bill",IF(ISNUMBER(SEARCH("M-Shwari",C112)),"Mshwari",IF(ISNUMBER(SEARCH("Mshwari",C112)),"Mshwari",IF(ISNUMBER(SEARCH("Withdrawal charge",C112)),"Fees",IF(ISNUMBER(SEARCH("Customer Withdrawal",C112)),"Fees",IF(ISNUMBER(SEARCH("charge",C112)),"Fees","Other"))))))))))))))))))))))))) -> Mshwari | R112: =TEXT(B112,"MMM YYYY") -> Jan 2026
A113: UA8A9360SJ | B113: 2026-01-08 14:19:05 | C113: Merchant Payment to 6275421 - MOSES MUNYALO KATANGA | D113: Completed | F113: 490 | G113: 481 | L113: =IF(ISNUMBER(SEARCH("Bundle",C113)),"Bundles",IF(ISNUMBER(SEARCH("Airtime",C113)),"Bundles",IF(ISNUMBER(SEARCH("Merchant",C113)),"Merchant Payment",IF(ISNUMBER(SEARCH("Offnet C2B",C113)),"Merchant Payment",IF(ISNUMBER(SEARCH("Offnet B2C",C113)),"Merchant Payment",IF(ISNUMBER(SEARCH("Customer Payment to Small",C113)),"Merchant Payment",IF(ISNUMBER(SEARCH("Payment to Small Business",C113)),"Merchant Payment",IF(ISNUMBER(SEARCH("Sent to",C113)),"Sent to Person",IF(ISNUMBER(SEARCH("Customer Transfer to",C113)),"Sent to Person",IF(ISNUMBER(SEARCH("Business Payment",C113)),"Money In",IF(ISNUMBER(SEARCH("Funds Received",C113)),"Money In",IF(ISNUMBER(SEARCH("Receive International",C113)),"Money In",IF(ISNUMBER(SEARCH("Send Money Reversal",C113)),"Money In",IF(ISNUMBER(SEARCH("Pay Utility Reversal",C113)),"Money In",IF(ISNUMBER(SEARCH("Customer Transfer",C113)),"Money In",IF(ISNUMBER(SEARCH("Ziidi",C113)),"Investment",IF(ISNUMBER(SEARCH("Nabo",C113)),"Investment",IF(ISNUMBER(SEARCH("Paybill Online",C113)),"Pay Bill",IF(ISNUMBER(SEARCH("Pay Bill",C113)),"Pay Bill",IF(ISNUMBER(SEARCH("Spotify",C113)),"Pay Bill",IF(ISNUMBER(SEARCH("M-Shwari",C113)),"Mshwari",IF(ISNUMBER(SEARCH("Mshwari",C113)),"Mshwari",IF(ISNUMBER(SEARCH("Withdrawal charge",C113)),"Fees",IF(ISNUMBER(SEARCH("Customer Withdrawal",C113)),"Fees",IF(ISNUMBER(SEARCH("charge",C113)),"Fees","Other"))))))))))))))))))))))))) -> Merchant Payment | R113: =TEXT(B113,"MMM YYYY") -> Jan 2026
A114: UA8A936AM1 | B114: 2026-01-08 14:58:33 | C114: Customer Bundle Purchase to 4093441SAFARICOM DATA BUNDLES by - 2547******109 NAOMI MUREITHI | D114: Completed | F114: 30 | G114: 451 | L114: =IF(ISNUMBER(SEARCH("Bundle",C114)),"Bundles",IF(ISNUMBER(SEARCH("Airtime",C114)),"Bundles",IF(ISNUMBER(SEARCH("Merchant",C114)),"Merchant Payment",IF(ISNUMBER(SEARCH("Offnet C2B",C114)),"Merchant Payment",IF(ISNUMBER(SEARCH("Offnet B2C",C114)),"Merchant Payment",IF(ISNUMBER(SEARCH("Customer Payment to Small",C114)),"Merchant Payment",IF(ISNUMBER(SEARCH("Payment to Small Business",C114)),"Merchant Payment",IF(ISNUMBER(SEARCH("Sent to",C114)),"Sent to Person",IF(ISNUMBER(SEARCH("Customer Transfer to",C114)),"Sent to Person",IF(ISNUMBER(SEARCH("Business Payment",C114)),"Money In",IF(ISNUMBER(SEARCH("Funds Received",C114)),"Money In",IF(ISNUMBER(SEARCH("Receive International",C114)),"Money In",IF(ISNUMBER(SEARCH("Send Money Reversal",C114)),"Money In",IF(ISNUMBER(SEARCH("Pay Utility Reversal",C114)),"Money In",IF(ISNUMBER(SEARCH("Customer Transfer",C114)),"Money In",IF(ISNUMBER(SEARCH("Ziidi",C114)),"Investment",IF(ISNUMBER(SEARCH("Nabo",C114)),"Investment",IF(ISNUMBER(SEARCH("Paybill Online",C114)),"Pay Bill",IF(ISNUMBER(SEARCH("Pay Bill",C114)),"Pay Bill",IF(ISNUMBER(SEARCH("Spotify",C114)),"Pay Bill",IF(ISNUMBER(SEARCH("M-Shwari",C114)),"Mshwari",IF(ISNUMBER(SEARCH("Mshwari",C114)),"Mshwari",IF(ISNUMBER(SEARCH("Withdrawal charge",C114)),"Fees",IF(ISNUMBER(SEARCH("Customer Withdrawal",C114)),"Fees",IF(ISNUMBER(SEARCH("charge",C114)),"Fees","Other"))))))))))))))))))))))))) -> Bundles | R114: =TEXT(B114,"MMM YYYY") -> Jan 2026
A115: UA8A936SCE | B115: 2026-01-08 18:29:35 | C115: Customer Bundle Purchase to 4093441SAFARICOM DATA BUNDLES by - 2547******109 NAOMI MUREITHI | D115: Completed | F115: 10 | G115: 441 | L115: =IF(ISNUMBER(SEARCH("Bundle",C115)),"Bundles",IF(ISNUMBER(SEARCH("Airtime",C115)),"Bundles",IF(ISNUMBER(SEARCH("Merchant",C115)),"Merchant Payment",IF(ISNUMBER(SEARCH("Offnet C2B",C115)),"Merchant Payment",IF(ISNUMBER(SEARCH("Offnet B2C",C115)),"Merchant Payment",IF(ISNUMBER(SEARCH("Customer Payment to Small",C115)),"Merchant Payment",IF(ISNUMBER(SEARCH("Payment to Small Business",C115)),"Merchant Payment",IF(ISNUMBER(SEARCH("Sent to",C115)),"Sent to Person",IF(ISNUMBER(SEARCH("Customer Transfer to",C115)),"Sent to Person",IF(ISNUMBER(SEARCH("Business Payment",C115)),"Money In",IF(ISNUMBER(SEARCH("Funds Received",C115)),"Money In",IF(ISNUMBER(SEARCH("Receive International",C115)),"Money In",IF(ISNUMBER(SEARCH("Send Money Reversal",C115)),"Money In",IF(ISNUMBER(SEARCH("Pay Utility Reversal",C115)),"Money In",IF(ISNUMBER(SEARCH("Customer Transfer",C115)),"Money In",IF(ISNUMBER(SEARCH("Ziidi",C115)),"Investment",IF(ISNUMBER(SEARCH("Nabo",C115)),"Investment",IF(ISNUMBER(SEARCH("Paybill Online",C115)),"Pay Bill",IF(ISNUMBER(SEARCH("Pay Bill",C115)),"Pay Bill",IF(ISNUMBER(SEARCH("Spotify",C115)),"Pay Bill",IF(ISNUMBER(SEARCH("M-Shwari",C115)),"Mshwari",IF(ISNUMBER(SEARCH("Mshwari",C115)),"Mshwari",IF(ISNUMBER(SEARCH("Withdrawal charge",C115)),"Fees",IF(ISNUMBER(SEARCH("Customer Withdrawal",C115)),"Fees",IF(ISNUMBER(SEARCH("charge",C115)),"Fees","Other"))))))))))))))))))))))))) -> Bundles | R115: =TEXT(B115,"MMM YYYY") -> Jan 2026
A116: UA84Q3782Z | B116: 2026-01-08 18:40:18 | C116: Funds received from - 2547******442 PETER MAGANJO | D116: Completed | E116: 3000 | G116: 3441 | L116: =IF(ISNUMBER(SEARCH("Bundle",C116)),"Bundles",IF(ISNUMBER(SEARCH("Airtime",C116)),"Bundles",IF(ISNUMBER(SEARCH("Merchant",C116)),"Merchant Payment",IF(ISNUMBER(SEARCH("Offnet C2B",C116)),"Merchant Payment",IF(ISNUMBER(SEARCH("Offnet B2C",C116)),"Merchant Payment",IF(ISNUMBER(SEARCH("Customer Payment to Small",C116)),"Merchant Payment",IF(ISNUMBER(SEARCH("Payment to Small Business",C116)),"Merchant Payment",IF(ISNUMBER(SEARCH("Sent to",C116)),"Sent to Person",IF(ISNUMBER(SEARCH("Customer Transfer to",C116)),"Sent to Person",IF(ISNUMBER(SEARCH("Business Payment",C116)),"Money In",IF(ISNUMBER(SEARCH("Funds Received",C116)),"Money In",IF(ISNUMBER(SEARCH("Receive International",C116)),"Money In",IF(ISNUMBER(SEARCH("Send Money Reversal",C116)),"Money In",IF(ISNUMBER(SEARCH("Pay Utility Reversal",C116)),"Money In",IF(ISNUMBER(SEARCH("Customer Transfer",C116)),"Money In",IF(ISNUMBER(SEARCH("Ziidi",C116)),"Investment",IF(ISNUMBER(SEARCH("Nabo",C116)),"Investment",IF(ISNUMBER(SEARCH("Paybill Online",C116)),"Pay Bill",IF(ISNUMBER(SEARCH("Pay Bill",C116)),"Pay Bill",IF(ISNUMBER(SEARCH("Spotify",C116)),"Pay Bill",IF(ISNUMBER(SEARCH("M-Shwari",C116)),"Mshwari",IF(ISNUMBER(SEARCH("Mshwari",C116)),"Mshwari",IF(ISNUMBER(SEARCH("Withdrawal charge",C116)),"Fees",IF(ISNUMBER(SEARCH("Customer Withdrawal",C116)),"Fees",IF(ISNUMBER(SEARCH("charge",C116)),"Fees","Other"))))))))))))))))))))))))) -> Money In | R116: =TEXT(B116,"MMM YYYY") -> Jan 2026
A117: UA8A937EV5 | B117: 2026-01-08 20:07:59 | C117: Customer Bundle Purchase to 826915Safaricom Offers by - 2547******109 NAOMI MUREITHI | D117: Completed | F117: 20 | G117: 3421 | L117: =IF(ISNUMBER(SEARCH("Bundle",C117)),"Bundles",IF(ISNUMBER(SEARCH("Airtime",C117)),"Bundles",IF(ISNUMBER(SEARCH("Merchant",C117)),"Merchant Payment",IF(ISNUMBER(SEARCH("Offnet C2B",C117)),"Merchant Payment",IF(ISNUMBER(SEARCH("Offnet B2C",C117)),"Merchant Payment",IF(ISNUMBER(SEARCH("Customer Payment to Small",C117)),"Merchant Payment",IF(ISNUMBER(SEARCH("Payment to Small Business",C117)),"Merchant Payment",IF(ISNUMBER(SEARCH("Sent to",C117)),"Sent to Person",IF(ISNUMBER(SEARCH("Customer Transfer to",C117)),"Sent to Person",IF(ISNUMBER(SEARCH("Business Payment",C117)),"Money In",IF(ISNUMBER(SEARCH("Funds Received",C117)),"Money In",IF(ISNUMBER(SEARCH("Receive International",C117)),"Money In",IF(ISNUMBER(SEARCH("Send Money Reversal",C117)),"Money In",IF(ISNUMBER(SEARCH("Pay Utility Reversal",C117)),"Money In",IF(ISNUMBER(SEARCH("Customer Transfer",C117)),"Money In",IF(ISNUMBER(SEARCH("Ziidi",C117)),"Investment",IF(ISNUMBER(SEARCH("Nabo",C117)),"Investment",IF(ISNUMBER(SEARCH("Paybill Online",C117)),"Pay Bill",IF(ISNUMBER(SEARCH("Pay Bill",C117)),"Pay Bill",IF(ISNUMBER(SEARCH("Spotify",C117)),"Pay Bill",IF(ISNUMBER(SEARCH("M-Shwari",C117)),"Mshwari",IF(ISNUMBER(SEARCH("Mshwari",C117)),"Mshwari",IF(ISNUMBER(SEARCH("Withdrawal charge",C117)),"Fees",IF(ISNUMBER(SEARCH("Customer Withdrawal",C117)),"Fees",IF(ISNUMBER(SEARCH("charge",C117)),"Fees","Other"))))))))))))))))))))))))) -> Bundles | R117: =TEXT(B117,"MMM YYYY") -> Jan 2026
A118: UA8A937H3T | B118: 2026-01-08 20:36:41 | C118: Customer Bundle Purchase to 4093441SAFARICOM DATA BUNDLES by - 2547******109 NAOMI MUREITHI | D118: Completed | F118: 20 | G118: 3401 | L118: =IF(ISNUMBER(SEARCH("Bundle",C118)),"Bundles",IF(ISNUMBER(SEARCH("Airtime",C118)),"Bundles",IF(ISNUMBER(SEARCH("Merchant",C118)),"Merchant Payment",IF(ISNUMBER(SEARCH("Offnet C2B",C118)),"Merchant Payment",IF(ISNUMBER(SEARCH("Offnet B2C",C118)),"Merchant Payment",IF(ISNUMBER(SEARCH("Customer Payment to Small",C118)),"Merchant Payment",IF(ISNUMBER(SEARCH("Payment to Small Business",C118)),"Merchant Payment",IF(ISNUMBER(SEARCH("Sent to",C118)),"Sent to Person",IF(ISNUMBER(SEARCH("Customer Transfer to",C118)),"Sent to Person",IF(ISNUMBER(SEARCH("Business Payment",C118)),"Money In",IF(ISNUMBER(SEARCH("Funds Received",C118)),"Money In",IF(ISNUMBER(SEARCH("Receive International",C118)),"Money In",IF(ISNUMBER(SEARCH("Send Money Reversal",C118)),"Money In",IF(ISNUMBER(SEARCH("Pay Utility Reversal",C118)),"Money In",IF(ISNUMBER(SEARCH("Customer Transfer",C118)),"Money In",IF(ISNUMBER(SEARCH("Ziidi",C118)),"Investment",IF(ISNUMBER(SEARCH("Nabo",C118)),"Investment",IF(ISNUMBER(SEARCH("Paybill Online",C118)),"Pay Bill",IF(ISNUMBER(SEARCH("Pay Bill",C118)),"Pay Bill",IF(ISNUMBER(SEARCH("Spotify",C118)),"Pay Bill",IF(ISNUMBER(SEARCH("M-Shwari",C118)),"Mshwari",IF(ISNUMBER(SEARCH("Mshwari",C118)),"Mshwari",IF(ISNUMBER(SEARCH("Withdrawal charge",C118)),"Fees",IF(ISNUMBER(SEARCH("Customer Withdrawal",C118)),"Fees",IF(ISNUMBER(SEARCH("charge",C118)),"Fees","Other"))))))))))))))))))))))))) -> Bundles | R118: =TEXT(B118,"MMM YYYY") -> Jan 2026
A119: UA9A937ZGF | B119: 2026-01-09 05:48:25 | C119: Customer Bundle Purchase to 4093441SAFARICOM DATA BUNDLES by - 2547******109 NAOMI MUREITHI | D119: Completed | F119: 10 | G119: 3391 | L119: =IF(ISNUMBER(SEARCH("Bundle",C119)),"Bundles",IF(ISNUMBER(SEARCH("Airtime",C119)),"Bundles",IF(ISNUMBER(SEARCH("Merchant",C119)),"Merchant Payment",IF(ISNUMBER(SEARCH("Offnet C2B",C119)),"Merchant Payment",IF(ISNUMBER(SEARCH("Offnet B2C",C119)),"Merchant Payment",IF(ISNUMBER(SEARCH("Customer Payment to Small",C119)),"Merchant Payment",IF(ISNUMBER(SEARCH("Payment to Small Business",C119)),"Merchant Payment",IF(ISNUMBER(SEARCH("Sent to",C119)),"Sent to Person",IF(ISNUMBER(SEARCH("Customer Transfer to",C119)),"Sent to Person",IF(ISNUMBER(SEARCH("Business Payment",C119)),"Money In",IF(ISNUMBER(SEARCH("Funds Received",C119)),"Money In",IF(ISNUMBER(SEARCH("Receive International",C119)),"Money In",IF(ISNUMBER(SEARCH("Send Money Reversal",C119)),"Money In",IF(ISNUMBER(SEARCH("Pay Utility Reversal",C119)),"Money In",IF(ISNUMBER(SEARCH("Customer Transfer",C119)),"Money In",IF(ISNUMBER(SEARCH("Ziidi",C119)),"Investment",IF(ISNUMBER(SEARCH("Nabo",C119)),"Investment",IF(ISNUMBER(SEARCH("Paybill Online",C119)),"Pay Bill",IF(ISNUMBER(SEARCH("Pay Bill",C119)),"Pay Bill",IF(ISNUMBER(SEARCH("Spotify",C119)),"Pay Bill",IF(ISNUMBER(SEARCH("M-Shwari",C119)),"Mshwari",IF(ISNUMBER(SEARCH("Mshwari",C119)),"Mshwari",IF(ISNUMBER(SEARCH("Withdrawal charge",C119)),"Fees",IF(ISNUMBER(SEARCH("Customer Withdrawal",C119)),"Fees",IF(ISNUMBER(SEARCH("charge",C119)),"Fees","Other"))))))))))))))))))))))))) -> Bundles | R119: =TEXT(B119,"MMM YYYY") -> Jan 2026
A120: UA9A938DV8 | B120: 2026-01-09 07:28:54 | C120: Customer Bundle Purchase to 4093441SAFARICOM DATA BUNDLES by - 2547******109 NAOMI MUREITHI | D120: Completed | F120: 20 | G120: 3371 | L120: =IF(ISNUMBER(SEARCH("Bundle",C120)),"Bundles",IF(ISNUMBER(SEARCH("Airtime",C120)),"Bundles",IF(ISNUMBER(SEARCH("Merchant",C120)),"Merchant Payment",IF(ISNUMBER(SEARCH("Offnet C2B",C120)),"Merchant Payment",IF(ISNUMBER(SEARCH("Offnet B2C",C120)),"Merchant Payment",IF(ISNUMBER(SEARCH("Customer Payment to Small",C120)),"Merchant Payment",IF(ISNUMBER(SEARCH("Payment to Small Business",C120)),"Merchant Payment",IF(ISNUMBER(SEARCH("Sent to",C120)),"Sent to Person",IF(ISNUMBER(SEARCH("Customer Transfer to",C120)),"Sent to Person",IF(ISNUMBER(SEARCH("Business Payment",C120)),"Money In",IF(ISNUMBER(SEARCH("Funds Received",C120)),"Money In",IF(ISNUMBER(SEARCH("Receive International",C120)),"Money In",IF(ISNUMBER(SEARCH("Send Money Reversal",C120)),"Money In",IF(ISNUMBER(SEARCH("Pay Utility Reversal",C120)),"Money In",IF(ISNUMBER(SEARCH("Customer Transfer",C120)),"Money In",IF(ISNUMBER(SEARCH("Ziidi",C120)),"Investment",IF(ISNUMBER(SEARCH("Nabo",C120)),"Investment",IF(ISNUMBER(SEARCH("Paybill Online",C120)),"Pay Bill",IF(ISNUMBER(SEARCH("Pay Bill",C120)),"Pay Bill",IF(ISNUMBER(SEARCH("Spotify",C120)),"Pay Bill",IF(ISNUMBER(SEARCH("M-Shwari",C120)),"Mshwari",IF(ISNUMBER(SEARCH("Mshwari",C120)),"Mshwari",IF(ISNUMBER(SEARCH("Withdrawal charge",C120)),"Fees",IF(ISNUMBER(SEARCH("Customer Withdrawal",C120)),"Fees",IF(ISNUMBER(SEARCH("charge",C120)),"Fees","Other"))))))))))))))))))))))))) -> Bundles | R120: =TEXT(B120,"MMM YYYY") -> Jan 2026
A121: UA9A938ELB | B121: 2026-01-09 08:29:44 | C121: Customer Bundle Purchase to 4093441SAFARICOM DATA BUNDLES by - 2547******109 NAOMI MUREITHI | D121: Completed | F121: 10 | G121: 3361 | L121: =IF(ISNUMBER(SEARCH("Bundle",C121)),"Bundles",IF(ISNUMBER(SEARCH("Airtime",C121)),"Bundles",IF(ISNUMBER(SEARCH("Merchant",C121)),"Merchant Payment",IF(ISNUMBER(SEARCH("Offnet C2B",C121)),"Merchant Payment",IF(ISNUMBER(SEARCH("Offnet B2C",C121)),"Merchant Payment",IF(ISNUMBER(SEARCH("Customer Payment to Small",C121)),"Merchant Payment",IF(ISNUMBER(SEARCH("Payment to Small Business",C121)),"Merchant Payment",IF(ISNUMBER(SEARCH("Sent to",C121)),"Sent to Person",IF(ISNUMBER(SEARCH("Customer Transfer to",C121)),"Sent to Person",IF(ISNUMBER(SEARCH("Business Payment",C121)),"Money In",IF(ISNUMBER(SEARCH("Funds Received",C121)),"Money In",IF(ISNUMBER(SEARCH("Receive International",C121)),"Money In",IF(ISNUMBER(SEARCH("Send Money Reversal",C121)),"Money In",IF(ISNUMBER(SEARCH("Pay Utility Reversal",C121)),"Money In",IF(ISNUMBER(SEARCH("Customer Transfer",C121)),"Money In",IF(ISNUMBER(SEARCH("Ziidi",C121)),"Investment",IF(ISNUMBER(SEARCH("Nabo",C121)),"Investment",IF(ISNUMBER(SEARCH("Paybill Online",C121)),"Pay Bill",IF(ISNUMBER(SEARCH("Pay Bill",C121)),"Pay Bill",IF(ISNUMBER(SEARCH("Spotify",C121)),"Pay Bill",IF(ISNUMBER(SEARCH("M-Shwari",C121)),"Mshwari",IF(ISNUMBER(SEARCH("Mshwari",C121)),"Mshwari",IF(ISNUMBER(SEARCH("Withdrawal charge",C121)),"Fees",IF(ISNUMBER(SEARCH("Customer Withdrawal",C121)),"Fees",IF(ISNUMBER(SEARCH("charge",C121)),"Fees","Other"))))))))))))))))))))))))) -> Bundles | R121: =TEXT(B121,"MMM YYYY") -> Jan 2026
A122: UA9A938QUD | B122: 2026-01-09 10:37:45 | C122: Customer Bundle Purchase to 4093441SAFARICOM DATA BUNDLES by - 2547******109 NAOMI MUREITHI | D122: Completed | F122: 10 | G122: 3351 | L122: =IF(ISNUMBER(SEARCH("Bundle",C122)),"Bundles",IF(ISNUMBER(SEARCH("Airtime",C122)),"Bundles",IF(ISNUMBER(SEARCH("Merchant",C122)),"Merchant Payment",IF(ISNUMBER(SEARCH("Offnet C2B",C122)),"Merchant Payment",IF(ISNUMBER(SEARCH("Offnet B2C",C122)),"Merchant Payment",IF(ISNUMBER(SEARCH("Customer Payment to Small",C122)),"Merchant Payment",IF(ISNUMBER(SEARCH("Payment to Small Business",C122)),"Merchant Payment",IF(ISNUMBER(SEARCH("Sent to",C122)),"Sent to Person",IF(ISNUMBER(SEARCH("Customer Transfer to",C122)),"Sent to Person",IF(ISNUMBER(SEARCH("Business Payment",C122)),"Money In",IF(ISNUMBER(SEARCH("Funds Received",C122)),"Money In",IF(ISNUMBER(SEARCH("Receive International",C122)),"Money In",IF(ISNUMBER(SEARCH("Send Money Reversal",C122)),"Money In",IF(ISNUMBER(SEARCH("Pay Utility Reversal",C122)),"Money In",IF(ISNUMBER(SEARCH("Customer Transfer",C122)),"Money In",IF(ISNUMBER(SEARCH("Ziidi",C122)),"Investment",IF(ISNUMBER(SEARCH("Nabo",C122)),"Investment",IF(ISNUMBER(SEARCH("Paybill Online",C122)),"Pay Bill",IF(ISNUMBER(SEARCH("Pay Bill",C122)),"Pay Bill",IF(ISNUMBER(SEARCH("Spotify",C122)),"Pay Bill",IF(ISNUMBER(SEARCH("M-Shwari",C122)),"Mshwari",IF(ISNUMBER(SEARCH("Mshwari",C122)),"Mshwari",IF(ISNUMBER(SEARCH("Withdrawal charge",C122)),"Fees",IF(ISNUMBER(SEARCH("Customer Withdrawal",C122)),"Fees",IF(ISNUMBER(SEARCH("charge",C122)),"Fees","Other"))))))))))))))))))))))))) -> Bundles | R122: =TEXT(B122,"MMM YYYY") -> Jan 2026
A123: UA9A9398CJ | B123: 2026-01-09 13:55:02 | C123: Customer Bundle Purchase to 4093441SAFARICOM DATA BUNDLES by - 2547******109 NAOMI MUREITHI | D123: Completed | F123: 10 | G123: 3341 | L123: =IF(ISNUMBER(SEARCH("Bundle",C123)),"Bundles",IF(ISNUMBER(SEARCH("Airtime",C123)),"Bundles",IF(ISNUMBER(SEARCH("Merchant",C123)),"Merchant Payment",IF(ISNUMBER(SEARCH("Offnet C2B",C123)),"Merchant Payment",IF(ISNUMBER(SEARCH("Offnet B2C",C123)),"Merchant Payment",IF(ISNUMBER(SEARCH("Customer Payment to Small",C123)),"Merchant Payment",IF(ISNUMBER(SEARCH("Payment to Small Business",C123)),"Merchant Payment",IF(ISNUMBER(SEARCH("Sent to",C123)),"Sent to Person",IF(ISNUMBER(SEARCH("Customer Transfer to",C123)),"Sent to Person",IF(ISNUMBER(SEARCH("Business Payment",C123)),"Money In",IF(ISNUMBER(SEARCH("Funds Received",C123)),"Money In",IF(ISNUMBER(SEARCH("Receive International",C123)),"Money In",IF(ISNUMBER(SEARCH("Send Money Reversal",C123)),"Money In",IF(ISNUMBER(SEARCH("Pay Utility Reversal",C123)),"Money In",IF(ISNUMBER(SEARCH("Customer Transfer",C123)),"Money In",IF(ISNUMBER(SEARCH("Ziidi",C123)),"Investment",IF(ISNUMBER(SEARCH("Nabo",C123)),"Investment",IF(ISNUMBER(SEARCH("Paybill Online",C123)),"Pay Bill",IF(ISNUMBER(SEARCH("Pay Bill",C123)),"Pay Bill",IF(ISNUMBER(SEARCH("Spotify",C123)),"Pay Bill",IF(ISNUMBER(SEARCH("M-Shwari",C123)),"Mshwari",IF(ISNUMBER(SEARCH("Mshwari",C123)),"Mshwari",IF(ISNUMBER(SEARCH("Withdrawal charge",C123)),"Fees",IF(ISNUMBER(SEARCH("Customer Withdrawal",C123)),"Fees",IF(ISNUMBER(SEARCH("charge",C123)),"Fees","Other"))))))))))))))))))))))))) -> Bundles | R123: =TEXT(B123,"MMM YYYY") -> Jan 2026
A124: UA9A939SJG | B124: 2026-01-09 17:07:19 | C124: Customer Bundle Purchase to 826915Safaricom Offers by - 2547******109 NAOMI MUREITHI | D124: Completed | F124: 20 | G124: 3321 | L124: =IF(ISNUMBER(SEARCH("Bundle",C124)),"Bundles",IF(ISNUMBER(SEARCH("Airtime",C124)),"Bundles",IF(ISNUMBER(SEARCH("Merchant",C124)),"Merchant Payment",IF(ISNUMBER(SEARCH("Offnet C2B",C124)),"Merchant Payment",IF(ISNUMBER(SEARCH("Offnet B2C",C124)),"Merchant Payment",IF(ISNUMBER(SEARCH("Customer Payment to Small",C124)),"Merchant Payment",IF(ISNUMBER(SEARCH("Payment to Small Business",C124)),"Merchant Payment",IF(ISNUMBER(SEARCH("Sent to",C124)),"Sent to Person",IF(ISNUMBER(SEARCH("Customer Transfer to",C124)),"Sent to Person",IF(ISNUMBER(SEARCH("Business Payment",C124)),"Money In",IF(ISNUMBER(SEARCH("Funds Received",C124)),"Money In",IF(ISNUMBER(SEARCH("Receive International",C124)),"Money In",IF(ISNUMBER(SEARCH("Send Money Reversal",C124)),"Money In",IF(ISNUMBER(SEARCH("Pay Utility Reversal",C124)),"Money In",IF(ISNUMBER(SEARCH("Customer Transfer",C124)),"Money In",IF(ISNUMBER(SEARCH("Ziidi",C124)),"Investment",IF(ISNUMBER(SEARCH("Nabo",C124)),"Investment",IF(ISNUMBER(SEARCH("Paybill Online",C124)),"Pay Bill",IF(ISNUMBER(SEARCH("Pay Bill",C124)),"Pay Bill",IF(ISNUMBER(SEARCH("Spotify",C124)),"Pay Bill",IF(ISNUMBER(SEARCH("M-Shwari",C124)),"Mshwari",IF(ISNUMBER(SEARCH("Mshwari",C124)),"Mshwari",IF(ISNUMBER(SEARCH("Withdrawal charge",C124)),"Fees",IF(ISNUMBER(SEARCH("Customer Withdrawal",C124)),"Fees",IF(ISNUMBER(SEARCH("charge",C124)),"Fees","Other"))))))))))))))))))))))))) -> Bundles | R124: =TEXT(B124,"MMM YYYY") -> Jan 2026
A125: UA9A93A1L2 | B125: 2026-01-09 18:14:10 | C125: Customer Bundle Purchase to 4093441SAFARICOM DATA BUNDLES by - 2547******109 NAOMI MUREITHI | D125: Completed | F125: 10 | G125: 3311 | L125: =IF(ISNUMBER(SEARCH("Bundle",C125)),"Bundles",IF(ISNUMBER(SEARCH("Airtime",C125)),"Bundles",IF(ISNUMBER(SEARCH("Merchant",C125)),"Merchant Payment",IF(ISNUMBER(SEARCH("Offnet C2B",C125)),"Merchant Payment",IF(ISNUMBER(SEARCH("Offnet B2C",C125)),"Merchant Payment",IF(ISNUMBER(SEARCH("Customer Payment to Small",C125)),"Merchant Payment",IF(ISNUMBER(SEARCH("Payment to Small Business",C125)),"Merchant Payment",IF(ISNUMBER(SEARCH("Sent to",C125)),"Sent to Person",IF(ISNUMBER(SEARCH("Customer Transfer to",C125)),"Sent to Person",IF(ISNUMBER(SEARCH("Business Payment",C125)),"Money In",IF(ISNUMBER(SEARCH("Funds Received",C125)),"Money In",IF(ISNUMBER(SEARCH("Receive International",C125)),"Money In",IF(ISNUMBER(SEARCH("Send Money Reversal",C125)),"Money In",IF(ISNUMBER(SEARCH("Pay Utility Reversal",C125)),"Money In",IF(ISNUMBER(SEARCH("Customer Transfer",C125)),"Money In",IF(ISNUMBER(SEARCH("Ziidi",C125)),"Investment",IF(ISNUMBER(SEARCH("Nabo",C125)),"Investment",IF(ISNUMBER(SEARCH("Paybill Online",C125)),"Pay Bill",IF(ISNUMBER(SEARCH("Pay Bill",C125)),"Pay Bill",IF(ISNUMBER(SEARCH("Spotify",C125)),"Pay Bill",IF(ISNUMBER(SEARCH("M-Shwari",C125)),"Mshwari",IF(ISNUMBER(SEARCH("Mshwari",C125)),"Mshwari",IF(ISNUMBER(SEARCH("Withdrawal charge",C125)),"Fees",IF(ISNUMBER(SEARCH("Customer Withdrawal",C125)),"Fees",IF(ISNUMBER(SEARCH("charge",C125)),"Fees","Other"))))))))))))))))))))))))) -> Bundles | R125: =TEXT(B125,"MMM YYYY") -> Jan 2026
A126: UA9A93A06C | B126: 2026-01-09 18:17:00 | C126: Pay Bill Charge | D126: Completed | F126: 20 | G126: 3291 | L126: =IF(ISNUMBER(SEARCH("Bundle",C126)),"Bundles",IF(ISNUMBER(SEARCH("Airtime",C126)),"Bundles",IF(ISNUMBER(SEARCH("Merchant",C126)),"Merchant Payment",IF(ISNUMBER(SEARCH("Offnet C2B",C126)),"Merchant Payment",IF(ISNUMBER(SEARCH("Offnet B2C",C126)),"Merchant Payment",IF(ISNUMBER(SEARCH("Customer Payment to Small",C126)),"Merchant Payment",IF(ISNUMBER(SEARCH("Payment to Small Business",C126)),"Merchant Payment",IF(ISNUMBER(SEARCH("Sent to",C126)),"Sent to Person",IF(ISNUMBER(SEARCH("Customer Transfer to",C126)),"Sent to Person",IF(ISNUMBER(SEARCH("Business Payment",C126)),"Money In",IF(ISNUMBER(SEARCH("Funds Received",C126)),"Money In",IF(ISNUMBER(SEARCH("Receive International",C126)),"Money In",IF(ISNUMBER(SEARCH("Send Money Reversal",C126)),"Money In",IF(ISNUMBER(SEARCH("Pay Utility Reversal",C126)),"Money In",IF(ISNUMBER(SEARCH("Customer Transfer",C126)),"Money In",IF(ISNUMBER(SEARCH("Ziidi",C126)),"Investment",IF(ISNUMBER(SEARCH("Nabo",C126)),"Investment",IF(ISNUMBER(SEARCH("Paybill Online",C126)),"Pay Bill",IF(ISNUMBER(SEARCH("Pay Bill",C126)),"Pay Bill",IF(ISNUMBER(SEARCH("Spotify",C126)),"Pay Bill",IF(ISNUMBER(SEARCH("M-Shwari",C126)),"Mshwari",IF(ISNUMBER(SEARCH("Mshwari",C126)),"Mshwari",IF(ISNUMBER(SEARCH("Withdrawal charge",C126)),"Fees",IF(ISNUMBER(SEARCH("Customer Withdrawal",C126)),"Fees",IF(ISNUMBER(SEARCH("charge",C126)),"Fees","Other"))))))))))))))))))))))))) -> Pay Bill | R126: =TEXT(B126,"MMM YYYY") -> Jan 2026
...

Sheet Dashboard 
B2: M-PESA Financial Dashboard|Jan – May 2026
B4: Total Money In
C5: =SUM(Data!E:E) -> 165120.13
B6: Total Money Out | C6: =SUM(Data!F:F) -> 161561.22
B7: Net Position | C7: =C5-C6 -> 3558.91
B9: SPENDING BY CATEGORY
C10: =SUMIF(Data!L:L,"Bundles",Data!F:F) -> 11302
C11: =SUMIF(Data!L:L,"Merchant Payment",Data!F:F) -> 36852
C12: =SUMIF(Data!L:L,"Pay Bill",Data!F:F) -> 16212
C13: =SUMIF(Data!L:L,"Sent to Person",Data!F:F) -> 25295
C14: =SUMIF(Data!L:L,"Fees",Data!F:F) -> 1780
C15: =SUMIF(Data!L:L,"Mshwari",Data!F:F) -> 42300
C16: =SUMIF(Data!L:L,"Investment",Data!F:F) -> 27313.22
B17: MONTHLY BREAKDOWN | C17: Money In | D17: Money Out | E17: Net
B18: Jan 2026 | C18: =SUMIF(Data!R:R,B18,Data!E:E) -> 23948 | D18: =SUMIF(Data!R:R,B18,Data!F:F) -> 21552 | E18: =C18-D18 -> 2396
B19: Feb 2026 | C19: =SUMIF(Data!R:R,B19,Data!E:E) -> 49631 | D19: =SUMIF(Data!R:R,B19,Data!F:F) -> 47979 | E19: =C19-D19 -> 1652
B20: Mar 2026 | C20: =SUMIF(Data!R:R,B20,Data!E:E) -> 35435 | D20: =SUMIF(Data!R:R,B20,Data!F:F) -> 35418.22 | E20: =C20-D20 -> 16.78
B21: Apr 2026 | C21: =SUMIF(Data!R:R,B21,Data!E:E) -> 31579 | D21: =SUMIF(Data!R:R,B21,Data!F:F) -> 31669 | E21: =C21-D21 -> -90
B22: May 2026 | C22: =SUMIF(Data!R:R,B22,Data!E:E) -> 23720 | D22: =SUMIF(Data!R:R,B22,Data!F:F) -> 22867 | E22: =C22-D22 -> 853
B23: Jun 2026 | C23: =SUMIF(Data!R:R,B23,Data!E:E) -> 807.13 | D23: =SUMIF(Data!R:R,B23,Data!F:F) -> 2007
B24: Total Money | C24: =SUM(C18:C23) -> 165120.13 | D24: =SUM(D18:D23) -> 161492.22
